Workbook

Sheet products
A1: id | B1: published | C1: parent | D1: template | E1: article | G1: pagetitle | H1: description | I1: price | J1: made_in | K1: weight | L1: alias | M1: content | N1: menuindex | O1: market_image | P1: market_title | Q1: market_description | R1: pole1 | S1: pole2 | T1: pole3 | U1: pole4 | V1: pole5 | W1: brend | X1: koncern | Y1: chastota | Z1: original | AA1: sosok | AB1: number2 | AC1: images | AD1: remK | AE1: tipP | AF1: meta_keywords | AG1: meta_description
A2: 302522 | B2: 1 | C2: 8253 | D2: 20 | E2: 51839114 | F2: =VLOOKUP(E2,Лист1!A1:A306,1,FALSE) -> 51839114 | G2: Датчик давления в шине BH Sens ( Huf ) 51839114 для Fiat/Alfa/Chrysler/Dodge/Jeep | H2: Покупайте датчик давления в шине BH Sens ( Huf ) 51839114 для Fiat/Alfa/Chrysler/Dodge/Jeep по выгодным ценам | Большой выбор датчиков давления в шине | Осуществляем доставку на всей территории РФ | I2: 3250 | J2: Германия | K2: 30 | L2: dk-datchik-davlenia-v-shinah-51839114-8 | M2: <p>Датчик давления в шинах, номер по каталогу 51839114, передает сигналы с помощью радиоканала. Рабочая частота - 433МГц. Компания производитель <a href="https://alltpms.ru/proizvoditeli-sistem-tpms/beru"> BH Sens ( Huf ) </a>. Страна производства - Германия. Устройства предназначены для установки в колеса автомобилей, выпускаемых концерном Fiat/Alfa/Chrysler/Dodge/Jeep.</p><p></p><p> При условии установки на специализированных СТО, срок службы устройства составляет до 7 лет.</p><p>Конструктивные особенности данного датчика гарантируют его полную совместимость с системами авто концерна Fiat/Alfa/Chrysler/Dodge/Jeep. Датчик поставляется в комплекте с ниппелем, что заметно облегчает установку и не требует покупки дополнительных деталей. Материал ниппеля - металл. После установки датчик 51839114 требует привязки к авто. Привязка производится по методике <a href="https://alltpms.ru/katalog/privyazka/privyazka-4">«Автоматическая привязка»</a> (Карточка привязки).</p> | N2: 78 | O2: /market/HUF1410.jpg | P2: Датчик давления в шине BH Sens ( Huf ) 51839114 для Fiat/Alfa/Chrysler/Dodge/Jeep | Q2: Датчик давления в шине BH Sens ( Huf ) 51839114 для Fiat/Alfa/Chrysler/Dodge/Jeep | R2: Доставка от 1 шт. без предоплаты, Гарантия 2 года | S2: 0 | T2: 1 | U2: 51839114-8 | V2: 5054208002059 | W2: 622 | X2: Fiat/Alfa/Chrysler/Dodge/Jeep | Y2: 433 | Z2: no | AA2: Clamp-in | AB2: 4054, TX-S138, TPS0138, 9014-4054, 9015-4054, 1210-4054, 2210-4054, 2200-4054, 1400-4054, 1401-4054, 4040-4054, 4041-4054, 590914-4054, 590918-4054, 4054PFR, 4054PFM, 4054PVM | AC2: HUF1400-1.JPG||HUF1400-2.JPG||HUF1400-3.JPG||HUF1400-4.JPG||HUF1400-5.JPG||HUF1400-6.JPG||HUF1400-7.JPG||HUF1400-8.JPG||HUF1400-9.JPG||HUF1400-10.JPG | AD2: 229||92867||241||244||48032 | AE2: 586 | AG2: Покупайте датчик давления в шине BH Sens ( Huf ) 51839114 для Fiat/Alfa/Chrysler/Dodge/Jeep по выгодным ценам | Большой выбор датчиков давления в шине | Осуществляем доставку на всей территории РФ
A3: 302529 | B3: 1 | C3: 8253 | D3: 20 | E3: 36106874829 | F3: =VLOOKUP(E3,Лист1!A1:A306,1,FALSE) -> 36106874829 | G3: Датчик давления в шине для BMW 36106874829 Оригинал | H3: Купить по низкой цене оригинальный датчик давления в шинах для BMW 36106874829 с доставкой по Москве или России. | I3: 8250 | J3: Германия | K3: 30 | L3: dk-datchik-davlenia-v-shinah-36106790054-20 | M3: <p>Датчик, каталожный номер 36106874829. Передача данных производится посредством радиосигнала. Частота работы - 433МГц. Для автомобилей BMW. Страна-производитель - Германия.</p><p> Срок службы устройства варьируется и может достигать 7 лет. Данный показатель во многом зависит от интенсивности использования авто и условий его эксплуатации.</p><p> Конструктивные особенности датчика позволяют использовать его на большинстве марок авто производства BMW. Комплект поставки – датчик и ниппель. Материал ниппеля - металл. Комплект полностью готов к установке. Данный датчик, номер 36106874829 требует привязки к системе автомобиля. Для этого используется процедура <a href="https://alltpms.ru/katalog/privyazka/privyazka-4">«Автоматизированная привязка»</a> (Карточка привязки).</p> | N3: 80 | O3: /market/BMW829.jpg | P3: Датчик давления в шине для BMW 36106874829 Оригинал | Q3: Датчик давления в шине для BMW 36106874829 Оригинал | R3: Доставка от 1 шт. без предоплаты, Гарантия 2 года | S3: 0 | T3: 0 | U3: 36106790054-20 | V3: 5054208002066 | W3: 622 | X3: BMW | Y3: 433 | Z3: yes | AA3: Clamp-in | AB3: 36106790054, 36106856227, 4010, 550-1912, TX-S005L/R, TPS0005L/R, ECR0010, RDE012V21, 9014-4010, 9015-4010, 1210-4010, 2210-4010, 2200-4010, 1400-4010, 1401-4010, 4040-4010, 4041-4010, 590914-4010, 590918-4010, 4010PFR, 4010PFM, 4010PVM, 4040-RDE012, 4041-RDE012, RDE012PVM, RDE012PFR, RDE012PVM, RDE012PFR | AC3: 36106790054-1.JPG||36106790054-2.JPG||36106790054-3.JPG||36106790054-4.JPG||36106790054-5.JPG||36106790054-6.JPG||36106790054-7.JPG||36106790054-8.JPG||36106790054-9.JPG||36106790054-10.JPG | AD3: 229||92867||241||244||48032 | AE3: 588 | AF3: BMW BH Sens ( Huf ) 36106874829 36106790054, 36106856227, 4010, 550-1912, TX-S005L/R, TPS0005L/R, ECR0010, RDE012V21, 9014-4010, 9015-4010, 1210-4010, 2210-4010, 2200-4010, 1400-4010, 1401-4010, 4040-4010, 4041-4010, 590914-4010, 590918-4010, 4010PFR, 4010PFM, 4010PVM, 4040-RDE012, 4041-RDE012, RDE012PVM, RDE012PFR, RDE012PVM, RDE012PFR 36106790054, 36106856227, 4010, 5501912, TXS005L/R, TPS0005L/R, ECR0010, RDE012V21, 90144010, 90154010, 12104010, 22104010, 22004010, 14004010, 14014010, 40404010, 40414010, 5909144010, 5909184010, 4010PFR, 4010PFM, 4010PVM, 4040RDE012, 4041RDE012, RDE012PVM, RDE012PFR, RDE012PVM, RDE012PFR Оригинал | AG3: Купить оригинальный датчик давления в шине для BMW 36106874829 в Москве с доставкой. Цена от производителя. Большой выбор датчиков. Гарантия.
A4: 302530 | B4: 1 | C4: 8253 | D4: 20 | E4: 36106874829 | F4: =VLOOKUP(E4,Лист1!A1:A306,1,FALSE) -> 36106874829 | G4: Датчик давления в шине BH Sens ( Huf ) 36106874829 для BMW (Black Edition) | H4: Покупайте датчик давления в шине BH Sens ( Huf ) 36106874829 для BMW (Black Edition) по выгодным ценам | Большой выбор датчиков давления в шине | Осуществляем доставку на всей территории РФ | I4: 4250 | J4: Германия | K4: 30 | L4: dk-datchik-davlenia-v-shinah-36106790054b-29 | M4: <p>Датчик, номер по каталогу запчастей 36106874829. Предназначен для контроля давления в шинах. Передача данных осуществляется посредством радиосигнала на частоте 433МГц. Компания производитель датчика - <a href="https://alltpms.ru/proizvoditeli-sistem-tpms/beru"> BH Sens ( Huf ) </a>. Место производства - Германия.</p><p>Правильно установленный датчик гарантировано проработает 7 лет. В каждом конкретном случае срок службы может изменяться. Он зависит от условий эксплуатации, длительности поездок, их частоты.</p><p>Предназначенный для установки в колеса автомобилей большинства моделей концерна BMW, датчик поставляется в комплекте с ниппелем. Покупатель получает комплектное устройство. После установки датчик 36106874829 активируется, используется метод <a href="https://alltpms.ru/katalog/privyazka/privyazka-4">«Автоматизированная привязка»</a> (Карточка привязки).</p> | N4: 82 | O4: /market/HUF4040B.jpg | P4: Датчик давления в шине BH Sens ( Huf ) 36106874829 для BMW (Black Edition) | Q4: Датчик давления в шине BH Sens ( Huf ) 36106874829 для BMW (Black Edition) | R4: Доставка от 1 шт. без предоплаты, Гарантия 2 года | S4: 0 | T4: 1 | U4: 36106790054b-29 | V4: 5054208002067 | W4: 622 | X4: BMW | Y4: 433 | Z4: no | AA4: Clamp-in | AB4: 36106790054, 36106856227, 4010, 550-1912, TX-S005L/R, TPS0005L/R, ECR0010, RDE012V21, 9014-4010, 9015-4010, 1210-4010, 2210-4010, 2200-4010, 1400-4010, 1401-4010, 4040-4010, 4041-4010, 590914-4010, 590918-4010, 4010PFR, 4010PFM, 4010PVM, 4040-RDE012, 4041-RDE012, RDE012PVM, RDE012PFR, RDE012PVM, RDE012PFR | AC4: HUF4040_B-1.JPG||HUF4040_B-2.JPG||HUF4040_B-3.JPG||HUF4040_B-4.JPG||HUF4040_B-5.JPG||HUF4040_B-6.JPG||HUF4040_B-7.JPG||HUF4040_B-8.JPG||HUF4040_B-9.JPG||HUF4040_B-10.JPG | AD4: 229||92867||241||244||48032 | AE4: 588 | AG4: Покупайте датчик давления в шине BH Sens ( Huf ) 36106874829 для BMW (Black Edition) по выгодным ценам | Большой выбор датчиков давления в шине | Осуществляем доставку на всей территории РФ
A5: 302531 | B5: 1 | C5: 8253 | D5: 20 | E5: 36106874829 | F5: =VLOOKUP(E5,Лист1!A1:A306,1,FALSE) -> 36106874829 | G5: Датчик давления в шине BH Sens (Huf, Германия) 36106874829 для BMW (Black Edition) | H5: Покупайте датчик давления в шине BH Sens (Huf, Германия) 36106874829 для BMW (Black Edition) по выгодным ценам | Большой выбор датчиков давления в шине | Осуществляем доставку на всей территории РФ | I5: 3750 | J5: Германия | K5: 30 | L5: dk-datchik-davlenia-v-shinah-36106790054b-19 | M5: <p>Датчик, номер по каталогу запчастей 36106874829. Предназначен для контроля давления в шинах. Передача данных осуществляется посредством радиосигнала на частоте 433МГц. Компания производитель датчика - <a href="https://alltpms.ru/proizvoditeli-sistem-tpms/beru"> BH Sens ( Huf ) </a>. Место производства - Германия.</p><p>Правильно установленный датчик гарантировано проработает 7 лет. В каждом конкретном случае срок службы может изменяться. Он зависит от условий эксплуатации, длительности поездок, их частоты.</p><p>Предназначенный для установки в колеса автомобилей большинства моделей концерна BMW, датчик поставляется в комплекте с ниппелем. Покупатель получает комплектное устройство. После установки датчик 36106874829 активируется, используется метод <a href="https://alltpms.ru/katalog/privyazka/privyazka-4">«Автоматизированная привязка»</a> (Карточка привязки).</p> | N5: 83 | O5: /market/HUF1410B.jpg | P5: Датчик давления в шине BH Sens ( Huf ) 36106874829 для BMW (Black Edition) | Q5: Датчик давления в шине BH Sens ( Huf ) 36106874829 для BMW (Black Edition) | R5: Доставка от 1 шт. без предоплаты, Гарантия 2 года | S5: 0 | T5: 1 | U5: 36106790054b-19 | V5: 5054208002068 | W5: 622 | X5: BMW | Y5: 433 | Z5: no | AA5: Clamp-in | AB5: 36106790054, 36106856227, 4010, 550-1912, TX-S005L/R, TPS0005L/R, ECR0010, RDE012V21, 9014-4010, 9015-4010, 1210-4010, 2210-4010, 2200-4010, 1400-4010, 1401-4010, 4040-4010, 4041-4010, 590914-4010, 590918-4010, 4010PFR, 4010PFM, 4010PVM, 4040-RDE012, 4041-RDE012, RDE012PVM, RDE012PFR, RDE012PVM, RDE012PFR | AC5: HUF1400_B-1.JPG||HUF1400_B-2.JPG||HUF1400_B-3.JPG||HUF1400_B-4.JPG||HUF1400_B-5.JPG||HUF1400_B-6.JPG||HUF1400_B-7.JPG||HUF1400_B-8.JPG||HUF1400_B-9.JPG||HUF1400_B-10.JPG | AD5: 229||92867||241||244||48032 | AE5: 588 | AG5: Покупайте датчик давления в шине BH Sens (Huf, Германия) 36106874829 для BMW (Black Edition) по выгодным ценам | Большой выбор датчиков давления в шине | Осуществляем доставку на всей территории РФ
A6: 302532 | B6: 1 | C6: 8253 | D6: 20 | E6: 36106874829 | F6: =VLOOKUP(E6,Лист1!A1:A306,1,FALSE) -> 36106874829 | G6: Датчик давления в шине BH Sens ( Huf ) 36106874829 для BMW | H6: Покупайте датчик давления в шине BH Sens ( Huf ) 36106874829 для BMW по выгодным ценам | Большой выбор датчиков давления в шине | Осуществляем доставку на всей территории РФ | I6: 3750 | J6: Германия | K6: 30 | L6: dk-datchik-davlenia-v-shinah-36106790054-29 | M6: <p>Датчик, номер по каталогу запчастей 36106874829. Предназначен для контроля давления в шинах. Передача данных осуществляется посредством радиосигнала на частоте 433МГц. Компания производитель датчика - <a href="https://alltpms.ru/proizvoditeli-sistem-tpms/beru"> BH Sens ( Huf ) </a>. Место производства - Германия.</p><p>Правильно установленный датчик гарантировано проработает 7 лет. В каждом конкретном случае срок службы может изменяться. Он зависит от условий эксплуатации, длительности поездок, их частоты.</p><p>Предназначенный для установки в колеса автомобилей большинства моделей концерна BMW, датчик поставляется в комплекте с ниппелем. Покупатель получает комплектное устройство. После установки датчик 36106874829 активируется, используется метод <a href="https://alltpms.ru/katalog/privyazka/privyazka-4">«Автоматизированная привязка»</a> (Карточка привязки).</p> | N6: 81 | O6: /market/HUF4040.jpg | P6: Датчик давления в шине BH Sens ( Huf ) 36106874829 для BMW | Q6: Датчик давления в шине BH Sens ( Huf ) 36106874829 для BMW | R6: Доставка от 1 шт. без предоплаты, Гарантия 2 года | S6: 0 | T6: 1 | U6: 36106790054-29 | V6: 5054208002069 | W6: 622 | X6: BMW | Y6: 433 | Z6: no | AA6: Clamp-in | AB6: 36106790054, 36106856227, 4010, 550-1912, TX-S005L/R, TPS0005L/R, ECR0010, RDE012V21, 9014-4010, 9015-4010, 1210-4010, 2210-4010, 2200-4010, 1400-4010, 1401-4010, 4040-4010, 4041-4010, 590914-4010, 590918-4010, 4010PFR, 4010PFM, 4010PVM, 4040-RDE012, 4041-RDE012, RDE012PVM, RDE012PFR, RDE012PVM, RDE012PFR | AC6: HUF4040-1.JPG||HUF4040-2.JPG||HUF4040-3.JPG||HUF4040-4.JPG||HUF4040-5.JPG||HUF4040-6.JPG||HUF4040-7.JPG||HUF4040-8.JPG||HUF4040-9.JPG||HUF4040-10.JPG | AD6: 229||92867||241||244||48032 | AE6: 588 | AG6: Покупайте датчик давления в шине BH Sens ( Huf ) 36106874829 для BMW по выгодным ценам | Большой выбор датчиков давления в шине | Осуществляем доставку на всей территории РФ
A7: 302533 | B7: 1 | C7: 8253 | D7: 20 | E7: 36106874829 | F7: =VLOOKUP(E7,Лист1!A1:A306,1,FALSE) -> 36106874829 | G7: Датчик давления в шине BH Sens (Huf, Германия) 36106874829 для BMW | H7: Покупайте датчик давления в шине BH Sens (Huf, Германия) 36106874829 для BMW по выгодным ценам | Большой выбор датчиков давления в шине | Осуществляем доставку на всей территории РФ | I7: 3250 | J7: Германия | K7: 30 | L7: dk-datchik-davlenia-v-shinah-36106790054-219 | M7: <p> Датчик давления в шинах. Предназначен для автомобилей BMW. Каталожный номер запчасти 36106874829. Компания производитель - <a href="https://alltpms.ru/proizvoditeli-sistem-tpms/beru"> BH Sens ( Huf ) </a>, Германия.</p><p></p><p>При условии соблюдения правил установки и эксплуатации, срок службы датчика варьируется в пределах от 7 до 8 лет. Срок нормальной работы зависит от условий эксплуатации.</p><p>Данный датчик полностью совместим с большинством моделей автомобилей концерна BMW. В продажу поступает комплект (датчик и ниппель). После установки требуется произвести привязку и активацию. Данные процедуры выполняются по методу <a href="https://alltpms.ru/katalog/privyazka/privyazka-4">«Автоматизированная привязка»</a> (Карточка привязки).</p> | N7: 84 | O7: /market/HUF1410.jpg | P7: Датчик давления в шине BH Sens ( Huf ) 36106874829 для BMW | Q7: Датчик давления в шине BH Sens ( Huf ) 36106874829 для BMW | R7: Доставка от 1 шт. без предоплаты, Гарантия 2 года | S7: 0 | T7: 1 | U7: 36106790054-219 | V7: 5054208002070 | W7: 622 | X7: BMW | Y7: 433 | Z7: no | AA7: Clamp-in | AB7: 36106790054, 36106856227, 4010, 550-1912, TX-S005L/R, TPS0005L/R, ECR0010, RDE012V21, 9014-4010, 9015-4010, 1210-4010, 2210-4010, 2200-4010, 1400-4010, 1401-4010, 4040-4010, 4041-4010, 590914-4010, 590918-4010, 4010PFR, 4010PFM, 4010PVM, 4040-RDE012, 4041-RDE012, RDE012PVM, RDE012PFR, RDE012PVM, RDE012PFR | AC7: HUF1400-1.JPG||HUF1400-2.JPG||HUF1400-3.JPG||HUF1400-4.JPG||HUF1400-5.JPG||HUF1400-6.JPG||HUF1400-7.JPG||HUF1400-8.JPG||HUF1400-9.JPG||HUF1400-10.JPG | AD7: 229||92867||241||244||48032 | AE7: 588 | AG7: Покупайте датчик давления в шине BH Sens (Huf, Германия) 36106874829 для BMW по выгодным ценам | Большой выбор датчиков давления в шине | Осуществляем доставку на всей территории РФ
A8: 302534 | B8: 1 | C8: 8253 | D8: 20 | E8: 36106877937 | F8: =VLOOKUP(E8,Лист1!A1:A306,1,FALSE) -> 36106877937 | G8: Датчик давления в шине для BMW 36106877937 Оригинал | H8: Купить по низкой цене оригинальный датчик давления в шинах для 36106877937 для BMW с доставкой по Москве или России. | I8: 7500 | J8: Германия | K8: 30 | L8: dk-datchik-davlenia-v-shinah-36106877937-150 | M8: <p>Датчик давления в шинах, номер по каталогу 36106877937, передает сигналы с помощью радиоканала. Рабочая частота - 433МГц. Компания производитель автомобиля BMW. Страна производства - Германия. Устройства предназначены для установки в колеса автомобилей, выпускаемых концерном BMW.</p><p></p><p> При условии установки на специализированных СТО, срок службы устройства составляет до 7 лет.</p><p>Конструктивные особенности данного датчика гарантируют его полную совместимость с системами авто концерна BMW. Датчик поставляется в комплекте с ниппелем, что заметно облегчает установку и не требует покупки дополнительных деталей. Материал ниппеля - металл. После установки датчик 36106877937 требует привязки к авто. Привязка производится по методике <a href="https://alltpms.ru/katalog/privyazka/privyazka-4">«Автоматизированная привязка»</a> (Карточка привязки).</p> | N8: 93 | O8: /market/A4104.jpg | P8: Датчик давления в шине для BMW 36106877937 Оригинал | Q8: Датчик давления в шине для BMW 36106877937 Оригинал | R8: Доставка от 1 шт. без предоплаты, Гарантия 2 года | S8: 0 | T8: 0 | U8: 36106877937-150 | V8: 5054208002071 | W8: 622 | X8: BMW | Y8: 433 | Z8: yes | AA8: Clamp-in | AB8: A0009054104, 36106872774, 36106872803, 36106876955, 36106876957, 36106876957, 36106887147, A0009052102, A0009057205, 3057, A0009058706, 28238, S180211005Z, ECR0280, RDE077V21, RDE035V21, 9014-3057, 9015-3057, 1210-3057, 2210-3057, 2200-3057, 1400-3057, 1401-3057, 4040-3057, 4041-3057, 590914-3057, 590918-3057, 1900-28238, 2901-28238, 4040-28238, 4041-28238, 1400-28238, 1401-28238, 590914-28238, 590918-28238, 3057PFR, 3057PFM, 3057PVM, 28238PVM, 28238PFR, 4040-RDE077, 4041-RDE077, RDE077PVM, RDE077PFR, RDE077PVM, RDE077PFR | AC8: 36106877937-1.JPG||36106877937-2.JPG||36106877937-3.JPG||36106877937-4.JPG||36106877937-5.JPG||36106877937-6.JPG||36106877937-7.JPG||36106877937-8.JPG||36106877937-9.JPG||36106877937-10.JPG | AD8: 229||92867||241||244||48032 | AE8: 588 | AF8: BMW BH Sens ( Huf ) 36106877937 A0009054104, 36106872774, 36106872803, 36106876955, 36106876957, 36106876957, 36106887147, A0009052102, A0009057205, 3057, A0009058706, 28238, S180211005Z, ECR0280, RDE077V21, RDE035V21, 9014-3057, 9015-3057, 1210-3057, 2210-3057, 2200-3057, 1400-3057, 1401-3057, 4040-3057, 4041-3057, 590914-3057, 590918-3057, 1900-28238, 2901-28238, 4040-28238, 4041-28238, 1400-28238, 1401-28238, 590914-28238, 590918-28238, 3057PFR, 3057PFM, 3057PVM, 28238PVM, 28238PFR, 4040-RDE077, 4041-RDE077, RDE077PVM, RDE077PFR, RDE077PVM, RDE077PFR A0009054104, 36106872774, 36106872803, 36106876955, 36106876957, 36106876957, 36106887147, A0009052102, A0009057205, 3057, A0009058706, 28238, S180211005Z, ECR0280, RDE077V21, RDE035V21, 90143057, 90153057, 12103057, 22103057, 22003057, 14003057, 14013057, 40403057, 40413057, 5909143057, 5909183057, 190028238, 290128238, 404028238, 404128238, 140028238, 140128238, 59091428238, 59091828238, 3057PFR, 3057PFM, 3057PVM, 28238PVM, 28238PFR, 4040RDE077, 4041RDE077, RDE077PVM, RDE077PFR, RDE077PVM, RDE077PFR Оригинал | AG8: Купить оригинальный датчик давления в шине для BMW 36106877937 в Москве с доставкой. Цена от производителя. Большой выбор датчиков. Гарантия.
A9: 302535 | B9: 1 | C9: 8253 | D9: 20 | E9: 36106877937 | F9: =VLOOKUP(E9,Лист1!A1:A306,1,FALSE) -> 36106877937 | G9: Датчик давления в шине BH Sens ( Huf ) 36106877937 для BMW (Black Edition) | H9: Покупайте датчик давления в шине BH Sens ( Huf ) 36106877937 для BMW (Black Edition) по выгодным ценам | Большой выбор датчиков давления в шине | Осуществляем доставку на всей территории РФ | I9: 5000 | J9: Германия | K9: 30 | L9: dk-datchik-davlenia-v-shinah-36106877937b-146n | M9: <p>Датчик давления в шинах, номер по каталогу 36106877937, передает сигналы с помощью радиоканала. Рабочая частота - 433МГц. Компания производитель <a href="https://alltpms.ru/proizvoditeli-sistem-tpms/beru"> BH Sens ( Huf ) </a>. Страна производства - Германия. Устройства предназначены для установки в колеса автомобилей, выпускаемых концерном BMW.</p><p></p><p> При условии установки на специализированных СТО, срок службы устройства составляет до 7 лет.</p><p>Конструктивные особенности данного датчика гарантируют его полную совместимость с системами авто концерна BMW. Датчик поставляется в комплекте с ниппелем, что заметно облегчает установку и не требует покупки дополнительных деталей. Материал ниппеля - металл. После установки датчик 36106877937 требует привязки к авто. Привязка производится по методике <a href="https://alltpms.ru/katalog/privyazka/privyazka-4">«Автоматизированная привязка»</a> (Карточка привязки).</p> | N9: 91 | O9: /market/RDE077B.jpg | P9: Датчик давления в шине BH Sens ( Huf ) 36106877937 для BMW (Black Edition) | Q9: Датчик давления в шине BH Sens ( Huf ) 36106877937 для BMW (Black Edition) | R9: Доставка от 1 шт. без предоплаты, Гарантия 2 года | S9: 0 | T9: 0 | U9: 36106877937b-146n | V9: 5054208002072 | W9: 622 | X9: BMW | Y9: 433 | Z9: no | AA9: Clamp-in | AB9: A0009054104, 36106872774, 36106872803, 36106876955, 36106876957, 36106876957, 36106887147, A0009052102, A0009057205, 3057, A0009058706, 28238, S180211005Z, ECR0280, RDE077V21, RDE035V21, 9014-3057, 9015-3057, 1210-3057, 2210-3057, 2200-3057, 1400-3057, 1401-3057, 4040-3057, 4041-3057, 590914-3057, 590918-3057, 1900-28238, 2901-28238, 4040-28238, 4041-28238, 1400-28238, 1401-28238, 590914-28238, 590918-28238, 3057PFR, 3057PFM, 3057PVM, 28238PVM, 28238PFR, 4040-RDE077, 4041-RDE077, RDE077PVM, RDE077PFR, RDE077PVM, RDE077PFR | AC9: RDE077V21_B-1.JPG||RDE077V21_B-2.JPG||RDE077V21_B-3.JPG||RDE077V21_B-4.JPG||RDE077V21_B-5.JPG||RDE077V21_B-6.JPG||RDE077V21_B-7.JPG||RDE077V21_B-8.JPG||RDE077V21_B-9.JPG||RDE077V21_B-10.JPG | AD9: 229||92867||241||244||48032 | AE9: 588 | AG9: Покупайте датчик давления в шине BH Sens ( Huf ) 36106877937 для BMW (Black Edition) по выгодным ценам | Большой выбор датчиков давления в шине | Осуществляем доставку на всей территории РФ
A10: 302536 | B10: 1 | C10: 8253 | D10: 20 | E10: 36106877937 | F10: =VLOOKUP(E10,Лист1!A1:A306,1,FALSE) -> 36106877937 | G10: Датчик давления в шине BH Sens ( Huf, Германия) 36106877937 для BMW (Black Edition) | H10: Покупайте датчик давления в шине BH Sens ( Huf, Германия) 36106877937 для BMW (Black Edition) по выгодным ценам | Большой выбор датчиков давления в шине | Осуществляем доставку на всей территории РФ | I10: 3750 | J10: Германия | K10: 30 | L10: dk-datchik-davlenia-v-shinah-36106877937b-1477 | M10: <p>Датчик давления в шинах, номер по каталогу 36106877937, передает сигналы с помощью радиоканала. Рабочая частота - 433МГц. Компания производитель <a href="https://alltpms.ru/proizvoditeli-sistem-tpms/beru"> BH Sens ( Huf ) </a>. Страна производства - Германия. Устройства предназначены для установки в колеса автомобилей, выпускаемых концерном BMW.</p><p></p><p> При условии установки на специализированных СТО, срок службы устройства составляет до 7 лет.</p><p>Конструктивные особенности данного датчика гарантируют его полную совместимость с системами авто концерна BMW. Датчик поставляется в комплекте с ниппелем, что заметно облегчает установку и не требует покупки дополнительных деталей. Материал ниппеля - металл. После установки датчик 36106877937 требует привязки к авто. Привязка производится по методике <a href="https://alltpms.ru/katalog/privyazka/privyazka-4">«Автоматизированная привязка»</a> (Карточка привязки).</p> | N10: 92 | O10: /market/HUF1410B.jpg | P10: Датчик давления в шине BH Sens ( Huf ) 36106877937 для BMW (Black Edition) | Q10: Датчик давления в шине BH Sens ( Huf ) 36106877937 для BMW (Black Edition) | R10: Доставка от 1 шт. без предоплаты, Гарантия 2 года | S10: 0 | T10: 1 | U10: 36106877937b-1477 | V10: 5054208002073 | W10: 622 | X10: BMW | Y10: 433 | Z10: no | AA10: Clamp-in | AB10: A0009054104, 36106872774, 36106872803, 36106876955, 36106876957, 36106876957, 36106887147, A0009052102, A0009057205, 3057, A0009058706, 28238, S180211005Z, ECR0280, RDE077V21, RDE035V21, 9014-3057, 9015-3057, 1210-3057, 2210-3057, 2200-3057, 1400-3057, 1401-3057, 4040-3057, 4041-3057, 590914-3057, 590918-3057, 1900-28238, 2901-28238, 4040-28238, 4041-28238, 1400-28238, 1401-28238, 590914-28238, 590918-28238, 3057PFR, 3057PFM, 3057PVM, 28238PVM, 28238PFR, 4040-RDE077, 4041-RDE077, RDE077PVM, RDE077PFR, RDE077PVM, RDE077PFR | AC10: HUF1400_B-1.JPG||HUF1400_B-2.JPG||HUF1400_B-3.JPG||HUF1400_B-4.JPG||HUF1400_B-5.JPG||HUF1400_B-6.JPG||HUF1400_B-7.JPG||HUF1400_B-8.JPG||HUF1400_B-9.JPG||HUF1400_B-10.JPG | AD10: 229||92867||241||244||48032 | AE10: 588 | AG10: Покупайте датчик давления в шине BH Sens ( Huf, Германия) 36106877937 для BMW (Black Edition) по выгодным ценам | Большой выбор датчиков давления в шине | Осуществляем доставку на всей территории РФ
A11: 302537 | B11: 1 | C11: 8253 | D11: 20 | E11: 36106877937 | F11: =VLOOKUP(E11,Лист1!A1:A306,1,FALSE) -> 36106877937 | G11: Датчик давления в шине BH Sens ( Huf ) 36106877937 для BMW | H11: Покупайте датчик давления в шине BH Sens ( Huf ) 36106877937 для BMW по выгодным ценам | Большой выбор датчиков давления в шине | Осуществляем доставку на всей территории РФ | I11: 4500 | J11: Германия | K11: 30 | L11: dk-datchik-davlenia-v-shinah-36106877937-146 | M11: <p>Датчик давления в шинах, номер по каталогу 36106877937, передает сигналы с помощью радиоканала. Рабочая частота - 433МГц. Компания производитель <a href="https://alltpms.ru/proizvoditeli-sistem-tpms/beru"> BH Sens ( Huf ) </a>. Страна производства - Германия. Устройства предназначены для установки в колеса автомобилей, выпускаемых концерном BMW.</p><p></p><p> При условии установки на специализированных СТО, срок службы устройства составляет до 7 лет.</p><p>Конструктивные особенности данного датчика гарантируют его полную совместимость с системами авто концерна BMW. Датчик поставляется в комплекте с ниппелем, что заметно облегчает установку и не требует покупки дополнительных деталей. Материал ниппеля - металл. После установки датчик 36106877937 требует привязки к авто. Привязка производится по методике <a href="https://alltpms.ru/katalog/privyazka/privyazka-4">«Автоматизированная привязка»</a> (Карточка привязки).</p> | N11: 95 | O11: /market/RDE077.jpg | P11: Датчик давления в шине BH Sens ( Huf ) 36106877937 для BMW | Q11: Датчик давления в шине BH Sens ( Huf ) 36106877937 для BMW | R11: Доставка от 1 шт. без предоплаты, Гарантия 2 года | S11: 0 | T11: 0 | U11: 36106877937-146 | V11: 5054208002074 | W11: 622 | X11: BMW | Y11: 433 | Z11: no | AA11: Clamp-in | AB11: A0009054104, 36106872774, 36106872803, 36106876955, 36106876957, 36106876957, 36106887147, A0009052102, A0009057205, 3057, A0009058706, 28238, S180211005Z, ECR0280, RDE077V21, RDE035V21, 9014-3057, 9015-3057, 1210-3057, 2210-3057, 2200-3057, 1400-3057, 1401-3057, 4040-3057, 4041-3057, 590914-3057, 590918-3057, 1900-28238, 2901-28238, 4040-28238, 4041-28238, 1400-28238, 1401-28238, 590914-28238, 590918-28238, 3057PFR, 3057PFM, 3057PVM, 28238PVM, 28238PFR, 4040-RDE077, 4041-RDE077, RDE077PVM, RDE077PFR, RDE077PVM, RDE077PFR | AC11: RDE077V21-1.JPG||RDE077V21-2.JPG||RDE077V21-3.JPG||RDE077V21-4.JPG||RDE077V21-5.JPG||RDE077V21-6.JPG||RDE077V21-7.JPG||RDE077V21-8.JPG||RDE077V21-9.JPG||RDE077V21-10.JPG | AD11: 229||92867||241||244||48032 | AE11: 588 | AG11: Покупайте датчик давления в шине BH Sens ( Huf ) 36106877937 для BMW по выгодным ценам | Большой выбор датчиков давления в шине | Осуществляем доставку на всей территории РФ
A12: 302538 | B12: 1 | C12: 8253 | D12: 20 | E12: 36106877937 | F12: =VLOOKUP(E12,Лист1!A1:A306,1,FALSE) -> 36106877937 | G12: Датчик давления в шине BH Sens ( Huf ) 36106877937 для BMW (БМВ) | H12: Покупайте датчик давления в шине BH Sens ( Huf ) 36106877937 для BMW (БМВ) по выгодным ценам | Большой выбор датчиков давления в шине | Осуществляем доставку на всей территории РФ | I12: 3250 | J12: Германия | K12: 30 | L12: dk-datchik-davlenia-v-shinah-36106877937-146n | M12: <p>Датчик TPMS производства компании <a href="https://alltpms.ru/proizvoditeli-sistem-tpms/beru"> BH Sens ( Huf ) </a>. Страна изготовления - Германия. Номер по каталогу 36106877937. Датчик специально разработан для автомобилей BMW.</p><p></p><p>В случае правильной эксплуатации срок службы устройства может достигать 8 лет. Данный показатель варьируется в достаточно широких пределах и зависит от условий эксплуатации автомобиля.</p><p>Выпускаемый компанией <a href="https://alltpms.ru/proizvoditeli-sistem-tpms/beru"> BH Sens ( Huf ) </a> Германия, датчик номер 36106877937 устанавливается на автомобили, производства BMW. Покупатель получает полный комплект для установки. Привязка датчика к автомобилю выполняется по методу <a href="https://alltpms.ru/katalog/privyazka/privyazka-4">«Автоматизированная привязка»</a> (Карточка привязки).</p> | N12: 94 | O12: /market/HUF1410.jpg | P12: Датчик давления в шине BH Sens ( Huf ) 36106877937 для BMW | Q12: Датчик давления в шине BH Sens ( Huf ) 36106877937 для BMW | R12: Доставка от 1 шт. без предоплаты, Гарантия 2 года | S12: 0 | T12: 1 | U12: 36106877937-146n | V12: 5054208002075 | W12: 622 | X12: BMW | Y12: 433 | Z12: no | AA12: Clamp-in | AB12: A0009054104, 36106872774, 36106872803, 36106876955, 36106876957, 36106876957, 36106887147, A0009052102, A0009057205, 3057, A0009058706, 28238, S180211005Z, ECR0280, RDE077V21, RDE035V21, 9014-3057, 9015-3057, 1210-3057, 2210-3057, 2200-3057, 1400-3057, 1401-3057, 4040-3057, 4041-3057, 590914-3057, 590918-3057, 1900-28238, 2901-28238, 4040-28238, 4041-28238, 1400-28238, 1401-28238, 590914-28238, 590918-28238, 3057PFR, 3057PFM, 3057PVM, 28238PVM, 28238PFR, 4040-RDE077, 4041-RDE077, RDE077PVM, RDE077PFR, RDE077PVM, RDE077PFR | AC12: HUF1400-1.JPG||HUF1400-2.JPG||HUF1400-3.JPG||HUF1400-4.JPG||HUF1400-5.JPG||HUF1400-6.JPG||HUF1400-7.JPG||HUF1400-8.JPG||HUF1400-9.JPG||HUF1400-10.JPG | AD12: 229||92867||241||244||48032 | AE12: 588 | AG12: Покупайте датчик давления в шине BH Sens ( Huf ) 36106877937 для BMW (БМВ) по выгодным ценам | Большой выбор датчиков давления в шине | Осуществляем доставку на всей территории РФ
A13: 302539 | B13: 1 | C13: 8253 | D13: 20 | E13: 36106881890 | F13: =VLOOKUP(E13,Лист1!A1:A306,1,FALSE) -> 36106881890 | G13: Датчик давления в шине для BMW 36106881890 Оригинал | H13: Купить по низкой цене оригинальный датчик давления в шинах для BMW 36106881890 с доставкой по Москве или России. | I13: 8250 | J13: Франция | K13: 30 | L13: dk-datchik-davlenia-v-shinah-36106856209-319 | M13: <p>Датчик TPMS для автомобилей производства компании BMW. Страна производства - Франция. Каталожный номер детали 36106881890. Датчик применяется в автомобилях, производства BMW.</p><p></p><p> При нормальных условиях эксплуатации устройство прослужит до 8 лет.</p><p>Данный датчик, производства компании BMW Франция номер 36106881890 рассчитан на установку в колеса легковых автомобилей BMW. Датчик продается в комплекте со штуцером, т.е. покупатель получает полный набор деталей для установки. Материал штуцера - металл. После установки датчика необходимо осуществить его привязку к системе авто. Для этого используется метод <a href="https://alltpms.ru/katalog/privyazka/privyazka-4">«Автоматизированная привязка»</a> (Карточка привязки).</p> | N13: 87 | O13: /market/36106881890.jpg | P13: Датчик давления в шине для BMW 36106881890 Оригинал | Q13: Датчик давления в шине для BMW 36106881890 Оригинал | R13: Доставка от 1 шт. без предоплаты, Гарантия 2 года | S13: 0 | T13: 0 | U13: 36106856209-319 | V13: 5054208002076 | W13: 180 | X13: BMW | Y13: 433 | Z13: yes | AA13: Clamp-in | AB13: 36106855539, 36106856209, 36106858887, 36106858888, 4043, A2C9743250080, A2C97432500, A2C97432501, A2C97432502, S180052056, S180052056Z, S180211011Z, S180211001Z, ECR0050, RDE027V21, 9014-4043, 9015-4043, 1210-4043, 2210-4043, 2200-4043, 1400-4043, 1401-4043, 4040-4043, 4041-4043, 590914-4043, 590918-4043, 4043PFR, 4043PFM, 4043PVM, 4040-RDE027, 4041-RDE027, RDE027PVM, RDE027PFR, RDE027PVM, RDE027PFR | AC13: 36106881890-1.JPG||36106881890-2.JPG||36106881890-3.JPG||36106881890-4.JPG||36106881890-5.JPG||36106881890-6.JPG||36106881890-7.JPG||36106881890-8.JPG||36106881890-9.JPG||36106881890-10.JPG | AD13: 226||48029 | AE13: 588 | AF13: BMW Continental ( VDO ) 36106881890 36106855539, 36106856209, 36106858887, 36106858888, 4043, A2C9743250080, A2C97432500, A2C97432501, A2C97432502, S180052056, S180052056Z, S180211011Z, S180211001Z, ECR0050, RDE027V21, 9014-4043, 9015-4043, 1210-4043, 2210-4043, 2200-4043, 1400-4043, 1401-4043, 4040-4043, 4041-4043, 590914-4043, 590918-4043, 4043PFR, 4043PFM, 4043PVM, 4040-RDE027, 4041-RDE027, RDE027PVM, RDE027PFR, RDE027PVM, RDE027PFR 36106855539, 36106856209, 36106858887, 36106858888, 4043, A2C9743250080, A2C97432500, A2C97432501, A2C97432502, S180052056, S180052056Z, S180211011Z, S180211001Z, ECR0050, RDE027V21, 90144043, 90154043, 12104043, 22104043, 22004043, 14004043, 14014043, 40404043, 40414043, 5909144043, 5909184043, 4043PFR, 4043PFM, 4043PVM, 4040RDE027, 4041RDE027, RDE027PVM, RDE027PFR, RDE027PVM, RDE027PFR Оригинал | AG13: Купить оригинальный датчик давления в шине для BMW 36106881890 в Москве с доставкой. Цена от производителя. Большой выбор датчиков. Гарантия.
A14: 302540 | B14: 1 | C14: 8253 | D14: 20 | E14: 36106881890 | F14: =VLOOKUP(E14,Лист1!A1:A306,1,FALSE) -> 36106881890 | G14: Датчик давления в шине BH Sens ( Huf ) 36106881890 для BMW (Black Edition) | H14: Покупайте датчик давления в шине BH Sens ( Huf ) 36106881890 для BMW (Black Edition) по выгодным ценам | Большой выбор датчиков давления в шине | Осуществляем доставку на всей территории РФ | I14: 3750 | J14: Германия | K14: 30 | L14: dk-datchik-davlenia-v-shinah-36106856209b-30 | M14: <p>Датчик, каталожный номер 36106881890. Передача данных производится посредством радиосигнала. Частота работы - 433МГц. Производитель – компания <a href="https://alltpms.ru/proizvoditeli-sistem-tpms/beru"> BH Sens ( Huf ) </a>. Страна-производитель - Германия.</p><p> Срок службы устройства варьируется и может достигать 7 лет. Данный показатель во многом зависит от интенсивности использования авто и условий его эксплуатации.</p><p> Конструктивные особенности датчика позволяют использовать его на большинстве марок авто производства BMW. Комплект поставки – датчик и ниппель. Материал ниппеля - металл. Комплект полностью готов к установке. Данный датчик, номер 36106881890 требует привязки к системе автомобиля. Для этого используется процедура <a href="https://alltpms.ru/katalog/privyazka/privyazka-4">«Автоматизированная привязка»</a> (Карточка привязки).</p> | N14: 88 | O14: /market/HUF1410B.jpg | P14: Датчик давления в шине BH Sens ( Huf ) 36106881890 для BMW (Black Edition) | Q14: Датчик давления в шине BH Sens ( Huf ) 36106881890 для BMW (Black Edition) | R14: Доставка от 1 шт. без предоплаты, Гарантия 2 года | S14: 0 | T14: 1 | U14: 36106856209b-30 | V14: 5054208002077 | W14: 622 | X14: BMW | Y14: 433 | Z14: no | AA14: Clamp-in | AB14: 36106855539, 36106856209, 36106858887, 36106858888, 4043, A2C9743250080, A2C97432500, A2C97432501, A2C97432502, S180052056, S180052056Z, S180211011Z, S180211001Z, ECR0050, RDE027V21, 9014-4043, 9015-4043, 1210-4043, 2210-4043, 2200-4043, 1400-4043, 1401-4043, 4040-4043, 4041-4043, 590914-4043, 590918-4043, 4043PFR, 4043PFM, 4043PVM, 4040-RDE027, 4041-RDE027, RDE027PVM, RDE027PFR, RDE027PVM, RDE027PFR | AC14: HUF1400_B-1.JPG||HUF1400_B-2.JPG||HUF1400_B-3.JPG||HUF1400_B-4.JPG||HUF1400_B-5.JPG||HUF1400_B-6.JPG||HUF1400_B-7.JPG||HUF1400_B-8.JPG||HUF1400_B-9.JPG||HUF1400_B-10.JPG | AD14: 226||48029 | AE14: 588 | AG14: Покупайте датчик давления в шине BH Sens ( Huf ) 36106881890 для BMW (Black Edition) по выгодным ценам | Большой выбор датчиков давления в шине | Осуществляем доставку на всей территории РФ
A15: 302541 | B15: 1 | C15: 8253 | D15: 20 | E15: 36106881890 | F15: =VLOOKUP(E15,Лист1!A1:A306,1,FALSE) -> 36106881890 | G15: Датчик давления в шине Continental ( VDO ) 36106881890 для BMW | H15: Купить по низкой цене датчик давления в шинах Continental ( VDO ) 36106881890 для BMW с доставкой по Москве или России. | I15: 4500 | J15: Франция | K15: 30 | L15: dk-datchik-davlenia-v-shinah-36106856209-3190 | M15: <p>Датчик 36106881890 контроля давления в шинах. Передача данных реализована по радиоканалу. Используемая частота - 433МГц. Производит устройства компания <a href="https://alltpms.ru/proizvoditeli-sistem-tpms/vdo"> Continental ( VDO ) </a>. Страна производства - Франция.</p><p> Датчики устанавливаются в автомобили, выпускаемые концерном BMW.</p><p></p><p> При условии правильной установки и эксплуатации, срок работы составит 6 лет и более. Срок варьируется в зависимости от интенсивности эксплуатации, частоты и продолжительности поездок.</p><p>Данный датчик 36106881890 сконструирован в расчете на установку в автомобили концерна BMW. В продажу поступают готовые комплекты. В комплект входит сам датчик и ниппель. После установки датчик необходимо активировать. Процесс выполняется с использованием методики <a href="https://alltpms.ru/katalog/privyazka/privyazka-4">«Автоматизированная привязка»</a> (Карточка привязки).</p> | N15: 90 | O15: /market/TG1CEVO.jpg | P15: Датчик давления в шине Continental ( VDO ) 36106881890 для BMW | Q15: Датчик давления в шине Continental ( VDO ) 36106881890 для BMW | R15: Доставка от 1 шт. без предоплаты, Гарантия 2 года | S15: 0 | T15: 0 | U15: 36106856209-3190 | V15: 5054208002078 | W15: 180 | X15: BMW | Y15: 433 | Z15: no | AA15: Clamp-in | AB15: 36106855539, 36106856209, 36106858887, 36106858888, 4043, A2C9743250080, A2C97432500, A2C97432501, A2C97432502, S180052056, S180052056Z, S180211011Z, S180211001Z, ECR0050, RDE027V21, 9014-4043, 9015-4043, 1210-4043, 2210-4043, 2200-4043, 1400-4043, 1401-4043, 4040-4043, 4041-4043, 590914-4043, 590918-4043, 4043PFR, 4043PFM, 4043PVM, 4040-RDE027, 4041-RDE027, RDE027PVM, RDE027PFR, RDE027PVM, RDE027PFR | AC15: 36106881890-VDO-1.JPG||36106881890-VDO-2.JPG||36106881890-VDO-3.JPG||36106881890-VDO-4.JPG||36106881890-VDO-5.JPG||36106881890-VDO-6.JPG||36106881890-VDO-7.JPG||36106881890-VDO-8.JPG||36106881890-VDO-9.JPG||36106881890-VDO-10.JPG | AD15: 226||48029 | AE15: 588 | AF15: BMW Continental ( VDO ) 36106881890 36106855539, 36106856209, 36106858887, 36106858888, 4043, A2C9743250080, A2C97432500, A2C97432501, A2C97432502, S180052056, S180052056Z, S180211011Z, S180211001Z, ECR0050, RDE027V21, 9014-4043, 9015-4043, 1210-4043, 2210-4043, 2200-4043, 1400-4043, 1401-4043, 4040-4043, 4041-4043, 590914-4043, 590918-4043, 4043PFR, 4043PFM, 4043PVM, 4040-RDE027, 4041-RDE027, RDE027PVM, RDE027PFR, RDE027PVM, RDE027PFR 36106855539, 36106856209, 36106858887, 36106858888, 4043, A2C9743250080, A2C97432500, A2C97432501, A2C97432502, S180052056, S180052056Z, S180211011Z, S180211001Z, ECR0050, RDE027V21, 90144043, 90154043, 12104043, 22104043, 22004043, 14004043, 14014043, 40404043, 40414043, 5909144043, 5909184043, 4043PFR, 4043PFM, 4043PVM, 4040RDE027, 4041RDE027, RDE027PVM, RDE027PFR, RDE027PVM, RDE027PFR | AG15: Купить датчик давления в шине Continental ( VDO ) 36106881890 для BMW в Москве с доставкой. Цена от производителя. Большой выбор датчиков. Гарантия.
A16: 302542 | B16: 1 | C16: 8253 | D16: 20 | E16: 36106881890 | F16: =VLOOKUP(E16,Лист1!A1:A306,1,FALSE) -> 36106881890 | G16: Датчик давления в шине BH Sens ( Huf ) 36106881890 для BMW | H16: Покупайте датчик давления в шине BH Sens ( Huf ) 36106881890 для BMW по выгодным ценам | Большой выбор датчиков давления в шине | Осуществляем доставку на всей территории РФ | I16: 3250 | J16: Германия | K16: 30 | L16: dk-datchik-davlenia-v-shinah-36106856209-30 | M16: <p>Датчик, номер по каталогу запчастей 36106881890. Предназначен для контроля давления в шинах. Передача данных осуществляется посредством радиосигнала на частоте 433МГц. Компания производитель датчика - <a href="https://alltpms.ru/proizvoditeli-sistem-tpms/beru"> BH Sens ( Huf ) </a>. Место производства - Германия.</p><p>Правильно установленный датчик гарантировано проработает 7 лет. В каждом конкретном случае срок службы может изменяться. Он зависит от условий эксплуатации, длительности поездок, их частоты.</p><p>Предназначенный для установки в колеса автомобилей большинства моделей концерна BMW, датчик поставляется в комплекте с ниппелем. Покупатель получает комплектное устройство. После установки датчик 36106881890 активируется, используется метод <a href="https://alltpms.ru/katalog/privyazka/privyazka-4">«Автоматизированная привязка»</a> (Карточка привязки).</p> | N16: 89 | O16: /market/HUF1410.jpg | P16: Датчик давления в шине BH Sens ( Huf ) 36106881890 для BMW | Q16: Датчик давления в шине BH Sens ( Huf ) 36106881890 для BMW | R16: Доставка от 1 шт. без предоплаты, Гарантия 2 года | S16: 0 | T16: 1 | U16: 36106856209-30 | V16: 5054208002079 | W16: 622 | X16: BMW | Y16: 433 | Z16: no | AA16: Clamp-in | AB16: 36106855539, 36106856209, 36106858887, 36106858888, 4043, A2C9743250080, A2C97432500, A2C97432501, A2C97432502, S180052056, S180052056Z, S180211011Z, S180211001Z, ECR0050, RDE027V21, 9014-4043, 9015-4043, 1210-4043, 2210-4043, 2200-4043, 1400-4043, 1401-4043, 4040-4043, 4041-4043, 590914-4043, 590918-4043, 4043PFR, 4043PFM, 4043PVM, 4040-RDE027, 4041-RDE027, RDE027PVM, RDE027PFR, RDE027PVM, RDE027PFR | AC16: HUF1400-1.JPG||HUF1400-2.JPG||HUF1400-3.JPG||HUF1400-4.JPG||HUF1400-5.JPG||HUF1400-6.JPG||HUF1400-7.JPG||HUF1400-8.JPG||HUF1400-9.JPG||HUF1400-10.JPG | AD16: 226||48029 | AE16: 588 | AG16: Покупайте датчик давления в шине BH Sens ( Huf ) 36106881890 для BMW по выгодным ценам | Большой выбор датчиков давления в шине | Осуществляем доставку на всей территории РФ
A17: 302543 | B17: 1 | C17: 8253 | D17: 20 | E17: 36106887147 | F17: =VLOOKUP(E17,Лист1!A1:A306,1,FALSE) -> 36106887147 | G17: Датчик давления в шине для BMW 36106887147 Оригинал | H17: Купить по низкой цене оригинальный датчик давления в шинах для BMW 36106887147 с доставкой по Москве или России. | I17: 7500 | J17: Англия | K17: 30 | L17: dk-datchik-davlenia-v-shinah-36106872803-319 | M17: <p>Датчик давления в шинах, номер по каталогу 36106887147, передает сигналы с помощью радиоканала. Рабочая частота - 433МГц. Компания производитель автомобиля BMW. Страна производства - Англия. Устройства предназначены для установки в колеса автомобилей, выпускаемых концерном BMW.</p><p></p><p> При условии установки на специализированных СТО, срок службы устройства составляет до 7 лет.</p><p>Конструктивные особенности данного датчика гарантируют его полную совместимость с системами авто концерна BMW. Датчик поставляется в комплекте с ниппелем, что заметно облегчает установку и не требует покупки дополнительных деталей. Материал ниппеля - металл. После установки датчик 36106887147 требует привязки к авто. Привязка производится по методике <a href="https://alltpms.ru/katalog/privyazka/privyazka-4">«Автоматизированная привязка»</a> (Карточка привязки).</p> | N17: 97 | O17: /market/A2102.jpg | P17: Датчик давления в шине для BMW 36106887147 Оригинал | Q17: Датчик давления в шине для BMW 36106887147 Оригинал | R17: Доставка от 1 шт. без предоплаты, Гарантия 2 года | S17: 0 | T17: 0 | U17: 36106872803-319 | V17: 5054208002080 | W17: 625 | X17: BMW | Y17: 433 | Z17: yes | AA17: Clamp-in | AB17: 36106872774, 36106872803, 36106876955, 36106876957, 36106876957, 36106877937, A0009052102, A0009057205, A0009054104, 3057, A0009058706, 28238, S180211005Z, ECR0280, RDE077V21, RDE035V21, 9014-3057, 9015-3057, 1210-3057, 2210-3057, 2200-3057, 1400-3057, 1401-3057, 4040-3057, 4041-3057, 590914-3057, 590918-3057, 1900-28238, 2901-28238, 4040-28238, 4041-28238, 1400-28238, 1401-28238, 590914-28238, 590918-28238, 3057PFR, 3057PFM, 3057PVM, 28238PVM, 28238PFR, 4040-RDE077, 4041-RDE077, RDE077PVM, RDE077PFR, RDE077PVM, RDE077PFR | AC17: 36106872803-1.JPG||36106872803-2.JPG||36106872803-3.JPG||36106872803-4.JPG||36106872803-5.JPG||36106872803-6.JPG||36106872803-7.JPG||36106872803-8.JPG||36106872803-9.JPG||36106872803-10.JPG | AD17: 211||48023||92872 | AE17: 588 | AF17: BMW Schrader 36106887147 36106872774, 36106872803, 36106876955, 36106876957, 36106876957, 36106877937, A0009052102, A0009057205, A0009054104, 3057, A0009058706, 28238, S180211005Z, ECR0280, RDE077V21, RDE035V21, 9014-3057, 9015-3057, 1210-3057, 2210-3057, 2200-3057, 1400-3057, 1401-3057, 4040-3057, 4041-3057, 590914-3057, 590918-3057, 1900-28238, 2901-28238, 4040-28238, 4041-28238, 1400-28238, 1401-28238, 590914-28238, 590918-28238, 3057PFR, 3057PFM, 3057PVM, 28238PVM, 28238PFR, 4040-RDE077, 4041-RDE077, RDE077PVM, RDE077PFR, RDE077PVM, RDE077PFR 36106872774, 36106872803, 36106876955, 36106876957, 36106876957, 36106877937, A0009052102, A0009057205, A0009054104, 3057, A0009058706, 28238, S180211005Z, ECR0280, RDE077V21, RDE035V21, 90143057, 90153057, 12103057, 22103057, 22003057, 14003057, 14013057, 40403057, 40413057, 5909143057, 5909183057, 190028238, 290128238, 404028238, 404128238, 140028238, 140128238, 59091428238, 59091828238, 3057PFR, 3057PFM, 3057PVM, 28238PVM, 28238PFR, 4040RDE077, 4041RDE077, RDE077PVM, RDE077PFR, RDE077PVM, RDE077PFR Оригинал | AG17: Купить оригинальный датчик давления в шине для BMW 36106887147 в Москве с доставкой. Цена от производителя. Большой выбор датчиков. Гарантия.
A18: 302544 | B18: 1 | C18: 8253 | D18: 20 | E18: 36106887147 | F18: =VLOOKUP(E18,Лист1!A1:A306,1,FALSE) -> 36106887147 | G18: Датчик давления в шине BH Sens ( Huf ) 36106887147 для BMW (Black Edition) | H18: Покупайте датчик давления в шине BH Sens ( Huf ) 36106887147 для BMW (Black Edition) по выгодным ценам | Большой выбор датчиков давления в шине | Осуществляем доставку на всей территории РФ | I18: 3750 | J18: Германия | K18: 30 | L18: dk-datchik-davlenia-v-shinah-36106872803bb-30 | M18: <p>Датчик TPMS, производства компании <a href="https://alltpms.ru/proizvoditeli-sistem-tpms/beru"> BH Sens ( Huf ) </a>. Страна производства - Германия. Каталожный номер детали 36106887147. Датчик применяется в автомобилях, производства BMW.</p><p></p><p> При нормальных условиях эксплуатации устройство прослужит до 8 лет.</p><p>Данный датчик, производства компании <a href="https://alltpms.ru/proizvoditeli-sistem-tpms/beru"> BH Sens ( Huf ) </a> Германия номер 36106887147 рассчитан на установку в колеса легковых автомобилей BMW. Датчик продается в комплекте со штуцером, т.е. покупатель получает полный набор деталей для установки. Материал штуцера - металл. После установки датчика необходимо осуществить его привязку к системе авто. Для этого используется метод <a href="https://alltpms.ru/katalog/privyazka/privyazka-4">«Автоматизированная привязка»</a> (Карточка привязки).</p> | N18: 96 | O18: /market/HUF1410B.jpg | P18: Датчик давления в шине BH Sens ( Huf ) 36106887147 для BMW (Black Edition) | Q18: Датчик давления в шине BH Sens ( Huf ) 36106887147 для BMW (Black Edition) | R18: Доставка от 1 шт. без предоплаты, Гарантия 2 года | S18: 0 | T18: 1 | U18: 36106872803bb-30 | V18: 5054208002081 | W18: 622 | X18: BMW | Y18: 433 | Z18: no | AA18: Clamp-in | AB18: 36106872774, 36106872803, 36106876955, 36106876957, 36106876957, 36106877937, A0009052102, A0009057205, A0009054104, 3057, A0009058706, 28238, S180211005Z, ECR0280, RDE077V21, RDE035V21, 9014-3057, 9015-3057, 1210-3057, 2210-3057, 2200-3057, 1400-3057, 1401-3057, 4040-3057, 4041-3057, 590914-3057, 590918-3057, 1900-28238, 2901-28238, 4040-28238, 4041-28238, 1400-28238, 1401-28238, 590914-28238, 590918-28238, 3057PFR, 3057PFM, 3057PVM, 28238PVM, 28238PFR, 4040-RDE077, 4041-RDE077, RDE077PVM, RDE077PFR, RDE077PVM, RDE077PFR | AC18: HUF1400_B-1.JPG||HUF1400_B-2.JPG||HUF1400_B-3.JPG||HUF1400_B-4.JPG||HUF1400_B-5.JPG||HUF1400_B-6.JPG||HUF1400_B-7.JPG||HUF1400_B-8.JPG||HUF1400_B-9.JPG||HUF1400_B-10.JPG | AD18: 211||48023||92872 | AE18: 588 | AG18: Покупайте датчик давления в шине BH Sens ( Huf ) 36106887147 для BMW (Black Edition) по выгодным ценам | Большой выбор датчиков давления в шине | Осуществляем доставку на всей территории РФ
A19: 302545 | B19: 1 | C19: 8253 | D19: 20 | E19: 36106887147 | F19: =VLOOKUP(E19,Лист1!A1:A306,1,FALSE) -> 36106887147 | G19: Датчик давления в шине BH Sens ( Huf ) 36106887147 для BMW | H19: Покупайте датчик давления в шине BH Sens ( Huf ) 36106887147 для BMW по выгодным ценам | Большой выбор датчиков давления в шине | Осуществляем доставку на всей территории РФ | I19: 3250 | J19: Германия | K19: 30 | L19: dk-datchik-davlenia-v-shinah-36106872803-30 | M19: <p>Датчик 36106887147 контроля давления в шинах. Передача данных реализована по радиоканалу. Используемая частота - 433МГц. Производит устройства компания <a href="https://alltpms.ru/proizvoditeli-sistem-tpms/beru"> BH Sens ( Huf ) </a>. Страна производства - Германия.</p><p> Датчики устанавливаются в автомобили, выпускаемые концерном BMW.</p><p></p><p> При условии правильной установки и эксплуатации, срок работы составит 6 лет и более. Срок варьируется в зависимости от интенсивности эксплуатации, частоты и продолжительности поездок.</p><p>Данный датчик 36106887147 сконструирован в расчете на установку в автомобили концерна BMW. В продажу поступают готовые комплекты. В комплект входит сам датчик и ниппель. После установки датчик необходимо активировать. Процесс выполняется с использованием методики <a href="https://alltpms.ru/katalog/privyazka/privyazka-4">«Автоматизированная привязка»</a> (Карточка привязки).</p> | N19: 98 | O19: /market/HUF1410.jpg | P19: Датчик давления в шине BH Sens ( Huf ) 36106887147 для BMW | Q19: Датчик давления в шине BH Sens ( Huf ) 36106887147 для BMW | R19: Доставка от 1 шт. без предоплаты, Гарантия 2 года | S19: 0 | T19: 1 | U19: 36106872803-30 | V19: 5054208002082 | W19: 622 | X19: BMW | Y19: 433 | Z19: no | AA19: Clamp-in | AB19: 36106872774, 36106872803, 36106876955, 36106876957, 36106876957, 36106877937, A0009052102, A0009057205, A0009054104, 3057, A0009058706, 28238, S180211005Z, ECR0280, RDE077V21, RDE035V21, 9014-3057, 9015-3057, 1210-3057, 2210-3057, 2200-3057, 1400-3057, 1401-3057, 4040-3057, 4041-3057, 590914-3057, 590918-3057, 1900-28238, 2901-28238, 4040-28238, 4041-28238, 1400-28238, 1401-28238, 590914-28238, 590918-28238, 3057PFR, 3057PFM, 3057PVM, 28238PVM, 28238PFR, 4040-RDE077, 4041-RDE077, RDE077PVM, RDE077PFR, RDE077PVM, RDE077PFR | AC19: HUF1400-1.JPG||HUF1400-2.JPG||HUF1400-3.JPG||HUF1400-4.JPG||HUF1400-5.JPG||HUF1400-6.JPG||HUF1400-7.JPG||HUF1400-8.JPG||HUF1400-9.JPG||HUF1400-10.JPG | AD19: 211||48023||92872 | AE19: 588 | AG19: Покупайте датчик давления в шине BH Sens ( Huf ) 36106887147 для BMW по выгодным ценам | Большой выбор датчиков давления в шине | Осуществляем доставку на всей территории РФ
A20: 302546 | B20: 1 | C20: 8253 | D20: 20 | E20: 36106887147 | F20: =VLOOKUP(E20,Лист1!A1:A306,1,FALSE) -> 36106887147 | G20: Датчик давления в шине Schrader 36106887147 для BMW | H20: Купить по низкой цене датчик давления в шинах Schrader 36106887147 для BMW с доставкой по Москве или России. | I20: 4500 | J20: Англия | K20: 30 | L20: dk-datchik-davlenia-v-shinah-36106872803-21 | M20: <p>Датчик давления в шинах, номер по каталогу 36106887147, передает сигналы с помощью радиоканала. Рабочая частота - 433МГц. Компания производитель <a href="https://alltpms.ru/proizvoditeli-sistem-tpms/schrader"> Schrader </a>. Страна производства - Англия. Устройства предназначены для установки в колеса автомобилей, выпускаемых концерном BMW.</p><p></p><p> При условии установки на специализированных СТО, срок службы устройства составляет до 7 лет.</p><p>Конструктивные особенности данного датчика гарантируют его полную совместимость с системами авто концерна BMW. Датчик поставляется в комплекте с ниппелем, что заметно облегчает установку и не требует покупки дополнительных деталей. Материал ниппеля - металл. После установки датчик 36106887147 требует привязки к авто. Привязка производится по методике <a href="https://alltpms.ru/katalog/privyazka/privyazka-4">«Автоматизированная привязка»</a> (Карточка привязки).</p> | N20: 99 | O20: /market/3057.jpg | P20: Датчик давления в шине Schrader 36106887147 для BMW | Q20: Датчик давления в шине Schrader 36106887147 для BMW | R20: Доставка от 1 шт. без предоплаты, Гарантия 2 года | S20: 0 | T20: 0 | U20: 36106872803-21 | V20: 5054208002083 | W20: 625 | X20: BMW | Y20: 433 | Z20: no | AA20: Clamp-in | AB20: 36106872774, 36106872803, 36106876955, 36106876957, 36106876957, 36106877937, A0009052102, A0009057205, A0009054104, 3057, A0009058706, 28238, S180211005Z, ECR0280, RDE077V21, RDE035V21, 9014-3057, 9015-3057, 1210-3057, 2210-3057, 2200-3057, 1400-3057, 1401-3057, 4040-3057, 4041-3057, 590914-3057, 590918-3057, 1900-28238, 2901-28238, 4040-28238, 4041-28238, 1400-28238, 1401-28238, 590914-28238, 590918-28238, 3057PFR, 3057PFM, 3057PVM, 28238PVM, 28238PFR, 4040-RDE077, 4041-RDE077, RDE077PVM, RDE077PFR, RDE077PVM, RDE077PFR | AC20: 3057-1.JPG||3057-2.JPG||3057-3.JPG||3057-4.JPG||3057-5.JPG||3057-6.JPG||3057-7.JPG||3057-8.JPG||3057-9.JPG||3057-10.JPG | AD20: 211||48023||92872 | AE20: 588 | AF20: BMW Schrader 36106887147 36106872774, 36106872803, 36106876955, 36106876957, 36106876957, 36106877937, A0009052102, A0009057205, A0009054104, 3057, A0009058706, 28238, S180211005Z, ECR0280, RDE077V21, RDE035V21, 9014-3057, 9015-3057, 1210-3057, 2210-3057, 2200-3057, 1400-3057, 1401-3057, 4040-3057, 4041-3057, 590914-3057, 590918-3057, 1900-28238, 2901-28238, 4040-28238, 4041-28238, 1400-28238, 1401-28238, 590914-28238, 590918-28238, 3057PFR, 3057PFM, 3057PVM, 28238PVM, 28238PFR, 4040-RDE077, 4041-RDE077, RDE077PVM, RDE077PFR, RDE077PVM, RDE077PFR 36106872774, 36106872803, 36106876955, 36106876957, 36106876957, 36106877937, A0009052102, A0009057205, A0009054104, 3057, A0009058706, 28238, S180211005Z, ECR0280, RDE077V21, RDE035V21, 90143057, 90153057, 12103057, 22103057, 22003057, 14003057, 14013057, 40403057, 40413057, 5909143057, 5909183057, 190028238, 290128238, 404028238, 404128238, 140028238, 140128238, 59091428238, 59091828238, 3057PFR, 3057PFM, 3057PVM, 28238PVM, 28238PFR, 4040RDE077, 4041RDE077, RDE077PVM, RDE077PFR, RDE077PVM, RDE077PFR | AG20: Купить датчик давления в шине Schrader 36106887147 для BMW в Москве с доставкой. Цена от производителя. Большой выбор датчиков. Гарантия.
A21: 302547 | B21: 1 | C21: 8253 | D21: 20 | E21: 36106890964 | F21: =VLOOKUP(E21,Лист1!A1:A306,1,FALSE) -> 36106890964 | G21: Датчик давления в шине BH Sens ( Huf ) 36106890964 для BMW (Black Edition) | H21: Покупайте датчик давления в шине BH Sens ( Huf ) 36106890964 для BMW (Black Edition) по выгодным ценам | Большой выбор датчиков давления в шине | Осуществляем доставку на всей территории РФ | I21: 4250 | J21: Германия | K21: 30 | L21: dk-datchik-davlenia-v-shinah-36106798872b-32 | M21: <p>Датчик 36106890964 контроля давления в шинах. Передача данных реализована по радиоканалу. Используемая частота - 433МГц. Производит устройства компания <a href="https://alltpms.ru/proizvoditeli-sistem-tpms/beru"> BH Sens ( Huf ) </a>. Страна производства - Германия.</p><p> Датчики устанавливаются в автомобили, выпускаемые концерном BMW.</p><p></p><p> При условии правильной установки и эксплуатации, срок работы составит 6 лет и более. Срок варьируется в зависимости от интенсивности эксплуатации, частоты и продолжительности поездок.</p><p>Данный датчик 36106890964 сконструирован в расчете на установку в автомобили концерна BMW. В продажу поступают готовые комплекты. В комплект входит сам датчик и ниппель. После установки датчик необходимо активировать. Процесс выполняется с использованием методики <a href="https://alltpms.ru/katalog/privyazka/privyazka-4">«Автоматизированная привязка»</a> (Карточка привязки).</p> | N21: 76 | O21: /market/RDE047V21B.jpg | P21: Датчик давления в шине BH Sens ( Huf ) 36106890964 для BMW (Black Edition) | Q21: Датчик давления в шине BH Sens ( Huf ) 36106890964 для BMW (Black Edition) | R21: Доставка от 1 шт. без предоплаты, Гарантия 2 года | S21: 0 | T21: 1 | U21: 36106798872b-32 | V21: 5054208002084 | W21: 622 | X21: BMW | Y21: 433 | Z21: no | AA21: Clamp-in | AB21: 36106798872, 36106874830, 4069, 550-1917, TX-S004L/R, TPS0004L/R, ECR0010, RDE012V21, 9014-4069, 9015-4069, 1210-4069, 2210-4069, 2200-4069, 1400-4069, 1401-4069, 4040-4069, 4041-4069, 590914-4069, 590918-4069, 4069PFR, 4069PFM, 4069PVM, 4040-RDE012, 4041-RDE012, RDE012PVM, RDE012PFR, RDE012PVM, RDE012PFR | AC21: HUF4040_B-1.JPG||HUF4040_B-2.JPG||HUF4040_B-3.JPG||HUF4040_B-4.JPG||HUF4040_B-5.JPG||HUF4040_B-6.JPG||HUF4040_B-7.JPG||HUF4040_B-8.JPG||HUF4040_B-9.JPG||HUF4040_B-10.JPG | AD21: 229||92867||241||244||48032 | AE21: 588 | AG21: Покупайте датчик давления в шине BH Sens ( Huf ) 36106890964 для BMW (Black Edition) по выгодным ценам | Большой выбор датчиков давления в шине | Осуществляем доставку на всей территории РФ
A22: 302548 | B22: 1 | C22: 8253 | D22: 20 | E22: 36106890964 | F22: =VLOOKUP(E22,Лист1!A1:A306,1,FALSE) -> 36106890964 | G22: Датчик давления в шине BH Sens ( Huf, Германия ) 36106890964 для BMW | H22: Покупайте датчик давления в шине BH Sens ( Huf, Германия ) 36106890964 для BMW по выгодным ценам | Большой выбор датчиков давления в шине | Осуществляем доставку на всей территории РФ | I22: 3750 | J22: Германия | K22: 30 | L22: dk-datchik-davlenia-v-shinah-36106798872-32 | M22: <p>Датчик 36106890964 контроля давления в шинах. Передача данных реализована по радиоканалу. Используемая частота - 433МГц. Производит устройства компания <a href="https://alltpms.ru/proizvoditeli-sistem-tpms/beru"> BH Sens ( Huf ) </a>. Страна производства - Германия.</p><p> Датчики устанавливаются в автомобили, выпускаемые концерном BMW.</p><p></p><p> При условии правильной установки и эксплуатации, срок работы составит 6 лет и более. Срок варьируется в зависимости от интенсивности эксплуатации, частоты и продолжительности поездок.</p><p>Данный датчик 36106890964 сконструирован в расчете на установку в автомобили концерна BMW. В продажу поступают готовые комплекты. В комплект входит сам датчик и ниппель. После установки датчик необходимо активировать. Процесс выполняется с использованием методики <a href="https://alltpms.ru/katalog/privyazka/privyazka-4">«Автоматизированная привязка»</a> (Карточка привязки).</p> | N22: 78 | O22: /market/RDE047.jpg | P22: Датчик давления в шине BH Sens ( Huf ) 36106890964 для BMW | Q22: Датчик давления в шине BH Sens ( Huf ) 36106890964 для BMW | R22: Доставка от 1 шт. без предоплаты, Гарантия 2 года | S22: 0 | T22: 1 | U22: 36106798872-32 | V22: 5054208002085 | W22: 622 | X22: BMW | Y22: 433 | Z22: no | AA22: Clamp-in | AB22: 36106798872, 36106874830, 4069, 550-1917, TX-S004L/R, TPS0004L/R, ECR0010, RDE012V21, 9014-4069, 9015-4069, 1210-4069, 2210-4069, 2200-4069, 1400-4069, 1401-4069, 4040-4069, 4041-4069, 590914-4069, 590918-4069, 4069PFR, 4069PFM, 4069PVM, 4040-RDE012, 4041-RDE012, RDE012PVM, RDE012PFR, RDE012PVM, RDE012PFR | AC22: HUF4040-1.JPG||HUF4040-2.JPG||HUF4040-3.JPG||HUF4040-4.JPG||HUF4040-5.JPG||HUF4040-6.JPG||HUF4040-7.JPG||HUF4040-8.JPG||HUF4040-9.JPG||HUF4040-10.JPG | AD22: 229||92867||241||244||48032 | AE22: 588 | AG22: Покупайте датчик давления в шине BH Sens ( Huf, Германия ) 36106890964 для BMW по выгодным ценам | Большой выбор датчиков давления в шине | Осуществляем доставку на всей территории РФ
A23: 302549 | B23: 1 | C23: 8253 | D23: 20 | E23: 36106890964 | F23: =VLOOKUP(E23,Лист1!A1:A306,1,FALSE) -> 36106890964 | G23: Датчик давления в шине для BMW 36106890964 Оригинал | H23: Купить по низкой цене оригинальный датчик давления в шинах для BMW 36106890964 с доставкой по Москве или России. | I23: 7000 | J23: Германия | K23: 30 | L23: dk-datchik-davlenia-v-shinah-36106798872-25 | M23: <p>Датчик TPMS для автомобилей производства компании BMW. Страна производства - Германия. Каталожный номер детали 36106890964. Датчик применяется в автомобилях, производства BMW.</p><p></p><p> При нормальных условиях эксплуатации устройство прослужит до 8 лет.</p><p>Данный датчик, производства компании BMW Германия номер 36106890964 рассчитан на установку в колеса легковых автомобилей BMW. Датчик продается в комплекте со штуцером, т.е. покупатель получает полный набор деталей для установки. Материал штуцера - металл. После установки датчика необходимо осуществить его привязку к системе авто. Для этого используется метод <a href="https://alltpms.ru/katalog/privyazka/privyazka-4">«Автоматизированная привязка»</a> (Карточка привязки).</p> | N23: 75 | O23: /market/BMW964.jpg | P23: Датчик давления в шине для BMW 36106890964 Оригинал | Q23: Датчик давления в шине для BMW 36106890964 Оригинал | R23: Доставка от 1 шт. без предоплаты, Гарантия 2 года | S23: 0 | T23: 0 | U23: 36106798872-25 | V23: 5054208002086 | W23: 622 | X23: BMW | Y23: 433 | Z23: yes | AA23: Clamp-in | AB23: 36106798872, 36106874830, 4069, 550-1917, TX-S004L/R, TPS0004L/R, ECR0010, RDE012V21, 9014-4069, 9015-4069, 1210-4069, 2210-4069, 2200-4069, 1400-4069, 1401-4069, 4040-4069, 4041-4069, 590914-4069, 590918-4069, 4069PFR, 4069PFM, 4069PVM, 4040-RDE012, 4041-RDE012, RDE012PVM, RDE012PFR, RDE012PVM, RDE012PFR | AC23: 36106798872-1.JPG||36106798872-2.JPG||36106798872-3.JPG||36106798872-4.JPG||36106798872-5.JPG||36106798872-6.JPG||36106798872-7.JPG||36106798872-8.JPG||36106798872-9.JPG||36106798872-10.JPG | AD23: 229||92867||241||244||48032 | AE23: 588 | AF23: BMW BH Sens ( Huf ) 36106890964 36106798872, 36106874830, 4069, 550-1917, TX-S004L/R, TPS0004L/R, ECR0010, RDE012V21, 9014-4069, 9015-4069, 1210-4069, 2210-4069, 2200-4069, 1400-4069, 1401-4069, 4040-4069, 4041-4069, 590914-4069, 590918-4069, 4069PFR, 4069PFM, 4069PVM, 4040-RDE012, 4041-RDE012, RDE012PVM, RDE012PFR, RDE012PVM, RDE012PFR 36106798872, 36106874830, 4069, 5501917, TXS004L/R, TPS0004L/R, ECR0010, RDE012V21, 90144069, 90154069, 12104069, 22104069, 22004069, 14004069, 14014069, 40404069, 40414069, 5909144069, 5909184069, 4069PFR, 4069PFM, 4069PVM, 4040RDE012, 4041RDE012, RDE012PVM, RDE012PFR, RDE012PVM, RDE012PFR Оригинал | AG23: Купить оригинальный датчик давления в шине для BMW 36106890964 в Москве с доставкой. Цена от производителя. Большой выбор датчиков. Гарантия.
A24: 302550 | B24: 1 | C24: 8253 | D24: 20 | E24: 36106890964 | F24: =VLOOKUP(E24,Лист1!A1:A306,1,FALSE) -> 36106890964 | G24: Датчик давления в шине BH Sens ( Huf, Германия ) 36106890964 для BMW (Black Edition) | H24: Покупайте датчик давления в шине BH Sens ( Huf, Германия ) 36106890964 для BMW (Black Edition) по выгодным ценам | Большой выбор датчиков давления в шине | Осуществляем доставку на всей территории РФ | I24: 3750 | J24: Германия | K24: 30 | L24: dk-datchik-davlenia-v-shinah-36106798872b-24 | M24: <p>Датчик, каталожный номер 36106890964. Передача данных производится посредством радиосигнала. Частота работы - 433МГц. Производитель – компания <a href="https://alltpms.ru/proizvoditeli-sistem-tpms/beru"> BH Sens ( Huf ) </a>. Страна-производитель - Германия.</p><p> Срок службы устройства варьируется и может достигать 7 лет. Данный показатель во многом зависит от интенсивности использования авто и условий его эксплуатации.</p><p> Конструктивные особенности датчика позволяют использовать его на большинстве марок авто производства BMW. Комплект поставки – датчик и ниппель. Материал ниппеля - металл. Комплект полностью готов к установке. Данный датчик, номер 36106890964 требует привязки к системе автомобиля. Для этого используется процедура <a href="https://alltpms.ru/katalog/privyazka/privyazka-4">«Автоматизированная привязка»</a> (Карточка привязки).</p> | N24: 77 | O24: /market/HUF1410B.jpg | P24: Датчик давления в шине BH Sens ( Huf ) 36106890964 для BMW (Black Edition) | Q24: Датчик давления в шине BH Sens ( Huf ) 36106890964 для BMW (Black Edition) | R24: Доставка от 1 шт. без предоплаты, Гарантия 2 года | S24: 0 | T24: 1 | U24: 36106798872b-24 | V24: 5054208002087 | W24: 622 | X24: BMW | Y24: 433 | Z24: no | AA24: Clamp-in | AB24: 36106798872, 36106874830, 4069, 550-1917, TX-S004L/R, TPS0004L/R, ECR0010, RDE012V21, 9014-4069, 9015-4069, 1210-4069, 2210-4069, 2200-4069, 1400-4069, 1401-4069, 4040-4069, 4041-4069, 590914-4069, 590918-4069, 4069PFR, 4069PFM, 4069PVM, 4040-RDE012, 4041-RDE012, RDE012PVM, RDE012PFR, RDE012PVM, RDE012PFR | AC24: HUF1400_B-1.JPG||HUF1400_B-2.JPG||HUF1400_B-3.JPG||HUF1400_B-4.JPG||HUF1400_B-5.JPG||HUF1400_B-6.JPG||HUF1400_B-7.JPG||HUF1400_B-8.JPG||HUF1400_B-9.JPG||HUF1400_B-10.JPG | AD24: 229||92867||241||244||48032 | AE24: 588 | AG24: Покупайте датчик давления в шине BH Sens ( Huf, Германия ) 36106890964 для BMW (Black Edition) по выгодным ценам | Большой выбор датчиков давления в шине | Осуществляем доставку на всей территории РФ
A25: 302551 | B25: 1 | C25: 8253 | D25: 20 | E25: 36106890964 | F25: =VLOOKUP(E25,Лист1!A1:A306,1,FALSE) -> 36106890964 | G25: Датчик давления в шине BH Sens ( Huf ) 36106890964 для BMW | H25: Покупайте датчик давления в шине BH Sens ( Huf ) 36106890964 для BMW по выгодным ценам | Большой выбор датчиков давления в шине | Осуществляем доставку на всей территории РФ | I25: 3250 | J25: Германия | K25: 30 | L25: dk-datchik-davlenia-v-shinah-36106798872-222 | M25: <p> Датчик давления в шинах. Предназначен для автомобилей BMW. Каталожный номер запчасти 36106890964. Компания производитель - <a href="https://alltpms.ru/proizvoditeli-sistem-tpms/beru"> BH Sens ( Huf ) </a>, Германия.</p><p></p><p>При условии соблюдения правил установки и эксплуатации, срок службы датчика варьируется в пределах от 7 до 8 лет. Срок нормальной работы зависит от условий эксплуатации.</p><p>Данный датчик полностью совместим с большинством моделей автомобилей концерна BMW. В продажу поступает комплект (датчик и ниппель). После установки требуется произвести привязку и активацию. Данные процедуры выполняются по методу <a href="https://alltpms.ru/katalog/privyazka/privyazka-4">«Автоматизированная привязка»</a> (Карточка привязки).</p> | N25: 79 | O25: /market/HUF1410.jpg | P25: Датчик давления в шине BH Sens ( Huf ) 36106890964 для BMW | Q25: Датчик давления в шине BH Sens ( Huf ) 36106890964 для BMW | R25: Доставка от 1 шт. без предоплаты, Гарантия 2 года | S25: 0 | T25: 1 | U25: 36106798872-222 | V25: 5054208002088 | W25: 622 | X25: BMW | Y25: 433 | Z25: no | AA25: Clamp-in | AB25: 36106798872, 36106874830, 4069, 550-1917, TX-S004L/R, TPS0004L/R, ECR0010, RDE012V21, 9014-4069, 9015-4069, 1210-4069, 2210-4069, 2200-4069, 1400-4069, 1401-4069, 4040-4069, 4041-4069, 590914-4069, 590918-4069, 4069PFR, 4069PFM, 4069PVM, 4040-RDE012, 4041-RDE012, RDE012PVM, RDE012PFR, RDE012PVM, RDE012PFR | AC25: HUF1400-1.JPG||HUF1400-2.JPG||HUF1400-3.JPG||HUF1400-4.JPG||HUF1400-5.JPG||HUF1400-6.JPG||HUF1400-7.JPG||HUF1400-8.JPG||HUF1400-9.JPG||HUF1400-10.JPG | AD25: 229||92867||241||244||48032 | AE25: 588 | AG25: Покупайте датчик давления в шине BH Sens ( Huf ) 36106890964 для BMW по выгодным ценам | Большой выбор датчиков давления в шине | Осуществляем доставку на всей территории РФ
A26: 302552 | B26: 1 | C26: 8253 | D26: 20 | E26: 36118378681 | F26: =VLOOKUP(E26,Лист1!A1:A306,1,FALSE) -> 36118378681 | G26: Датчик давления в шине (только США) BH Sens ( Huf ) 36118378681 для BMW | H26: Купить по низкой цене датчик давления в шинах BH Sens ( Huf ) 36118378681 для BMW с доставкой по Москве или России. | I26: 3750 | J26: Германия | K26: 30 | L26: dk-datchik-davlenia-v-shinah-36118378681-353 | M26: <p> Каталожный номер датчика 36118378681. Передача данных происходит по радиоканалу, задействована частота 315МГц. Компания производитель – <a href="https://alltpms.ru/proizvoditeli-sistem-tpms/beru"> BH Sens ( Huf ) </a>. Страна - Германия.</p><p> Датчики предназначены для авто производства BMW.</p><p></p><p>В зависимости от интенсивности эксплуатации комплекта колес срок службы устройства достигает 7 лет. Срок эксплуатации зависит от продолжительности поездок, поскольку именно во время движения автомобиля датчик расходует заряд элемента питания.</p><p> Предназначенный для установки в автомобили концерна BMW, датчик поступает в продажу с ниппелем. Благодаря этому покупатель получает полностью комплектное устройство. Для активации датчика и привязки его к автомобилю выполняется процедура <a href="https://alltpms.ru/katalog/privyazka/privyazka-4">«Автоматизированная привязка»</a> (Карточка привязки).</p> | N26: 72 | O26: /market/HUF4050A.jpg | P26: Датчик давления в шине BH Sens ( Huf ) 36118378681 для BMW | Q26: Датчик давления в шине BH Sens ( Huf ) 36118378681 для BMW | R26: Доставка от 1 шт. без предоплаты, Гарантия 2 года | S26: 0 | T26: 0 | U26: 36118378681-353 | V26: 5054208002089 | W26: 622 | X26: BMW | Y26: 315 | Z26: no | AA26: Clamp-in | AB26: 20079, 550-1904, TX-S002, TPS0002, RDE004V21, 1900-20079, 2901-20079, 3040-20079, 3041-20079, 590882-20079, 590880-20079, 20079PVM, 20079PFR, 3040-RDE004, 3041-RDE004, RDE004PVM, RDE004PFR, RDE004PVM, RDE004PFR | AC26: HUF4050A-1.JPG||HUF4050A-2.JPG||HUF4050A-3.JPG||HUF4050A-4.JPG||HUF4050A-5.JPG||HUF4050A-6.JPG||HUF4050A-7.JPG||HUF4050A-8.JPG||HUF4050A-9.JPG||HUF4050A-10.JPG | AD26: 229||92867||241||244||48032 | AE26: 588 | AF26: BMW BH Sens ( Huf ) 36118378681 20079, 550-1904, TX-S002, TPS0002, RDE004V21, 1900-20079, 2901-20079, 3040-20079, 3041-20079, 590882-20079, 590880-20079, 20079PVM, 20079PFR, 3040-RDE004, 3041-RDE004, RDE004PVM, RDE004PFR, RDE004PVM, RDE004PFR 20079, 5501904, TXS002, TPS0002, RDE004V21, 190020079, 290120079, 304020079, 304120079, 59088220079, 59088020079, 20079PVM, 20079PFR, 3040RDE004, 3041RDE004, RDE004PVM, RDE004PFR, RDE004PVM, RDE004PFR | AG26: Купить датчик давления в шине BH Sens ( Huf ) 36118378681 для BMW в Москве с доставкой. Цена от производителя. Большой выбор датчиков. Гарантия.
A27: 302553 | B27: 1 | C27: 8253 | D27: 20 | E27: 36118378682 | F27: =VLOOKUP(E27,Лист1!A1:A306,1,FALSE) -> 36118378682 | G27: Датчик давления в шине BH Sens ( Huf ) 36118378682 для BMW | H27: Купить по низкой цене датчик давления в шинах BH Sens ( Huf ) 36118378682 для BMW с доставкой по Москве или России. | I27: 3750 | J27: Германия | K27: 30 | L27: dk-datchik-davlenia-v-shinah-36118378682-31 | M27: <p> Каталожный номер датчика 36118378682. Передача данных происходит по радиоканалу, задействована частота 433МГц. Компания производитель – <a href="https://alltpms.ru/proizvoditeli-sistem-tpms/beru"> BH Sens ( Huf ) </a>. Страна - Германия.</p><p> Датчики предназначены для авто производства BMW.</p><p></p><p>В зависимости от интенсивности эксплуатации комплекта колес срок службы устройства достигает 7 лет. Срок эксплуатации зависит от продолжительности поездок, поскольку именно во время движения автомобиля датчик расходует заряд элемента питания.</p><p> Предназначенный для установки в автомобили концерна BMW, датчик поступает в продажу с ниппелем. Благодаря этому покупатель получает полностью комплектное устройство. Для активации датчика и привязки его к автомобилю выполняется процедура <a href="https://alltpms.ru/katalog/privyazka/privyazka-4">«Автоматизированная привязка»</a> (Карточка привязки).</p> | N27: 73 | O27: /market/RDE001.jpg | P27: Датчик давления в шине BH Sens ( Huf ) 36118378682 для BMW | Q27: Датчик давления в шине BH Sens ( Huf ) 36118378682 для BMW | R27: Доставка от 1 шт. без предоплаты, Гарантия 2 года | S27: 0 | T27: 0 | U27: 36118378682-31 | V27: 5054208002090 | W27: 622 | X27: BMW | Y27: 433 | Z27: no | AA27: Clamp-in | AB27: 36112360420, 4002, 20080, 550-1902, TX-S001, TPS0001, RDE001V21, RDE002V21, 9014-4002, 9015-4002, 1210-4002, 2210-4002, 2200-4002, 1400-4002, 1401-4002, 4040-4002, 4041-4002, 590914-4002, 590918-4002, 1900-20080, 2901-20080, 4040-20080, 4041-20080, 1400-20080, 1401-20080, 590914-20080, 590918-20080, 4002PFR, 4002PFM, 4002PVM, 20080PVM, 20080PFR, 4040-RDE001, 4041-RDE001, RDE001PVM, RDE001PFR, RDE001PVM, RDE001PFR | AC27: HUF4040-1.JPG||HUF4040-2.JPG||HUF4040-3.JPG||HUF4040-4.JPG||HUF4040-5.JPG||HUF4040-6.JPG||HUF4040-7.JPG||HUF4040-8.JPG||HUF4040-9.JPG||HUF4040-10.JPG | AD27: 229||92867||241||244||48032 | AE27: 588 | AF27: BMW BH Sens ( Huf ) 36118378682 36112360420, 4002, 20080, 550-1902, TX-S001, TPS0001, RDE001V21, RDE002V21, 9014-4002, 9015-4002, 1210-4002, 2210-4002, 2200-4002, 1400-4002, 1401-4002, 4040-4002, 4041-4002, 590914-4002, 590918-4002, 1900-20080, 2901-20080, 4040-20080, 4041-20080, 1400-20080, 1401-20080, 590914-20080, 590918-20080, 4002PFR, 4002PFM, 4002PVM, 20080PVM, 20080PFR, 4040-RDE001, 4041-RDE001, RDE001PVM, RDE001PFR, RDE001PVM, RDE001PFR 36112360420, 4002, 20080, 5501902, TXS001, TPS0001, RDE001V21, RDE002V21, 90144002, 90154002, 12104002, 22104002, 22004002, 14004002, 14014002, 40404002, 40414002, 5909144002, 5909184002, 190020080, 290120080, 404020080, 404120080, 140020080, 140120080, 59091420080, 59091820080, 4002PFR, 4002PFM, 4002PVM, 20080PVM, 20080PFR, 4040RDE001, 4041RDE001, RDE001PVM, RDE001PFR, RDE001PVM, RDE001PFR | AG27: Заказать датчик давления в шине BH Sens ( Huf ) 36118378682 для BMW (Германия) с доставкой по Москве и всей России. Большой выбор датчиков давления в шинах. Гарантия
A28: 302554 | B28: 1 | C28: 8253 | D28: 20 | E28: 36146752128 | F28: =VLOOKUP(E28,Лист1!A1:A306,1,FALSE) -> 36146752128 | G28: Датчик давления в шине BH Sens ( Huf ) 36146752128 для BMW | H28: Купить по низкой цене датчик давления в шинах BH Sens ( Huf ) 36146752128 для BMW с доставкой по Москве или России. | I28: 4500 | J28: Германия | K28: 30 | L28: dk-datchik-davlenia-v-shinah-36146752128-33 | M28: <p> Датчик TPMS, номер по каталогу 36146752128. Совместим с системами большинства марок автомобилей, производства концерна BMW. Производитель устройства - <a href="https://alltpms.ru/proizvoditeli-sistem-tpms/beru"> BH Sens ( Huf ) </a>, страна изготовитель - Германия.</p><p></p><p>Производитель гарантирует нормальную работу устройства на протяжении всего срока службы, составляющего 7-8 лет.</p><p>Датчик специально сконструирован для использования в автомобилях концерна BMW. Комплект поставки устройства: датчик и штуцер. После установки требуется привязка устройства к системе автомобиля. Процедура выполняется по методу <a href="https://alltpms.ru/katalog/privyazka/privyazka-4">«Автоматизированная привязка»</a> (Карточка привязки).</p> | N28: 74 | O28: /market/RDE005.jpg | P28: Датчик давления в шине BH Sens ( Huf ) 36146752128 для BMW | Q28: Датчик давления в шине BH Sens ( Huf ) 36146752128 для BMW | R28: Доставка от 1 шт. без предоплаты, Гарантия 2 года | S28: 0 | T28: 0 | U28: 36146752128-33 | V28: 5054208002091 | W28: 622 | X28: BMW | Y28: 433 | Z28: no | AA28: Clamp-in | AB28: 18YDB000060, YDB000060, YDB000061, 4003, 28082, 550-1903, TX-S001, TPS0001, RDE005V21, RDE003V21, 9014-4003, 9015-4003, 1210-4003, 2210-4003, 2200-4003, 1400-4003, 1401-4003, 4040-4003, 4041-4003, 590914-4003, 590918-4003, 1900-28082, 2901-28082, 4040-28082, 4041-28082, 1400-28082, 1401-28082, 590914-28082, 590918-28082, 4003PFR, 4003PFM, 4003PVM, 28082PVM, 28082PFR, 4040-RDE005, 4041-RDE005, RDE005PVM, RDE005PFR, RDE005PVM, RDE005PFR | AC28: RDE005V21-1.JPG||RDE005V21-2.JPG||RDE005V21-3.JPG||RDE005V21-4.JPG||RDE005V21-5.JPG||RDE005V21-6.JPG||RDE005V21-7.JPG||RDE005V21-8.JPG||RDE005V21-9.JPG||RDE005V21-10.JPG | AD28: 229||92867||241||244||48032 | AE28: 588 | AF28: BMW BH Sens ( Huf ) 36146752128 18YDB000060, YDB000060, YDB000061, 4003, 28082, 550-1903, TX-S001, TPS0001, RDE005V21, RDE003V21, 9014-4003, 9015-4003, 1210-4003, 2210-4003, 2200-4003, 1400-4003, 1401-4003, 4040-4003, 4041-4003, 590914-4003, 590918-4003, 1900-28082, 2901-28082, 4040-28082, 4041-28082, 1400-28082, 1401-28082, 590914-28082, 590918-28082, 4003PFR, 4003PFM, 4003PVM, 28082PVM, 28082PFR, 4040-RDE005, 4041-RDE005, RDE005PVM, RDE005PFR, RDE005PVM, RDE005PFR 18YDB000060, YDB000060, YDB000061, 4003, 28082, 5501903, TXS001, TPS0001, RDE005V21, RDE003V21, 90144003, 90154003, 12104003, 22104003, 22004003, 14004003, 14014003, 40404003, 40414003, 5909144003, 5909184003, 190028082, 290128082, 404028082, 404128082, 140028082, 140128082, 59091428082, 59091828082, 4003PFR, 4003PFM, 4003PVM, 28082PVM, 28082PFR, 4040RDE005, 4041RDE005, RDE005PVM, RDE005PFR, RDE005PVM, RDE005PFR | AG28: Купить датчик давления в шине BH Sens ( Huf ) 36146752128 для BMW в Москве с доставкой. Цена от производителя. Большой выбор датчиков. Гарантия.
A29: 302555 | B29: 1 | C29: 8253 | D29: 20 | E29: 36236781847 | F29: =VLOOKUP(E29,Лист1!A1:A306,1,FALSE) -> 36236781847 | G29: Датчик давления в шине BH Sens ( Huf ) 36236781847 для BMW (Black Edition) | H29: Покупайте датчик давления в шине BH Sens ( Huf ) 36236781847 для BMW (Black Edition) по выгодным ценам | Большой выбор датчиков давления в шине | Осуществляем доставку на всей территории РФ | I29: 4250 | J29: Германия | K29: 30 | L29: dk-datchik-davlenia-v-shinah-36236781847b-28 | M29: <p>Датчик давления в шинах, номер по каталогу 36236781847, передает сигналы с помощью радиоканала. Рабочая частота - 433МГц. Компания производитель <a href="https://alltpms.ru/proizvoditeli-sistem-tpms/beru"> BH Sens ( Huf ) </a>. Страна производства - Германия. Устройства предназначены для установки в колеса автомобилей, выпускаемых концерном BMW.</p><p></p><p> При условии установки на специализированных СТО, срок службы устройства составляет до 7 лет.</p><p>Конструктивные особенности данного датчика гарантируют его полную совместимость с системами авто концерна BMW. Датчик поставляется в комплекте с ниппелем, что заметно облегчает установку и не требует покупки дополнительных деталей. Материал ниппеля - металл. После установки датчик 36236781847 требует привязки к авто. Привязка производится по методике <a href="https://alltpms.ru/katalog/privyazka/privyazka-4">«Автоматизированная привязка»</a> (Карточка привязки).</p> | N29: 85 | O29: /market/RDE048B.jpg | P29: Датчик давления в шине BH Sens ( Huf ) 36236781847 для BMW (Black Edition) | Q29: Датчик давления в шине BH Sens ( Huf ) 36236781847 для BMW (Black Edition) | R29: Доставка от 1 шт. без предоплаты, Гарантия 2 года | S29: 0 | T29: 0 | U29: 36236781847b-28 | V29: 5054208002092 | W29: 622 | X29: BMW | Y29: 433 | Z29: no | AA29: Clamp-in | AB29: 36236771034, 36236779490, 36236798726, 4007, 20083, 550-1908, TX-S003, TPS0003, RDE008V21, 9014-4007, 9015-4007, 1210-4007, 2210-4007, 2200-4007, 1400-4007, 1401-4007, 4040-4007, 4041-4007, 590914-4007, 590918-4007, 1900-20083, 2901-20083, 4040-20083, 4041-20083, 1400-20083, 1401-20083, 590914-20083, 590918-20083, 4007PFR, 4007PFM, 4007PVM, 20083PVM, 20083PFR, 4040-RDE008, 4041-RDE008, RDE008PVM, RDE008PFR, RDE008PVM, RDE008PFR | AC29: HUF4040_B-1.JPG||HUF4040_B-2.JPG||HUF4040_B-3.JPG||HUF4040_B-4.JPG||HUF4040_B-5.JPG||HUF4040_B-6.JPG||HUF4040_B-7.JPG||HUF4040_B-8.JPG||HUF4040_B-9.JPG||HUF4040_B-10.JPG | AD29: 229||92867||241||244||48032 | AE29: 588 | AG29: Покупайте датчик давления в шине BH Sens ( Huf ) 36236781847 для BMW (Black Edition) по выгодным ценам | Большой выбор датчиков давления в шине | Осуществляем доставку на всей территории РФ
A30: 302556 | B30: 1 | C30: 8253 | D30: 20 | E30: 36236781847 | F30: =VLOOKUP(E30,Лист1!A1:A306,1,FALSE) -> 36236781847 | G30: Датчик давления в шине BH Sens ( Huf, Германия ) 36236781847 для BMW | H30: Покупайте датчик давления в шине BH Sens ( Huf, Германия ) 36236781847 для BMW по выгодным ценам | Большой выбор датчиков давления в шине | Осуществляем доставку на всей территории РФ | I30: 3750 | J30: Германия | K30: 30 | L30: dk-datchik-davlenia-v-shinah-36236781847-28 | M30: <p> Датчик TPMS, номер по каталогу 36236781847. Совместим с системами большинства марок автомобилей, производства концерна BMW. Производитель устройства - <a href="https://alltpms.ru/proizvoditeli-sistem-tpms/beru"> BH Sens ( Huf ) </a>, страна изготовитель - Германия.</p><p></p><p>Производитель гарантирует нормальную работу устройства на протяжении всего срока службы, составляющего 7-8 лет.</p><p>Датчик специально сконструирован для использования в автомобилях концерна BMW. Комплект поставки устройства: датчик и штуцер. После установки требуется привязка устройства к системе автомобиля. Процедура выполняется по методу <a href="https://alltpms.ru/katalog/privyazka/privyazka-4">«Автоматизированная привязка»</a> (Карточка привязки).</p> | N30: 86 | O30: /market/RDE048.jpg | P30: Датчик давления в шине BH Sens ( Huf ) 36236781847 для BMW | Q30: Датчик давления в шине BH Sens ( Huf ) 36236781847 для BMW | R30: Доставка от 1 шт. без предоплаты, Гарантия 2 года | S30: 0 | T30: 0 | U30: 36236781847-28 | V30: 5054208002093 | W30: 622 | X30: BMW | Y30: 433 | Z30: no | AA30: Clamp-in | AB30: 36236771034, 36236779490, 36236798726, 4007, 20083, 550-1908, TX-S003, TPS0003, RDE008V21, 9014-4007, 9015-4007, 1210-4007, 2210-4007, 2200-4007, 1400-4007, 1401-4007, 4040-4007, 4041-4007, 590914-4007, 590918-4007, 1900-20083, 2901-20083, 4040-20083, 4041-20083, 1400-20083, 1401-20083, 590914-20083, 590918-20083, 4007PFR, 4007PFM, 4007PVM, 20083PVM, 20083PFR, 4040-RDE008, 4041-RDE008, RDE008PVM, RDE008PFR, RDE008PVM, RDE008PFR | AC30: HUF4040-1.JPG||HUF4040-2.JPG||HUF4040-3.JPG||HUF4040-4.JPG||HUF4040-5.JPG||HUF4040-6.JPG||HUF4040-7.JPG||HUF4040-8.JPG||HUF4040-9.JPG||HUF4040-10.JPG | AD30: 229||92867||241||244||48032 | AE30: 588 | AG30: Покупайте датчик давления в шине BH Sens ( Huf, Германия ) 36236781847 для BMW по выгодным ценам | Большой выбор датчиков давления в шине | Осуществляем доставку на всей территории РФ
A31: 302568 | B31: 1 | C31: 8253 | D31: 20 | E31: 05154876AA | F31: =VLOOKUP(E31,Лист1!A1:A306,1,FALSE) -> 05154876AA | G31: Датчик давления в шине для Fiat/Alfa/Chrysler/Dodge/Jeep 05154876AA Оригинал | H31: Купить по низкой цене оригинальный датчик давления в шинах для Fiat/Alfa/Chrysler/Dodge/Jeep 05154876AA с доставкой по Москве или России. | I31: 7500 | J31: Англия | K31: 30 | L31: dk-datchik-davlenia-v-shinah-05154876aa-213 | M31: <p>Датчик 05154876AA контроля давления в шинах. Передача данных реализована по радиоканалу. Используемая частота - 433МГц. Для автомобилей Fiat/Alfa/Chrysler/Dodge/Jeep. Страна производства - Англия.</p><p> Датчики устанавливаются в автомобили, выпускаемые концерном Fiat/Alfa/Chrysler/Dodge/Jeep.</p><p></p><p> При условии правильной установки и эксплуатации, срок работы составит 6 лет и более. Срок варьируется в зависимости от интенсивности эксплуатации, частоты и продолжительности поездок.</p><p>Данный датчик 05154876AA сконструирован в расчете на установку в автомобили концерна Fiat/Alfa/Chrysler/Dodge/Jeep. В продажу поступают готовые комплекты. В комплект входит сам датчик и ниппель. После установки датчик необходимо активировать. Процесс выполняется с использованием методики <a href="https://alltpms.ru/katalog/privyazka/privyazka-4">«Автоматическая привязка»</a> (Карточка привязки).</p> | N31: 79 | O31: /market/A0030.jpg | P31: Датчик давления в шине для Fiat/Alfa/Chrysler/Dodge/Jeep 05154876AA Оригинал | Q31: Датчик давления в шине для Fiat/Alfa/Chrysler/Dodge/Jeep 05154876AA Оригинал | R31: Доставка от 1 шт. без предоплаты, Гарантия 2 года | S31: 0 | T31: 0 | U31: 05154876aa-213 | V31: 5054208002105 | W31: 625 | X31: Fiat/Alfa/Chrysler/Dodge/Jeep | Y31: 433 | Z31: yes | AA31: Clamp-in | AB31: 95518233, 670002790, 670034786, 670106084, 05154876AC, 3009, 20284, TX-S033L/R, TPS0033L/R, 9014-3009, 9015-3009, 1210-3009, 2210-3009, 2200-3009, 1400-3009, 1401-3009, 4040-3009, 4041-3009, 590914-3009, 590918-3009, 1900-20284, 2901-20284, 4040-20284, 4041-20284, 1400-20284, 1401-20284, 590914-20284, 590918-20284, 3009PFR, 3009PFM, 3009PVM, 20284PVM, 20284PFR | AC31: 05154876AA-1.JPG||05154876AA-2.JPG||05154876AA-3.JPG||05154876AA-4.JPG||05154876AA-5.JPG||05154876AA-6.JPG||05154876AA-7.JPG||05154876AA-8.JPG||05154876AA-9.JPG||05154876AA-10.JPG | AD31: 211||48023||92872 | AE31: 586 | AF31: Fiat/Alfa/Chrysler/Dodge/Jeep Schrader 05154876AA 95518233, 670002790, 670034786, 670106084, 05154876AC, 3009, 20284, TX-S033L/R, TPS0033L/R, 9014-3009, 9015-3009, 1210-3009, 2210-3009, 2200-3009, 1400-3009, 1401-3009, 4040-3009, 4041-3009, 590914-3009, 590918-3009, 1900-20284, 2901-20284, 4040-20284, 4041-20284, 1400-20284, 1401-20284, 590914-20284, 590918-20284, 3009PFR, 3009PFM, 3009PVM, 20284PVM, 20284PFR 95518233, 670002790, 670034786, 670106084, 05154876AC, 3009, 20284, TXS033L/R, TPS0033L/R, 90143009, 90153009, 12103009, 22103009, 22003009, 14003009, 14013009, 40403009, 40413009, 5909143009, 5909183009, 190020284, 290120284, 404020284, 404120284, 140020284, 140120284, 59091420284, 59091820284, 3009PFR, 3009PFM, 3009PVM, 20284PVM, 20284PFR Оригинал | AG31: Купить оригинальный датчик давления в шине для Fiat/Alfa/Chrysler/Dodge/Jeep 05154876AA в Москве с доставкой. Цена от производителя. Большой выбор датчиков. Гарантия.
A32: 302569 | B32: 1 | C32: 8253 | D32: 20 | E32: 05154876AA | F32: =VLOOKUP(E32,Лист1!A1:A306,1,FALSE) -> 05154876AA | G32: Датчик давления в шине BH Sens ( Huf ) 05154876AA для Fiat/Alfa/Chrysler/Dodge/Jeep (Black Edition) | H32: Покупайте датчик давления в шине BH Sens ( Huf ) 05154876AA для Fiat/Alfa/Chrysler/Dodge/Jeep (Black Edition) по выгодным ценам | Большой выбор датчиков давления в шине | Осуществляем доставку на всей территории РФ | I32: 3750 | J32: Германия | K32: 30 | L32: dk-datchik-davlenia-v-shinah-05154876aab-9 | M32: <p>Датчик, номер по каталогу запчастей 05154876AA. Предназначен для контроля давления в шинах. Передача данных осуществляется посредством радиосигнала на частоте 433МГц. Компания производитель датчика - <a href="https://alltpms.ru/proizvoditeli-sistem-tpms/beru"> BH Sens ( Huf ) </a>. Место производства - Германия.</p><p>Правильно установленный датчик гарантировано проработает 7 лет. В каждом конкретном случае срок службы может изменяться. Он зависит от условий эксплуатации, длительности поездок, их частоты.</p><p>Предназначенный для установки в колеса автомобилей большинства моделей концерна Fiat/Alfa/Chrysler/Dodge/Jeep, датчик поставляется в комплекте с ниппелем. Покупатель получает комплектное устройство. После установки датчик 05154876AA активируется, используется метод <a href="https://alltpms.ru/katalog/privyazka/privyazka-4">«Автоматическая привязка»</a> (Карточка привязки).</p> | N32: 80 | O32: /market/HUF1410B.jpg | P32: Датчик давления в шине BH Sens ( Huf ) 05154876AA для Fiat/Alfa/Chrysler/Dodge/Jeep (Black Edition) | Q32: Датчик давления в шине BH Sens ( Huf ) 05154876AA для Fiat/Alfa/Chrysler/Dodge/Jeep (Black Edition) | R32: Доставка от 1 шт. без предоплаты, Гарантия 2 года | S32: 0 | T32: 1 | U32: 05154876aab-9 | V32: 5054208002106 | W32: 622 | X32: Fiat/Alfa/Chrysler/Dodge/Jeep | Y32: 433 | Z32: no | AA32: Clamp-in | AB32: 95518233, 670002790, 670034786, 670106084, 05154876AC, 3009, 20284, TX-S033L/R, TPS0033L/R, 9014-3009, 9015-3009, 1210-3009, 2210-3009, 2200-3009, 1400-3009, 1401-3009, 4040-3009, 4041-3009, 590914-3009, 590918-3009, 1900-20284, 2901-20284, 4040-20284, 4041-20284, 1400-20284, 1401-20284, 590914-20284, 590918-20284, 3009PFR, 3009PFM, 3009PVM, 20284PVM, 20284PFR | AC32: HUF1400_B-1.JPG||HUF1400_B-2.JPG||HUF1400_B-3.JPG||HUF1400_B-4.JPG||HUF1400_B-5.JPG||HUF1400_B-6.JPG||HUF1400_B-7.JPG||HUF1400_B-8.JPG||HUF1400_B-9.JPG||HUF1400_B-10.JPG | AD32: 211||48023||92872 | AE32: 586 | AG32: Покупайте датчик давления в шине BH Sens ( Huf ) 05154876AA для Fiat/Alfa/Chrysler/Dodge/Jeep (Black Edition) по выгодным ценам | Большой выбор датчиков давления в шине | Осуществляем доставку на всей территории РФ
A33: 302570 | B33: 1 | C33: 8253 | D33: 20 | E33: 05154876AA | F33: =VLOOKUP(E33,Лист1!A1:A306,1,FALSE) -> 05154876AA | G33: Датчик давления в шине BH Sens ( Huf, Германия ) 05154876AA для Fiat/Alfa/Chrysler/Dodge/Jeep | H33: Покупайте датчик давления в шине BH Sens ( Huf, Германия ) 05154876AA для Fiat/Alfa/Chrysler/Dodge/Jeep по выгодным ценам | Большой выбор датчиков давления в шине | Осуществляем доставку на всей территории РФ | I33: 3250 | J33: Германия | K33: 30 | L33: dk-datchik-davlenia-v-shinah-05154876aa-9 | M33: <p>Датчик, номер по каталогу запчастей 05154876AA. Предназначен для контроля давления в шинах. Передача данных осуществляется посредством радиосигнала на частоте 433МГц. Компания производитель датчика - <a href="https://alltpms.ru/proizvoditeli-sistem-tpms/beru"> BH Sens ( Huf ) </a>. Место производства - Германия.</p><p>Правильно установленный датчик гарантировано проработает 7 лет. В каждом конкретном случае срок службы может изменяться. Он зависит от условий эксплуатации, длительности поездок, их частоты.</p><p>Предназначенный для установки в колеса автомобилей большинства моделей концерна Fiat/Alfa/Chrysler/Dodge/Jeep, датчик поставляется в комплекте с ниппелем. Покупатель получает комплектное устройство. После установки датчик 05154876AA активируется, используется метод <a href="https://alltpms.ru/katalog/privyazka/privyazka-4">«Автоматическая привязка»</a> (Карточка привязки).</p> | N33: 81 | O33: /market/HUF1410.jpg | P33: Датчик давления в шине BH Sens ( Huf, Германия ) 05154876AA для Fiat/Alfa/Chrysler/Dodge/Jeep | Q33: Датчик давления в шине BH Sens ( Huf, Германия ) 05154876AA для Fiat/Alfa/Chrysler/Dodge/Jeep | R33: Доставка от 1 шт. без предоплаты, Гарантия 2 года | S33: 0 | T33: 1 | U33: 05154876aa-9 | V33: 5054208002107 | W33: 622 | X33: Fiat/Alfa/Chrysler/Dodge/Jeep | Y33: 433 | Z33: no | AA33: Clamp-in | AB33: 95518233, 670002790, 670034786, 670106084, 05154876AC, 3009, 20284, TX-S033L/R, TPS0033L/R, 9014-3009, 9015-3009, 1210-3009, 2210-3009, 2200-3009, 1400-3009, 1401-3009, 4040-3009, 4041-3009, 590914-3009, 590918-3009, 1900-20284, 2901-20284, 4040-20284, 4041-20284, 1400-20284, 1401-20284, 590914-20284, 590918-20284, 3009PFR, 3009PFM, 3009PVM, 20284PVM, 20284PFR | AC33: HUF1400-1.JPG||HUF1400-2.JPG||HUF1400-3.JPG||HUF1400-4.JPG||HUF1400-5.JPG||HUF1400-6.JPG||HUF1400-7.JPG||HUF1400-8.JPG||HUF1400-9.JPG||HUF1400-10.JPG | AD33: 211||48023||92872 | AE33: 586 | AG33: Покупайте датчик давления в шине BH Sens ( Huf, Германия ) 05154876AA для Fiat/Alfa/Chrysler/Dodge/Jeep по выгодным ценам | Большой выбор датчиков давления в шине | Осуществляем доставку на всей территории РФ
A34: 302571 | B34: 1 | C34: 8253 | D34: 20 | E34: 06421-S3V-A04 | F34: =VLOOKUP(E34,Лист1!A1:A306,1,FALSE) -> 06421-S3V-A04 | G34: Датчик давления в шине (только США) BH Sens ( Huf ) 06421-S3V-A04 ( 06421S3VA04 ) для Honda/Acura | H34: Купить по низкой цене датчик давления в шинах BH Sens ( Huf ) 06421-S3V-A04 ( 06421S3VA04 ) для Honda/Acura с доставкой по Москве или России. | I34: 3750 | J34: Германия | K34: 30 | L34: dk-datchik-davlenia-v-shinah-06421-s3v-a04-347 | M34: <p>Датчик давления в шинах, номер по каталогу 06421-S3V-A04, передает сигналы с помощью радиоканала. Рабочая частота - 315МГц. Компания производитель <a href="https://alltpms.ru/proizvoditeli-sistem-tpms/beru"> BH Sens ( Huf ) </a>. Страна производства - Германия. Устройства предназначены для установки в колеса автомобилей, выпускаемых концерном Honda/Acura.</p><p></p><p> При условии установки на специализированных СТО, срок службы устройства составляет до 7 лет.</p><p>Конструктивные особенности данного датчика гарантируют его полную совместимость с системами авто концерна Honda/Acura. Датчик поставляется в комплекте с ниппелем, что заметно облегчает установку и не требует покупки дополнительных деталей. Материал ниппеля - металл. После установки датчик 06421-S3V-A04 требует привязки к авто. Привязка производится по методике <a href="https://alltpms.ru/katalog/privyazka/privyazka-4">«Автоматическая привязка»</a> (Карточка привязки).</p> | N34: 85 | O34: /market/HUF4050A.jpg | P34: Датчик давления в шине BH Sens ( Huf ) 06421-S3V-A04 ( 06421S3VA04 ) для Honda/Acura | Q34: Датчик давления в шине BH Sens ( Huf ) 06421-S3V-A04 ( 06421S3VA04 ) для Honda/Acura | R34: Доставка от 1 шт. без предоплаты, Гарантия 2 года | S34: 0 | T34: 0 | U34: 06421-s3v-a04-347 | V34: 5054208002108 | W34: 622 | X34: Honda/Acura | Y34: 315 | Z34: no | AA34: Clamp-in | AB34: 06421-S3V-A00, 06421-S3V-A02, 06421-S3V-A03, 42753-SHJ-A53, 42753-SHJ-A54, 28981, TX-S015, TPS0015, 1900-28981, 2901-28981, 3040-28981, 3041-28981, 590882-28981, 590880-28981, 28981PVM, 28981PFR | AC34: HUF4050A-1.JPG||HUF4050A-2.JPG||HUF4050A-3.JPG||HUF4050A-4.JPG||HUF4050A-5.JPG||HUF4050A-6.JPG||HUF4050A-7.JPG||HUF4050A-8.JPG||HUF4050A-9.JPG||HUF4050A-10.JPG | AD34: 229||92867||241||244||48032 | AE34: 586 | AF34: Honda/Acura BH Sens ( Huf ) 06421-S3V-A04 ( 06421S3VA04 ) 06421-S3V-A00, 06421-S3V-A02, 06421-S3V-A03, 42753-SHJ-A53, 42753-SHJ-A54, 28981, TX-S015, TPS0015, 1900-28981, 2901-28981, 3040-28981, 3041-28981, 590882-28981, 590880-28981, 28981PVM, 28981PFR 06421S3VA00, 06421S3VA02, 06421S3VA03, 42753SHJA53, 42753SHJA54, 28981, TXS015, TPS0015, 190028981, 290128981, 304028981, 304128981, 59088228981, 59088028981, 28981PVM, 28981PFR | AG34: Заказать датчик давления в шине (только США) BH Sens ( Huf ) 06421-S3V-A04 ( 06421S3VA04 ) для Honda/Acura с доставкой по Москве и всей России, большой выбор датчиков. Гарантия
A35: 302579 | B35: 1 | C35: 8253 | D35: 20 | E35: 1K0907253D | F35: =VLOOKUP(E35,Лист1!A1:A306,1,FALSE) -> 1K0907253D | G35: Датчик давления в шине (только США) BH Sens ( Huf ) 1K0907253D для VAG/Porsche | H35: Купить по низкой цене датчик давления в шинах BH Sens ( Huf ) 1K0907253D для VAG/Porsche с доставкой по Москве или России. | I35: 3750 | J35: Германия | K35: 30 | L35: dk-datchik-davlenia-v-shinah-1k0907253d-351 | M35: <p>Датчик, каталожный номер 1K0907253D. Передача данных производится посредством радиосигнала. Частота работы - 315МГц. Производитель – компания <a href="https://alltpms.ru/proizvoditeli-sistem-tpms/beru"> BH Sens ( Huf ) </a>. Страна-производитель - Германия.</p><p> Срок службы устройства варьируется и может достигать 7 лет. Данный показатель во многом зависит от интенсивности использования авто и условий его эксплуатации.</p><p> Конструктивные особенности датчика позволяют использовать его на большинстве марок авто производства VAG/Porsche. Комплект поставки – датчик и ниппель. Материал ниппеля - металл. Комплект полностью готов к установке. Данный датчик, номер 1K0907253D требует привязки к системе автомобиля. Для этого используется процедура <a href="https://alltpms.ru/katalog/privyazka/privyazka-4">«Автоматизированная привязка»</a> (Карточка привязки).</p> | N35: 82 | O35: /market/HUF4050A.jpg | P35: Датчик давления в шине BH Sens ( Huf ) 1K0907253D для VAG/Porsche | Q35: Датчик давления в шине BH Sens ( Huf ) 1K0907253D для VAG/Porsche | R35: Доставка от 1 шт. без предоплаты, Гарантия 2 года | S35: 0 | T35: 0 | U35: 1k0907253d-351 | V35: 5054208002116 | W35: 622 | X35: VAG/Porsche | Y35: 315 | Z35: no | AA35: Clamp-in | AB35: 1K0907253E, 20088, TX-S036, TPS0036, RDE099V21, 1900-20088, 2901-20088, 3040-20088, 3041-20088, 590882-20088, 590880-20088, 20088PVM, 20088PFR, 3040-RDE099, 3041-RDE099, RDE099PVM, RDE099PFR, RDE099PVM, RDE099PFR | AC35: HUF4050A-1.JPG||HUF4050A-2.JPG||HUF4050A-3.JPG||HUF4050A-4.JPG||HUF4050A-5.JPG||HUF4050A-6.JPG||HUF4050A-7.JPG||HUF4050A-8.JPG||HUF4050A-9.JPG||HUF4050A-10.JPG | AD35: 223 | AE35: 588 | AF35: VAG/Porsche BH Sens ( Huf ) 1K0907253D 1K0907253E, 20088, TX-S036, TPS0036, RDE099V21, 1900-20088, 2901-20088, 3040-20088, 3041-20088, 590882-20088, 590880-20088, 20088PVM, 20088PFR, 3040-RDE099, 3041-RDE099, RDE099PVM, RDE099PFR, RDE099PVM, RDE099PFR 1K0907253E, 20088, TXS036, TPS0036, RDE099V21, 190020088, 290120088, 304020088, 304120088, 59088220088, 59088020088, 20088PVM, 20088PFR, 3040RDE099, 3041RDE099, RDE099PVM, RDE099PFR, RDE099PVM, RDE099PFR | AG35: Заказать датчик давления в шине (только США) BH Sens ( Huf ) 1K0907253D для VAG/Porsche с доставкой по Москве и всей России. Большой выбор датчиков давления в шинах. Гарантия
A36: 302684 | B36: 1 | C36: 8253 | D36: 20 | E36: 42753-SHJ-A82 | F36: =VLOOKUP(E36,Лист1!A1:A306,1,FALSE) -> 42753-SHJ-A82 | G36: Датчик давления в шине (только США) BH Sens ( Huf ) 42753-SHJ-A82 ( 42753SHJA82 ) для Honda/Acura | H36: Купить датчик давления в шине (только США) BH Sens ( Huf ) 42753-SHJ-A82 ( 42753SHJA82 ) для Honda/Acura в Москве с доставкой. Цена от производителя. Большой выбор датчиков. Гарантия. | I36: 3750 | J36: Германия | K36: 30 | L36: dk-datchik-davlenia-v-shinah-42753-shj-a82-376 | M36: <p>Датчик давления в шинах, номер по каталогу 42753-SHJ-A82, передает сигналы с помощью радиоканала. Рабочая частота - 315МГц. Компания производитель <a href="https://alltpms.ru/proizvoditeli-sistem-tpms/beru"> BH Sens ( Huf ) </a>. Страна производства - Германия. Устройства предназначены для установки в колеса автомобилей, выпускаемых концерном Honda/Acura.</p><p></p><p> При условии установки на специализированных СТО, срок службы устройства составляет до 7 лет.</p><p>Конструктивные особенности данного датчика гарантируют его полную совместимость с системами авто концерна Honda/Acura. Датчик поставляется в комплекте с ниппелем, что заметно облегчает установку и не требует покупки дополнительных деталей. Материал ниппеля - металл. После установки датчик 42753-SHJ-A82 требует привязки к авто. Привязка производится по методике <a href="https://alltpms.ru/katalog/privyazka/privyazka-6">«Активация диагностикой и активатором»</a> (Карточка привязки).</p> | N36: 87 | O36: /market/HUF4050A.jpg | P36: Датчик давления в шине BH Sens ( Huf ) 42753-SHJ-A82 ( 42753SHJA82 ) для Honda/Acura | Q36: Датчик давления в шине BH Sens ( Huf ) 42753-SHJ-A82 ( 42753SHJA82 ) для Honda/Acura | R36: Доставка от 1 шт. без предоплаты, Гарантия 2 года | S36: 0 | T36: 0 | U36: 42753-shj-a82-376 | V36: 5054208002221 | W36: 622 | X36: Honda/Acura | Y36: 315 | Z36: no | AA36: Clamp-in | AB36: RDE205V21, 3040-RDE205, 3041-RDE205, RDE205PVM, RDE205PFR, RDE205PVM, RDE205PFR | AC36: HUF4050A-1.JPG||HUF4050A-2.JPG||HUF4050A-3.JPG||HUF4050A-4.JPG||HUF4050A-5.JPG||HUF4050A-6.JPG||HUF4050A-7.JPG||HUF4050A-8.JPG||HUF4050A-9.JPG||HUF4050A-10.JPG | AD36: 278057 | AE36: 592 | AF36: Honda/Acura BH Sens ( Huf ) 42753-SHJ-A82 ( 42753SHJA82 ) RDE205V21, 3040-RDE205, 3041-RDE205, RDE205PVM, RDE205PFR, RDE205PVM, RDE205PFR RDE205V21, 3040RDE205, 3041RDE205, RDE205PVM, RDE205PFR, RDE205PVM, RDE205PFR | AG36: Купить датчик давления в шине BH Sens ( Huf ) 42753-SHJ-A82 ( 42753SHJA82 ) для Honda/Acura в Москве с доставкой. Цена от производителя. Большой выбор датчиков. Гарантия.
A37: 302685 | B37: 1 | C37: 8253 | D37: 20 | E37: 42753-SNA-A83 | F37: =VLOOKUP(E37,Лист1!A1:A306,1,FALSE) -> 42753-SNA-A83 | G37: Датчик давления в шине (только США) BH Sens ( Huf ) 42753-SNA-A83 ( 42753SNAA83 ) для Honda/Acura | H37: Купить датчик давления в шине (только США) BH Sens ( Huf ) 42753-SNA-A83 ( 42753SNAA83 ) для Honda/Acura в Москве с доставкой. Цена от производителя. Большой выбор датчиков. Гарантия. | I37: 3750 | J37: Германия | K37: 30 | L37: dk-datchik-davlenia-v-shinah-42753-sna-a83-345 | M37: <p>Датчик 42753-SNA-A83 контроля давления в шинах. Передача данных реализована по радиоканалу. Используемая частота - 315МГц. Производит устройства компания <a href="https://alltpms.ru/proizvoditeli-sistem-tpms/beru"> BH Sens ( Huf ) </a>. Страна производства - Германия.</p><p> Датчики устанавливаются в автомобили, выпускаемые концерном Honda/Acura.</p><p></p><p> При условии правильной установки и эксплуатации, срок работы составит 6 лет и более. Срок варьируется в зависимости от интенсивности эксплуатации, частоты и продолжительности поездок.</p><p>Данный датчик 42753-SNA-A83 сконструирован в расчете на установку в автомобили концерна Honda/Acura. В продажу поступают готовые комплекты. В комплект входит сам датчик и ниппель. После установки датчик необходимо активировать. Процесс выполняется с использованием методики <a href="https://alltpms.ru/katalog/privyazka/privyazka-6">«Активация диагностикой и активатором»</a> (Карточка привязки).</p> | N37: 88 | O37: /market/HUF4050A.jpg | P37: Датчик давления в шине BH Sens ( Huf ) 42753-SNA-A83 ( 42753SNAA83 ) для Honda/Acura | Q37: Датчик давления в шине BH Sens ( Huf ) 42753-SNA-A83 ( 42753SNAA83 ) для Honda/Acura | R37: Доставка от 1 шт. без предоплаты, Гарантия 2 года | S37: 0 | T37: 0 | U37: 42753-sna-a83-345 | V37: 5054208002222 | W37: 622 | X37: Honda/Acura | Y37: 315 | Z37: no | AA37: Clamp-in | AB37: 42753-SNA-A81, 42753-SNA-A84, 42753-TR0-A81, 42753-TR3-A81, 28720, TX-S016, TPS0016, 1900-28720, 2901-28720, 3040-28720, 3041-28720, 590882-28720, 590880-28720, 28720PVM, 28720PFR | AC37: HUF4050A-1.JPG||HUF4050A-2.JPG||HUF4050A-3.JPG||HUF4050A-4.JPG||HUF4050A-5.JPG||HUF4050A-6.JPG||HUF4050A-7.JPG||HUF4050A-8.JPG||HUF4050A-9.JPG||HUF4050A-10.JPG | AD37: 278057 | AE37: 592 | AF37: Honda/Acura BH Sens ( Huf ) 42753-SNA-A83 ( 42753SNAA83 ) 42753-SNA-A81, 42753-SNA-A84, 42753-TR0-A81, 42753-TR3-A81, 28720, TX-S016, TPS0016, 1900-28720, 2901-28720, 3040-28720, 3041-28720, 590882-28720, 590880-28720, 28720PVM, 28720PFR 42753SNAA81, 42753SNAA84, 42753TR0A81, 42753TR3A81, 28720, TXS016, TPS0016, 190028720, 290128720, 304028720, 304128720, 59088228720, 59088028720, 28720PVM, 28720PFR | AG37: Купить датчик давления в шине BH Sens ( Huf ) 42753-SNA-A83 ( 42753SNAA83 ) для Honda/Acura в Москве с доставкой. Цена от производителя. Большой выбор датчиков. Гарантия.
A38: 302686 | B38: 1 | C38: 8253 | D38: 20 | E38: 42753-STK-A04 | F38: =VLOOKUP(E38,Лист1!A1:A306,1,FALSE) -> 42753-STK-A04 | G38: Датчик давления в шине для (только США) Honda/Acura 42753-STK-A04 ( 42753STKA04 ) Оригинал | H38: Купить по низкой цене оригинальный датчик давления в шинах для Honda/Acura 42753-STK-A04 ( 42753STKA04 ) с доставкой по Москве или России. | I38: 6750 | J38: Япония | K38: 30 | L38: dk-datchik-davlenia-v-shinah-42753-stk-a04-438 | M38: <p>Датчик, номер по каталогу запчастей 42753-STK-A04. Предназначен для контроля давления в шинах. Передача данных осуществляется посредством радиосигнала на частоте 315МГц. Компания производитель автомобиля - Honda/Acura. Место производства - Япония.</p><p>Правильно установленный датчик гарантировано проработает 7 лет. В каждом конкретном случае срок службы может изменяться. Он зависит от условий эксплуатации, длительности поездок, их частоты.</p><p>Предназначенный для установки в колеса автомобилей большинства моделей концерна Honda/Acura, датчик поставляется в комплекте с ниппелем. Покупатель получает комплектное устройство. После установки датчик 42753-STK-A04 активируется, используется метод <a href="https://alltpms.ru/katalog/privyazka/privyazka-4">«Автоматическая привязка»</a> (Карточка привязки).</p> | N38: 96 | O38: /market/STK.jpg | P38: Датчик давления в шине для (только США) Honda/Acura 42753-STK-A04 ( 42753STKA04 ) Оригинал | Q38: Датчик давления в шине для (только США) Honda/Acura 42753-STK-A04 ( 42753STKA04 ) Оригинал | R38: Доставка от 1 шт. без предоплаты, Гарантия 2 года | S38: 0 | T38: 0 | U38: 42753-stk-a04-438 | V38: 5054208002223 | W38: 626 | X38: Honda/Acura | Y38: 315 | Z38: yes | AA38: Clamp-in | AB38: 42753-STK-A02, 42753-STK-A03, 42753-TL2-A51, 42753-TL2-A52, 550-0206, 550-0201, 550-0203, PMV-107G, TX-S072, TPS0072 | AC38: 42753-STK-A04-1.JPG||42753-STK-A04-2.JPG||42753-STK-A04-3.JPG||42753-STK-A04-4.JPG||42753-STK-A04-5.JPG||42753-STK-A04-6.JPG||42753-STK-A04-7.JPG||42753-STK-A04-8.JPG||42753-STK-A04-9.JPG||42753-STK-A04-10.JPG | AD38: 277531 | AE38: 586 | AF38: Honda/Acura Pacific 42753-STK-A04 ( 42753STKA04 ) 42753-STK-A02, 42753-STK-A03, 42753-TL2-A51, 42753-TL2-A52, 550-0206, 550-0201, 550-0203, PMV-107G, TX-S072, TPS0072 42753STKA02, 42753STKA03, 42753TL2A51, 42753TL2A52, 5500206, 5500201, 5500203, PMV107G, TXS072, TPS0072 Оригинал | AG38: Купить оригинальный датчик давления в шине для Honda/Acura 42753-STK-A04 ( 42753STKA04 ) в Москве с доставкой. Цена от производителя. Большой выбор датчиков. Гарантия.
A39: 302687 | B39: 1 | C39: 8253 | D39: 20 | E39: 42753-STK-A04 | F39: =VLOOKUP(E39,Лист1!A1:A306,1,FALSE) -> 42753-STK-A04 | G39: Датчик давления в шине (только США) BH Sens ( Huf ) 42753-STK-A04 ( 42753STKA04 ) для Honda/Acura | H39: Купить по низкой цене датчик давления в шинах BH Sens ( Huf ) 42753-STK-A04 ( 42753STKA04 ) для Honda/Acura с доставкой по Москве или России. | I39: 3750 | J39: Германия | K39: 30 | L39: dk-datchik-davlenia-v-shinah-42753-stk-a04-348 | M39: <p>Датчик, каталожный номер 42753-STK-A04. Передача данных производится посредством радиосигнала. Частота работы - 315МГц. Производитель – компания <a href="https://alltpms.ru/proizvoditeli-sistem-tpms/beru"> BH Sens ( Huf ) </a>. Страна-производитель - Германия.</p><p> Срок службы устройства варьируется и может достигать 7 лет. Данный показатель во многом зависит от интенсивности использования авто и условий его эксплуатации.</p><p> Конструктивные особенности датчика позволяют использовать его на большинстве марок авто производства Honda/Acura. Комплект поставки – датчик и ниппель. Материал ниппеля - металл. Комплект полностью готов к установке. Данный датчик, номер 42753-STK-A04 требует привязки к системе автомобиля. Для этого используется процедура <a href="https://alltpms.ru/katalog/privyazka/privyazka-4">«Автоматическая привязка»</a> (Карточка привязки).</p> | N39: 97 | O39: /market/HUF4050A.jpg | P39: Датчик давления в шине BH Sens ( Huf ) 42753-STK-A04 ( 42753STKA04 ) для Honda/Acura | Q39: Датчик давления в шине BH Sens ( Huf ) 42753-STK-A04 ( 42753STKA04 ) для Honda/Acura | R39: Доставка от 1 шт. без предоплаты, Гарантия 2 года | S39: 0 | T39: 0 | U39: 42753-stk-a04-348 | V39: 5054208002224 | W39: 622 | X39: Honda/Acura | Y39: 315 | Z39: no | AA39: Clamp-in | AB39: 42753-STK-A02, 42753-STK-A03, 42753-TL2-A51, 42753-TL2-A52, 550-0206, 550-0201, 550-0203, PMV-107G, TX-S072, TPS0072 | AC39: HUF4050A-1.JPG||HUF4050A-2.JPG||HUF4050A-3.JPG||HUF4050A-4.JPG||HUF4050A-5.JPG||HUF4050A-6.JPG||HUF4050A-7.JPG||HUF4050A-8.JPG||HUF4050A-9.JPG||HUF4050A-10.JPG | AD39: 277531 | AE39: 586 | AF39: Honda/Acura BH Sens ( Huf ) 42753-STK-A04 ( 42753STKA04 ) 42753-STK-A02, 42753-STK-A03, 42753-TL2-A51, 42753-TL2-A52, 550-0206, 550-0201, 550-0203, PMV-107G, TX-S072, TPS0072 42753STKA02, 42753STKA03, 42753TL2A51, 42753TL2A52, 5500206, 5500201, 5500203, PMV107G, TXS072, TPS0072 | AG39: Купить датчик давления в шине (только США) BH Sens ( Huf ) 42753-STK-A04 ( 42753STKA04 ) для Honda/Acura в Москве с доставкой. Цена от производителя. Большой выбор датчиков. Гарантия.
A40: 302691 | B40: 1 | C40: 8253 | D40: 20 | E40: 42753-TK4-A01 | F40: =VLOOKUP(E40,Лист1!A1:A306,1,FALSE) -> 42753-TK4-A01 | G40: Датчик давления в шине (только США) BH Sens ( Huf ) 42753-TK4-A01 ( 42753TK4A01 ) для Honda/Acura | H40: Купить по низкой цене датчик давления в шинах BH Sens ( Huf ) 42753-TK4-A01 ( 42753TK4A01 ) для Honda/Acura с доставкой по Москве или России. | I40: 3750 | J40: Германия | K40: 30 | L40: dk-datchik-davlenia-v-shinah-42753-tk4-a01-350 | M40: <p> Датчик TPMS, номер по каталогу 42753-TK4-A01. Совместим с системами большинства марок автомобилей, производства концерна Honda/Acura. Производитель устройства - <a href="https://alltpms.ru/proizvoditeli-sistem-tpms/beru"> BH Sens ( Huf ) </a>, страна изготовитель - Германия.</p><p></p><p>Производитель гарантирует нормальную работу устройства на протяжении всего срока службы, составляющего 7-8 лет.</p><p>Датчик специально сконструирован для использования в автомобилях концерна Honda/Acura. Комплект поставки устройства: датчик и штуцер. После установки требуется привязка устройства к системе автомобиля. Процедура выполняется по методу <a href="https://alltpms.ru/katalog/privyazka/privyazka-4">«Автоматическая привязка»</a> (Карточка привязки).</p> | N40: 92 | O40: /market/HUF4050A.jpg | P40: Датчик давления в шине BH Sens ( Huf ) 42753-TK4-A01 ( 42753TK4A01 ) для Honda/Acura | Q40: Датчик давления в шине BH Sens ( Huf ) 42753-TK4-A01 ( 42753TK4A01 ) для Honda/Acura | R40: Доставка от 1 шт. без предоплаты, Гарантия 2 года | S40: 0 | T40: 0 | U40: 42753-tk4-a01-350 | V40: 5054208002228 | W40: 622 | X40: Honda/Acura | Y40: 315 | Z40: no | AA40: Clamp-in | AB40: 42753-TY2-A51, 20720, TX-S075, TPS0075, RDE083V21, 1900-20720, 2901-20720, 3040-20720, 3041-20720, 590882-20720, 590880-20720, 20720PVM, 20720PFR, 3040-RDE083, 3041-RDE083, RDE083PVM, RDE083PFR, RDE083PVM, RDE083PFR | AC40: HUF4050A-1.JPG||HUF4050A-2.JPG||HUF4050A-3.JPG||HUF4050A-4.JPG||HUF4050A-5.JPG||HUF4050A-6.JPG||HUF4050A-7.JPG||HUF4050A-8.JPG||HUF4050A-9.JPG||HUF4050A-10.JPG | AD40: 278057 | AE40: 586 | AF40: Honda/Acura BH Sens ( Huf ) 42753-TK4-A01 ( 42753TK4A01 ) 42753-TY2-A51, 20720, TX-S075, TPS0075, RDE083V21, 1900-20720, 2901-20720, 3040-20720, 3041-20720, 590882-20720, 590880-20720, 20720PVM, 20720PFR, 3040-RDE083, 3041-RDE083, RDE083PVM, RDE083PFR, RDE083PVM, RDE083PFR 42753TY2A51, 20720, TXS075, TPS0075, RDE083V21, 190020720, 290120720, 304020720, 304120720, 59088220720, 59088020720, 20720PVM, 20720PFR, 3040RDE083, 3041RDE083, RDE083PVM, RDE083PFR, RDE083PVM, RDE083PFR | AG40: Купить датчик давления в шине (только США) BH Sens ( Huf ) 42753-TK4-A01 ( 42753TK4A01 ) для Honda/Acura в Москве с доставкой. Цена от производителя. Большой выбор датчиков. Гарантия.
A41: 302692 | B41: 1 | C41: 8253 | D41: 20 | E41: 42753-TL0-G52 | F41: =VLOOKUP(E41,Лист1!A1:A306,1,FALSE) -> 42753-TL0-G52 | G41: Датчик давления в шине для Honda/Acura 42753-TL0-G52 ( 42753TL0G52 ) Оригинал | H41: Купить по низкой цене оригинальный датчик давления в шинах для Honda/Acura 42753-TL0-G52 ( 42753TL0G52 ) с доставкой по Москве или России. | I41: 6750 | J41: Франция | K41: 30 | L41: dk-datchik-davlenia-v-shinah-42753-tl0-g52-318 | M41: <p>Датчик 42753-TL0-G52 контроля давления в шинах. Передача данных реализована по радиоканалу. Используемая частота - 433МГц. Для автомобилей Honda/Acura. Страна производства - Франция.</p><p> Датчики устанавливаются в автомобили, выпускаемые концерном Honda/Acura.</p><p></p><p> При условии правильной установки и эксплуатации, срок работы составит 6 лет и более. Срок варьируется в зависимости от интенсивности эксплуатации, частоты и продолжительности поездок.</p><p>Данный датчик 42753-TL0-G52 сконструирован в расчете на установку в автомобили концерна Honda/Acura. В продажу поступают готовые комплекты. В комплект входит сам датчик и ниппель. После установки датчик необходимо активировать. Процесс выполняется с использованием методики <a href="https://alltpms.ru/katalog/privyazka/privyazka-4">«Автоматическая привязка»</a> (Карточка привязки).</p> | N41: 98 | O41: /market/TG7.jpg | P41: Датчик давления в шине для Honda/Acura 42753-TL0-G52 ( 42753TL0G52 ) Оригинал | Q41: Датчик давления в шине для Honda/Acura 42753-TL0-G52 ( 42753TL0G52 ) Оригинал | R41: Доставка от 1 шт. без предоплаты, Гарантия 2 года | S41: 0 | T41: 0 | U41: 42753-tl0-g52-318 | V41: 5054208002229 | W41: 180 | X41: Honda/Acura | Y41: 433 | Z41: yes | AA41: Clamp-in | AB41: 42753-TG7-A51, 42753-T6N-A01, 42753-T6N-E024072, S180052059Z, S180052059, S180052070Z, S180052070, TX-S158, TPS0158, 9014-4072, 9015-4072, 1210-4072, 2210-4072, 2200-4072, 1400-4072, 1401-4072, 4040-4072, 4041-4072, 590914-4072, 590918-4072, 4072PFR, 4072PFM, 4072PVM, S180052070Z, S180052070 | AC41: 42753-TL0-G52-1.JPG||42753-TL0-G52-2.JPG||42753-TL0-G52-3.JPG||42753-TL0-G52-4.JPG||42753-TL0-G52-5.JPG||42753-TL0-G52-6.JPG||42753-TL0-G52-7.JPG||42753-TL0-G52-8.JPG||42753-TL0-G52-9.JPG||42753-TL0-G52-10.JPG | AD41: 226||48029 | AE41: 586 | AF41: Honda/Acura Continental ( VDO ) 42753-TL0-G52 ( 42753TL0G52 ) 42753-TG7-A51, 42753-T6N-A01, 42753-T6N-E024072, S180052059Z, S180052059, S180052070Z, S180052070, TX-S158, TPS0158, 9014-4072, 9015-4072, 1210-4072, 2210-4072, 2200-4072, 1400-4072, 1401-4072, 4040-4072, 4041-4072, 590914-4072, 590918-4072, 4072PFR, 4072PFM, 4072PVM, S180052070Z, S180052070 42753TG7A51, 42753T6NA01, 42753T6NE024072, S180052059Z, S180052059, S180052070Z, S180052070, TXS158, TPS0158, 90144072, 90154072, 12104072, 22104072, 22004072, 14004072, 14014072, 40404072, 40414072, 5909144072, 5909184072, 4072PFR, 4072PFM, 4072PVM, S180052070Z, S180052070 Оригинал | AG41: Купить оригинальный датчик давления в шине для Honda/Acura 42753-TL0-G52 ( 42753TL0G52 ) в Москве с доставкой. Цена от производителя. Большой выбор датчиков. Гарантия.
A42: 302693 | B42: 1 | C42: 8253 | D42: 20 | E42: 42753-TL0-G52 | F42: =VLOOKUP(E42,Лист1!A1:A306,1,FALSE) -> 42753-TL0-G52 | G42: Датчик давления в шине Continental ( VDO ) 42753-TL0-G52 ( 42753TL0G52 ) для Honda/Acura | H42: Купить по низкой цене датчик давления в шинах Continental ( VDO ) 42753-TL0-G52 ( 42753TL0G52 ) для Honda/Acura с доставкой по Москве или России. | I42: 4500 | J42: Франция | K42: 30 | L42: dk-datchik-davlenia-v-shinah-42753-tl0-g52-2 | M42: <p>Датчик давления в шинах. Компания производитель - <a href="https://alltpms.ru/proizvoditeli-sistem-tpms/vdo"> Continental ( VDO ) </a>. Страна производства - Франция. Каталожный номер запчасти 42753-TL0-G52. Данные передаются на частоте 433МГц. Устройство предназначено для установки на автомобили выпускаемые концерном Honda/Acura.</p><p></p><p>Производитель гарантирует качественную работу устройства, при условии правильной эксплуатации. Срок службы датчика составляет от 7 до 8 лет.</p><p>Для упрощения процесса установки датчика на автомобили концерна Honda/Acura, датчик уже укомплектован ниппелем. Материал изготовления ниппеля - металл.</p><p>Датчик требует привязки к авто. Процедура выполняется по методу <a href="https://alltpms.ru/katalog/privyazka/privyazka-4">«Автоматическая привязка»</a> (Карточка привязки). </p> | N42: 99 | O42: /market/2059z.jpg | P42: Датчик давления в шине Continental ( VDO ) 42753-TL0-G52 ( 42753TL0G52 ) для Honda/Acura | Q42: Датчик давления в шине Continental ( VDO ) 42753-TL0-G52 ( 42753TL0G52 ) для Honda/Acura | R42: Доставка от 1 шт. без предоплаты, Гарантия 2 года | S42: 0 | T42: 0 | U42: 42753-tl0-g52-2 | V42: 5054208002230 | W42: 180 | X42: Honda/Acura | Y42: 433 | Z42: no | AA42: Clamp-in | AB42: 42753-TG7-A51, 42753-T6N-A01, 42753-T6N-E024072, S180052059Z, S180052059, S180052070Z, S180052070, TX-S158, TPS0158, 9014-4072, 9015-4072, 1210-4072, 2210-4072, 2200-4072, 1400-4072, 1401-4072, 4040-4072, 4041-4072, 590914-4072, 590918-4072, 4072PFR, 4072PFM, 4072PVM, S180052070Z, S180052070 | AC42: 42753-TL0-G52-VDO-1.JPG||42753-TL0-G52-VDO-2.JPG||42753-TL0-G52-VDO-3.JPG||42753-TL0-G52-VDO-4.JPG||42753-TL0-G52-VDO-5.JPG||42753-TL0-G52-VDO-6.JPG||42753-TL0-G52-VDO-7.JPG||42753-TL0-G52-VDO-8.JPG||42753-TL0-G52-VDO-9.JPG||42753-TL0-G52-VDO-10.JPG | AD42: 226||48029 | AE42: 586 | AF42: Honda/Acura Continental ( VDO ) 42753-TL0-G52 ( 42753TL0G52 ) 42753-TG7-A51, 42753-T6N-A01, 42753-T6N-E024072, S180052059Z, S180052059, S180052070Z, S180052070, TX-S158, TPS0158, 9014-4072, 9015-4072, 1210-4072, 2210-4072, 2200-4072, 1400-4072, 1401-4072, 4040-4072, 4041-4072, 590914-4072, 590918-4072, 4072PFR, 4072PFM, 4072PVM, S180052070Z, S180052070 42753TG7A51, 42753T6NA01, 42753T6NE024072, S180052059Z, S180052059, S180052070Z, S180052070, TXS158, TPS0158, 90144072, 90154072, 12104072, 22104072, 22004072, 14004072, 14014072, 40404072, 40414072, 5909144072, 5909184072, 4072PFR, 4072PFM, 4072PVM, S180052070Z, S180052070 | AG42: Купить датчик давления в шине Continental ( VDO ) 42753-TL0-G52 ( 42753TL0G52 ) для Honda/Acura в Москве с доставкой. Цена от производителя. Большой выбор датчиков. Гарантия.
A43: 302695 | B43: 1 | C43: 8253 | D43: 20 | E43: 42753-TX4-A51 | F43: =VLOOKUP(E43,Лист1!A1:A306,1,FALSE) -> 42753-TX4-A51 | G43: Датчик давления в шине (только США) BH Sens ( Huf ) 42753-TX4-A51 ( 42753TX4A51 ) для Honda/Acura | H43: Купить по низкой цене датчик давления в шинах BH Sens ( Huf ) 42753-TX4-A51 ( 42753TX4A51 ) для Honda/Acura с доставкой по Москве или России. | I43: 3750 | J43: Германия | K43: 30 | L43: dk-datchik-davlenia-v-shinah-42753-tx4-a51-349 | M43: <p>Датчик TPMS производства компании <a href="https://alltpms.ru/proizvoditeli-sistem-tpms/beru"> BH Sens ( Huf ) </a>. Страна изготовления - Германия. Номер по каталогу 42753-TX4-A51. Датчик специально разработан для автомобилей Honda/Acura.</p><p></p><p>В случае правильной эксплуатации срок службы устройства может достигать 8 лет. Данный показатель варьируется в достаточно широких пределах и зависит от условий эксплуатации автомобиля.</p><p>Выпускаемый компанией <a href="https://alltpms.ru/proizvoditeli-sistem-tpms/beru"> BH Sens ( Huf ) </a> Германия, датчик номер 42753-TX4-A51 устанавливается на автомобили, производства Honda/Acura. Покупатель получает полный комплект для установки. Привязка датчика к автомобилю выполняется по методу <a href="https://alltpms.ru/katalog/privyazka/privyazka-4">«Автоматическая привязка»</a> (Карточка привязки).</p> | N43: 94 | O43: /market/HUF4050A.jpg | P43: Датчик давления в шине BH Sens ( Huf ) 42753-TX4-A51 ( 42753TX4A51 ) для Honda/Acura | Q43: Датчик давления в шине BH Sens ( Huf ) 42753-TX4-A51 ( 42753TX4A51 ) для Honda/Acura | R43: Доставка от 1 шт. без предоплаты, Гарантия 2 года | S43: 0 | T43: 0 | U43: 42753-tx4-a51-349 | V43: 5054208002232 | W43: 622 | X43: Honda/Acura | Y43: 315 | Z43: no | AA43: Clamp-in | AB43: 28128, TX-S080, TPS0080, 1900-28128, 2901-28128, 3040-28128, 3041-28128, 590882-28128, 590880-28128, 28128PVM, 28128PFR | AC43: HUF4050A-1.JPG||HUF4050A-2.JPG||HUF4050A-3.JPG||HUF4050A-4.JPG||HUF4050A-5.JPG||HUF4050A-6.JPG||HUF4050A-7.JPG||HUF4050A-8.JPG||HUF4050A-9.JPG||HUF4050A-10.JPG | AD43: 226||48029 | AE43: 586 | AF43: Honda/Acura BH Sens ( Huf ) 42753-TX4-A51 ( 42753TX4A51 ) 28128, TX-S080, TPS0080, 1900-28128, 2901-28128, 3040-28128, 3041-28128, 590882-28128, 590880-28128, 28128PVM, 28128PFR 28128, TXS080, TPS0080, 190028128, 290128128, 304028128, 304128128, 59088228128, 59088028128, 28128PVM, 28128PFR | AG43: Купить датчик давления в шине (только США) BH Sens ( Huf ) 42753-TX4-A51 ( 42753TX4A51 ) для Honda/Acura в Москве с доставкой. Цена от производителя. Большой выбор датчиков. Гарантия.
A44: 302696 | B44: 1 | C44: 8253 | D44: 20 | E44: 42753-TX6-A81 | F44: =VLOOKUP(E44,Лист1!A1:A306,1,FALSE) -> 42753-TX6-A81 | G44: Датчик давления в шине (только США) BH Sens ( Huf ) 42753-TX6-A81 ( 42753TX6A81 ) для Honda/Acura | H44: Купить по низкой цене датчик давления в шинах BH Sens ( Huf ) 42753-TX6-A81 ( 42753TX6A81 ) для Honda/Acura с доставкой по Москве или России. | I44: 3750 | J44: Германия | K44: 30 | L44: dk-datchik-davlenia-v-shinah-42753-tx6-a81-346 | M44: <p>Датчик, номер по каталогу запчастей 42753-TX6-A81. Предназначен для контроля давления в шинах. Передача данных осуществляется посредством радиосигнала на частоте 315МГц. Компания производитель датчика - <a href="https://alltpms.ru/proizvoditeli-sistem-tpms/beru"> BH Sens ( Huf ) </a>. Место производства - Германия.</p><p>Правильно установленный датчик гарантировано проработает 7 лет. В каждом конкретном случае срок службы может изменяться. Он зависит от условий эксплуатации, длительности поездок, их частоты.</p><p>Предназначенный для установки в колеса автомобилей большинства моделей концерна Honda/Acura, датчик поставляется в комплекте с ниппелем. Покупатель получает комплектное устройство. После установки датчик 42753-TX6-A81 активируется, используется метод <a href="https://alltpms.ru/katalog/privyazka/privyazka-1">«Привязка через OBD»</a> (Карточка привязки).</p> | N44: 95 | O44: /market/HUF4050A.jpg | P44: Датчик давления в шине BH Sens ( Huf ) 42753-TX6-A81 ( 42753TX6A81 ) для Honda/Acura | Q44: Датчик давления в шине BH Sens ( Huf ) 42753-TX6-A81 ( 42753TX6A81 ) для Honda/Acura | R44: Доставка от 1 шт. без предоплаты, Гарантия 2 года | S44: 0 | T44: 0 | U44: 42753-tx6-a81-346 | V44: 5054208002233 | W44: 622 | X44: Honda/Acura | Y44: 315 | Z44: no | AA44: Clamp-in | AB44: TX-S074, TPS0074, RDE098V41, 3040-RDE098, 3041-RDE098, RDE098PVM, RDE098PFR, RDE098PVM, RDE098PFR | AC44: HUF4050A-1.JPG||HUF4050A-2.JPG||HUF4050A-3.JPG||HUF4050A-4.JPG||HUF4050A-5.JPG||HUF4050A-6.JPG||HUF4050A-7.JPG||HUF4050A-8.JPG||HUF4050A-9.JPG||HUF4050A-10.JPG | AD44: 226||48029 | AE44: 203 | AF44: Honda/Acura BH Sens ( Huf ) 42753-TX6-A81 ( 42753TX6A81 ) TX-S074, TPS0074, RDE098V41, 3040-RDE098, 3041-RDE098, RDE098PVM, RDE098PFR, RDE098PVM, RDE098PFR TXS074, TPS0074, RDE098V41, 3040RDE098, 3041RDE098, RDE098PVM, RDE098PFR, RDE098PVM, RDE098PFR | AG44: Купить датчик давления в шине (только США) BH Sens ( Huf ) 42753-TX6-A81 ( 42753TX6A81 ) для Honda/Acura в Москве с доставкой. Цена от производителя. Большой выбор датчиков. Гарантия.
A45: 302703 | B45: 1 | C45: 8253 | D45: 20 | E45: 4D0907275A | F45: =VLOOKUP(E45,Лист1!A1:A306,1,FALSE) -> 4D0907275A | G45: Датчик давления в шине (только США) BH Sens ( Huf ) 4D0907275A для VAG/Porsche | H45: Купить по низкой цене датчик давления в шинах BH Sens ( Huf ) 4D0907275A для VAG/Porsche с доставкой по Москве или России. | I45: 3750 | J45: Германия | K45: 30 | L45: dk-datchik-davlenia-v-shinah-4d0907275a-352 | M45: <p>Датчик TPMS производства компании <a href="https://alltpms.ru/proizvoditeli-sistem-tpms/beru"> BH Sens ( Huf ) </a>. Страна изготовления - Германия. Номер по каталогу 4D0907275A. Датчик специально разработан для автомобилей VAG/Porsche.</p><p></p><p>В случае правильной эксплуатации срок службы устройства может достигать 8 лет. Данный показатель варьируется в достаточно широких пределах и зависит от условий эксплуатации автомобиля.</p><p>Выпускаемый компанией <a href="https://alltpms.ru/proizvoditeli-sistem-tpms/beru"> BH Sens ( Huf ) </a> Германия, датчик номер 4D0907275A устанавливается на автомобили, производства VAG/Porsche. Покупатель получает полный комплект для установки. Привязка датчика к автомобилю выполняется по методу <a href="https://alltpms.ru/katalog/privyazka/privyazka-4">«Автоматизированная привязка»</a> (Карточка привязки).</p> | N45: 80 | O45: /market/HUF4050A.jpg | P45: Датчик давления в шине BH Sens ( Huf ) 4D0907275A для VAG/Porsche | Q45: Датчик давления в шине BH Sens ( Huf ) 4D0907275A для VAG/Porsche | R45: Доставка от 1 шт. без предоплаты, Гарантия 2 года | S45: 0 | T45: 0 | U45: 4d0907275a-352 | V45: 5054208002240 | W45: 622 | X45: VAG/Porsche | Y45: 315 | Z45: no | AA45: Clamp-in | AB45: 33001, 550-1904, TX-S002, TPS0002, RDE004V21, 1900-33001, 2901-33001, 3040-33001, 3041-33001, 590882-33001, 590880-33001, 33001PVM, 33001PFR, 3040-RDE004, 3041-RDE004, RDE004PVM, RDE004PFR, RDE004PVM, RDE004PFR | AC45: HUF4050A-1.JPG||HUF4050A-2.JPG||HUF4050A-3.JPG||HUF4050A-4.JPG||HUF4050A-5.JPG||HUF4050A-6.JPG||HUF4050A-7.JPG||HUF4050A-8.JPG||HUF4050A-9.JPG||HUF4050A-10.JPG | AD45: 229||92867||241||244||48032 | AE45: 588 | AF45: VAG/Porsche BH Sens ( Huf ) 4D0907275A 33001, 550-1904, TX-S002, TPS0002, RDE004V21, 1900-33001, 2901-33001, 3040-33001, 3041-33001, 590882-33001, 590880-33001, 33001PVM, 33001PFR, 3040-RDE004, 3041-RDE004, RDE004PVM, RDE004PFR, RDE004PVM, RDE004PFR 33001, 5501904, TXS002, TPS0002, RDE004V21, 190033001, 290133001, 304033001, 304133001, 59088233001, 59088033001, 33001PVM, 33001PFR, 3040RDE004, 3041RDE004, RDE004PVM, RDE004PFR, RDE004PVM, RDE004PFR | AG45: Купить датчик давления в шине BH Sens ( Huf ) 4D0907275A для VAG/Porsche в Москве с доставкой. Цена от производителя. Большой выбор датчиков. Гарантия.
A46: 302704 | B46: 1 | C46: 8253 | D46: 20 | E46: 4D0907275C | F46: =VLOOKUP(E46,Лист1!A1:A306,1,FALSE) -> 4D0907275C | G46: Датчик давления в шине BH Sens ( Huf ) 4D0907275C для VAG/Porsche (Black Edition) | H46: Покупайте датчик давления в шине BH Sens ( Huf ) 4D0907275C для VAG/Porsche (Black Edition) по выгодным ценам | Большой выбор датчиков давления в шине | Осуществляем доставку на всей территории РФ | I46: 4250 | J46: Германия | K46: 30 | L46: dk-datchik-davlenia-v-shinah-4d0907275cb-10 | M46: <p>Датчик давления в шинах, номер по каталогу 4D0907275C, передает сигналы с помощью радиоканала. Рабочая частота - 433МГц. Компания производитель <a href="https://alltpms.ru/proizvoditeli-sistem-tpms/beru"> BH Sens ( Huf ) </a>. Страна производства - Германия. Устройства предназначены для установки в колеса автомобилей, выпускаемых концерном VAG/Porsche.</p><p></p><p> При условии установки на специализированных СТО, срок службы устройства составляет до 7 лет.</p><p>Конструктивные особенности данного датчика гарантируют его полную совместимость с системами авто концерна VAG/Porsche. Датчик поставляется в комплекте с ниппелем, что заметно облегчает установку и не требует покупки дополнительных деталей. Материал ниппеля - металл. После установки датчик 4D0907275C требует привязки к авто. Привязка производится по методике <a href="https://alltpms.ru/katalog/privyazka/privyazka-4">«Автоматизированная привязка»</a> (Карточка привязки).</p> | N46: 83 | O46: /market/RDE001B.jpg | P46: Датчик давления в шине BH Sens ( Huf ) 4D0907275C для VAG/Porsche (Black Edition) | Q46: Датчик давления в шине BH Sens ( Huf ) 4D0907275C для VAG/Porsche (Black Edition) | R46: Доставка от 1 шт. без предоплаты, Гарантия 2 года | S46: 0 | T46: 0 | U46: 4d0907275cb-10 | V46: 5054208002241 | W46: 622 | X46: VAG/Porsche | Y46: 433 | Z46: no | AA46: Clamp-in | AB46: 185189, 312450, 99760602100, 99760602101, 99760602102, 4D0907275, 4D0907275E, A0008223306, A0055422318, AY93-360671-AA, 4001, 550-1901, TX-S001, TPS0001, RDE001V21, 9014-4001, 9015-4001, 1210-4001, 2210-4001, 2200-4001, 1400-4001, 1401-4001, 4040-4001, 4041-4001, 590914-4001, 590918-4001, 4001PFR, 4001PFM, 4001PVM, 4040-RDE001, 4041-RDE001, RDE001PVM, RDE001PFR, RDE001PVM, RDE001PFR | AC46: HUF4040_B-1.JPG||HUF4040_B-2.JPG||HUF4040_B-3.JPG||HUF4040_B-4.JPG||HUF4040_B-5.JPG||HUF4040_B-6.JPG||HUF4040_B-7.JPG||HUF4040_B-8.JPG||HUF4040_B-9.JPG||HUF4040_B-10.JPG | AD46: 229||92867||241||244||48032 | AE46: 588 | AG46: Покупайте датчик давления в шине BH Sens ( Huf ) 4D0907275C для VAG/Porsche (Black Edition) по выгодным ценам | Большой выбор датчиков давления в шине | Осуществляем доставку на всей территории РФ
A47: 302705 | B47: 1 | C47: 8253 | D47: 20 | E47: 4D0907275C | F47: =VLOOKUP(E47,Лист1!A1:A306,1,FALSE) -> 4D0907275C | G47: Датчик давления в шине BH Sens ( Huf ) 4D0907275C для VAG/Porsche | H47: Покупайте датчик давления в шине BH Sens ( Huf ) 4D0907275C для VAG/Porsche по выгодным ценам | Большой выбор датчиков давления в шине | Осуществляем доставку на всей территории РФ | I47: 3750 | J47: Германия | K47: 30 | L47: dk-datchik-davlenia-v-shinah-4d0907275c-10 | M47: <p> Каталожный номер датчика 4D0907275C. Передача данных происходит по радиоканалу, задействована частота 433МГц. Компания производитель – <a href="https://alltpms.ru/proizvoditeli-sistem-tpms/beru"> BH Sens ( Huf ) </a>. Страна - Германия.</p><p> Датчики предназначены для авто производства VAG/Porsche.</p><p></p><p>В зависимости от интенсивности эксплуатации комплекта колес срок службы устройства достигает 7 лет. Срок эксплуатации зависит от продолжительности поездок, поскольку именно во время движения автомобиля датчик расходует заряд элемента питания.</p><p> Предназначенный для установки в автомобили концерна VAG/Porsche, датчик поступает в продажу с ниппелем. Благодаря этому покупатель получает полностью комплектное устройство. Для активации датчика и привязки его к автомобилю выполняется процедура <a href="https://alltpms.ru/katalog/privyazka/privyazka-4">«Автоматизированная привязка»</a> (Карточка привязки).</p> | N47: 84 | O47: /market/RDE001.jpg | P47: Датчик давления в шине BH Sens ( Huf ) 4D0907275C для VAG/Porsche | Q47: Датчик давления в шине BH Sens ( Huf ) 4D0907275C для VAG/Porsche | R47: Доставка от 1 шт. без предоплаты, Гарантия 2 года | S47: 0 | T47: 0 | U47: 4d0907275c-10 | V47: 5054208002242 | W47: 622 | X47: VAG/Porsche | Y47: 433 | Z47: no | AA47: Clamp-in | AB47: 185189, 312450, 99760602100, 99760602101, 99760602102, 4D0907275, 4D0907275E, A0008223306, A0055422318, AY93-360671-AA, 4001, 550-1901, TX-S001, TPS0001, RDE001V21, 9014-4001, 9015-4001, 1210-4001, 2210-4001, 2200-4001, 1400-4001, 1401-4001, 4040-4001, 4041-4001, 590914-4001, 590918-4001, 4001PFR, 4001PFM, 4001PVM, 4040-RDE001, 4041-RDE001, RDE001PVM, RDE001PFR, RDE001PVM, RDE001PFR | AC47: HUF4040-1.JPG||HUF4040-2.JPG||HUF4040-3.JPG||HUF4040-4.JPG||HUF4040-5.JPG||HUF4040-6.JPG||HUF4040-7.JPG||HUF4040-8.JPG||HUF4040-9.JPG||HUF4040-10.JPG | AD47: 229||92867||241||244||48032 | AE47: 588 | AG47: Покупайте датчик давления в шине BH Sens ( Huf ) 4D0907275C для VAG/Porsche по выгодным ценам | Большой выбор датчиков давления в шине | Осуществляем доставку на всей территории РФ
A48: 302758 | B48: 1 | C48: 8253 | D48: 20 | E48: 56029398AB | F48: =VLOOKUP(E48,Лист1!A1:A306,1,FALSE) -> 56029398AB | G48: Датчик давления в шине для Fiat/Alfa/Chrysler/Dodge/Jeep 56029398AB Оригинал | H48: Купить по низкой цене оригинальный датчик давления в шинах для Fiat/Alfa/Chrysler/Dodge/Jeep 56029398AB с доставкой по Москве или России. | I48: 7750 | J48: Англия | K48: 30 | L48: dk-datchik-davlenia-v-shinah-56029398ab-234 | M48: <p>Датчик, номер по каталогу запчастей 56029398AB. Предназначен для контроля давления в шинах. Передача данных осуществляется посредством радиосигнала на частоте 433МГц. Компания производитель автомобиля - Fiat/Alfa/Chrysler/Dodge/Jeep. Место производства - Англия.</p><p>Правильно установленный датчик гарантировано проработает 7 лет. В каждом конкретном случае срок службы может изменяться. Он зависит от условий эксплуатации, длительности поездок, их частоты.</p><p>Предназначенный для установки в колеса автомобилей большинства моделей концерна Fiat/Alfa/Chrysler/Dodge/Jeep, датчик поставляется в комплекте с ниппелем. Покупатель получает комплектное устройство. После установки датчик 56029398AB активируется, используется метод <a href="https://alltpms.ru/katalog/privyazka/privyazka-4">«Автоматическая привязка»</a> (Карточка привязки).</p> | N48: 95 | O48: /market/56029398AB.jpg | P48: Датчик давления в шине для Fiat/Alfa/Chrysler/Dodge/Jeep 56029398AB Оригинал | Q48: Датчик давления в шине для Fiat/Alfa/Chrysler/Dodge/Jeep 56029398AB Оригинал | R48: Доставка от 1 шт. без предоплаты, Гарантия 2 года | S48: 0 | T48: 0 | U48: 56029398ab-234 | V48: 5054208002299 | W48: 625 | X48: Fiat/Alfa/Chrysler/Dodge/Jeep | Y48: 433 | Z48: yes | AA48: Snap-in | AB48: 53104671, 56029398AA, 68142397AA, 68406537AA, 68510382AA, 68464665AA, 56029400AA, 56029400AB, 56029400AC, 56029400AD, 56029400AE, 68241067AA, 68241067AA, 68241067AB, 3007, 3008, 550-2500, 550-2503, TX-S033L/R, TPS0033L/R, ECR0110, RDE036V21, 9014-3007, 9015-3007, 1210-3007, 2210-3007, 2200-3007, 1400-3007, 1401-3007, 4040-3007, 4041-3007, 590914-3007, 590918-3007, 3007PFR, 3007PFM, 3007PVM, 4040-RDE036, 4041-RDE036, RDE036PVM, RDE036PFR, RDE036PVM, RDE036PFR | AC48: 56029398AB-1.JPG||56029398AB-2.JPG||56029398AB-3.JPG||56029398AB-4.JPG||56029398AB-5.JPG||56029398AB-6.JPG||56029398AB-7.JPG||56029398AB-8.JPG||56029398AB-9.JPG||56029398AB-10.JPG | AD48: 220||48026||232 | AE48: 586 | AF48: Fiat/Alfa/Chrysler/Dodge/Jeep Schrader 56029398AB 53104671, 56029398AA, 68142397AA, 68406537AA, 68510382AA, 68464665AA, 56029400AA, 56029400AB, 56029400AC, 56029400AD, 56029400AE, 68241067AA, 68241067AA, 68241067AB, 3007, 3008, 550-2500, 550-2503, TX-S033L/R, TPS0033L/R, ECR0110, RDE036V21, 9014-3007, 9015-3007, 1210-3007, 2210-3007, 2200-3007, 1400-3007, 1401-3007, 4040-3007, 4041-3007, 590914-3007, 590918-3007, 3007PFR, 3007PFM, 3007PVM, 4040-RDE036, 4041-RDE036, RDE036PVM, RDE036PFR, RDE036PVM, RDE036PFR 53104671, 56029398AA, 68142397AA, 68406537AA, 68510382AA, 68464665AA, 56029400AA, 56029400AB, 56029400AC, 56029400AD, 56029400AE, 68241067AA, 68241067AA, 68241067AB, 3007, 3008, 5502500, 5502503, TXS033L/R, TPS0033L/R, ECR0110, RDE036V21, 90143007, 90153007, 12103007, 22103007, 22003007, 14003007, 14013007, 40403007, 40413007, 5909143007, 5909183007, 3007PFR, 3007PFM, 3007PVM, 4040RDE036, 4041RDE036, RDE036PVM, RDE036PFR, RDE036PVM, RDE036PFR Оригинал | AG48: Купить оригинальный датчик давления в шине для Fiat/Alfa/Chrysler/Dodge/Jeep 56029398AB в Москве с доставкой. Цена от производителя. Большой выбор датчиков. Гарантия.
A49: 302759 | B49: 1 | C49: 8253 | D49: 20 | E49: 56029398AB | F49: =VLOOKUP(E49,Лист1!A1:A306,1,FALSE) -> 56029398AB | G49: Датчик давления в шине BH Sens ( Huf ) 56029398AB для Fiat/Alfa/Chrysler/Dodge/Jeep | H49: Покупайте датчик давления в шине BH Sens ( Huf ) 56029398AB для Fiat/Alfa/Chrysler/Dodge/Jeep по выгодным ценам | Большой выбор датчиков давления в шине | Осуществляем доставку на всей территории РФ | I49: 3250 | J49: Германия | K49: 30 | L49: dk-datchik-davlenia-v-shinah-56029398ab-48 | M49: <p>Датчик давления в шинах, номер по каталогу 56029398AB, передает сигналы с помощью радиоканала. Рабочая частота - 433МГц. Компания производитель <a href="https://alltpms.ru/proizvoditeli-sistem-tpms/beru"> BH Sens ( Huf ) </a>. Страна производства - Германия. Устройства предназначены для установки в колеса автомобилей, выпускаемых концерном Fiat/Alfa/Chrysler/Dodge/Jeep.</p><p></p><p> При условии установки на специализированных СТО, срок службы устройства составляет до 7 лет.</p><p>Конструктивные особенности данного датчика гарантируют его полную совместимость с системами авто концерна Fiat/Alfa/Chrysler/Dodge/Jeep. Датчик поставляется в комплекте с ниппелем, что заметно облегчает установку и не требует покупки дополнительных деталей. Материал ниппеля - резина. После установки датчик 56029398AB требует привязки к авто. Привязка производится по методике <a href="https://alltpms.ru/katalog/privyazka/privyazka-4">«Автоматическая привязка»</a> (Карточка привязки).</p> | N49: 96 | O49: /market/HUF1411.jpg | P49: Датчик давления в шине BH Sens ( Huf ) 56029398AB для Fiat/Alfa/Chrysler/Dodge/Jeep | Q49: Датчик давления в шине BH Sens ( Huf ) 56029398AB для Fiat/Alfa/Chrysler/Dodge/Jeep | R49: Доставка от 1 шт. без предоплаты, Гарантия 2 года | S49: 0 | T49: 1 | U49: 56029398ab-48 | V49: 5054208002300 | W49: 622 | X49: Fiat/Alfa/Chrysler/Dodge/Jeep | Y49: 433 | Z49: no | AA49: Snap-in | AB49: 53104671, 56029398AA, 68142397AA, 68406537AA, 68510382AA, 68464665AA, 56029400AA, 56029400AB, 56029400AC, 56029400AD, 56029400AE, 68241067AA, 68241067AA, 68241067AB, 3007, 3008, 550-2500, 550-2503, TX-S033L/R, TPS0033L/R, ECR0110, RDE036V21, 9014-3007, 9015-3007, 1210-3007, 2210-3007, 2200-3007, 1400-3007, 1401-3007, 4040-3007, 4041-3007, 590914-3007, 590918-3007, 3007PFR, 3007PFM, 3007PVM, 4040-RDE036, 4041-RDE036, RDE036PVM, RDE036PFR, RDE036PVM, RDE036PFR | AC49: HUF1401-1.JPG||HUF1401-2.JPG||HUF1401-3.JPG||HUF1401-4.JPG||HUF1401-5.JPG||HUF1401-6.JPG||HUF1401-7.JPG||HUF1401-8.JPG||HUF1401-9.JPG||HUF1401-10.JPG | AD49: 220||48026||232 | AE49: 586 | AG49: Покупайте датчик давления в шине BH Sens ( Huf ) 56029398AB для Fiat/Alfa/Chrysler/Dodge/Jeep по выгодным ценам | Большой выбор датчиков давления в шине | Осуществляем доставку на всей территории РФ
A50: 302763 | B50: 1 | C50: 8253 | D50: 20 | E50: 5Q0907275F | F50: =VLOOKUP(E50,Лист1!A1:A306,1,FALSE) -> 5Q0907275F | G50: Датчик давления в шине для VAG/Porsche 5Q0907275F Оригинал (Black Edition) | H50: Покупайте датчик давления в шине для VAG/Porsche 5Q0907275F Оригинал (Black Edition) по выгодным ценам | Большой выбор датчиков давления в шине для VAG/Porsche | Осуществляем доставку на всей территории РФ | I50: 7500 | J50: Германия | K50: 30 | L50: dk-datchik-davlenia-v-shinah-5q0907275b-15 | M50: <p> Датчик TPMS, номер по каталогу 5Q0907275F. Совместим с системами большинства марок автомобилей, производства концерна VAG/Porsche. Производитель автомобиля - VAG/Porsche, страна изготовитель - Германия.</p><p></p><p>Производитель гарантирует нормальную работу устройства на протяжении всего срока службы, составляющего 7-8 лет.</p><p>Датчик специально сконструирован для использования в автомобилях концерна VAG/Porsche. Комплект поставки устройства: датчик и штуцер. После установки требуется привязка устройства к системе автомобиля. Процедура выполняется по методу <a href="https://alltpms.ru/katalog/privyazka/privyazka-4">«Автоматизированная привязка»</a> (Карточка привязки).</p> | N50: 95 | O50: /market/5Q0FB.jpg | P50: Датчик давления в шине для VAG/Porsche 5Q0907275F Оригинал (Black Edition) | Q50: Датчик давления в шине для VAG/Porsche 5Q0907275F Оригинал (Black Edition) | R50: Доставка от 1 шт. без предоплаты, Гарантия 2 года | S50: 0 | T50: 0 | U50: 5q0907275b-15 | V50: 5054208002304 | W50: 622 | X50: VAG/Porsche | Y50: 433 | Z50: yes | AA50: Clamp-in | AB50: 5Q0907275, 5Q0907275B, 9J1907275, 9A790727502, PAB907275, 2N0907251A, 2N0907275A, 9A7907275, 9J1907275, 9A7907275, 9J1907275PFM, 4012, 550-1918, TX-S005L/R, TPS0005L/R, ECR0030, RDE047V21, RDE018V21, 9014-4012, 9015-4012, 1210-4012, 2210-4012, 2200-4012, 1400-4012, 1401-4012, 4040-4012, 4041-4012, 590914-4012, 590918-4012, 4012PFR, 4012PFM, 4012PVM, 4040-RDE047, 4041-RDE047, RDE047PVM, RDE047PFR, RDE047PVM, RDE047PFR | AC50: 5Q0907275F_B-1.JPG||5Q0907275F_B-2.JPG||5Q0907275F_B-3.JPG||5Q0907275F_B-4.JPG||5Q0907275F_B-5.JPG||5Q0907275F_B-6.JPG||5Q0907275F_B-7.JPG||5Q0907275F_B-8.JPG||5Q0907275F_B-9.JPG||5Q0907275F_B-10.JPG | AD50: 229||92867||241||244||48032 | AE50: 588 | AG50: Покупайте датчик давления в шине для VAG/Porsche 5Q0907275F Оригинал (Black Edition) по выгодным ценам | Большой выбор датчиков давления в шине для VAG/Porsche | Осуществляем доставку на всей территории РФ
A51: 302764 | B51: 1 | C51: 8253 | D51: 20 | E51: 5Q0907275F | F51: =VLOOKUP(E51,Лист1!A1:A306,1,FALSE) -> 5Q0907275F | G51: Датчик давления в шине для VAG/Porsche 5Q0907275F Оригинал | H51: Покупайте датчик давления в шине для VAG/Porsche 5Q0907275F Оригинал по выгодным ценам | Большой выбор датчиков давления в шине для VAG/Porsche | Осуществляем доставку на всей территории РФ | I51: 7000 | J51: Германия | K51: 30 | L51: dk-datchik-davlenia-v-shinah-5q0907275-15 | M51: <p> Датчик TPMS, номер по каталогу 5Q0907275F. Совместим с системами большинства марок автомобилей, производства концерна VAG/Porsche. Производитель автомобиля - VAG/Porsche, страна изготовитель - Германия.</p><p></p><p>Производитель гарантирует нормальную работу устройства на протяжении всего срока службы, составляющего 7-8 лет.</p><p>Датчик специально сконструирован для использования в автомобилях концерна VAG/Porsche. Комплект поставки устройства: датчик и штуцер. После установки требуется привязка устройства к системе автомобиля. Процедура выполняется по методу <a href="https://alltpms.ru/katalog/privyazka/privyazka-4">«Автоматизированная привязка»</a> (Карточка привязки).</p> | N51: 97 | O51: /market/5Q0F.jpg | P51: Датчик давления в шине для VAG/Porsche 5Q0907275F Оригинал | Q51: Датчик давления в шине для VAG/Porsche 5Q0907275F Оригинал | R51: Доставка от 1 шт. без предоплаты, Гарантия 2 года | S51: 0 | T51: 0 | U51: 5q0907275-15 | V51: 5054208002305 | W51: 622 | X51: VAG/Porsche | Y51: 433 | Z51: yes | AA51: Clamp-in | AB51: 5Q0907275, 5Q0907275B, 9J1907275, 9A790727502, PAB907275, 2N0907251A, 2N0907275A, 9A7907275, 9J1907275, 9A7907275, 9J1907275PFM, 4012, 550-1918, TX-S005L/R, TPS0005L/R, ECR0030, RDE047V21, RDE018V21, 9014-4012, 9015-4012, 1210-4012, 2210-4012, 2200-4012, 1400-4012, 1401-4012, 4040-4012, 4041-4012, 590914-4012, 590918-4012, 4012PFR, 4012PFM, 4012PVM, 4040-RDE047, 4041-RDE047, RDE047PVM, RDE047PFR, RDE047PVM, RDE047PFR | AC51: 5Q0907275F-1.JPG||5Q0907275F-2.JPG||5Q0907275F-3.JPG||5Q0907275F-4.JPG||5Q0907275F-5.JPG||5Q0907275F-6.JPG||5Q0907275F-7.JPG||5Q0907275F-8.JPG||5Q0907275F-9.JPG||5Q0907275F-10.JPG | AD51: 229||92867||241||244||48032 | AE51: 588 | AG51: Покупайте датчик давления в шине для VAG/Porsche 5Q0907275F Оригинал по выгодным ценам | Большой выбор датчиков давления в шине для VAG/Porsche | Осуществляем доставку на всей территории РФ
A52: 302765 | B52: 1 | C52: 8253 | D52: 20 | E52: 5Q0907275F | F52: =VLOOKUP(E52,Лист1!A1:A306,1,FALSE) -> 5Q0907275F | G52: Датчик давления в шине BH Sens ( Huf ) 5Q0907275F для VAG/Porsche (Black Edition) | H52: Покупайте датчик давления в шине BH Sens ( Huf ) 5Q0907275F для VAG/Porsche (Black Edition) по выгодным ценам | Большой выбор датчиков давления в шине | Осуществляем доставку на всей территории РФ | I52: 3750 | J52: Германия | K52: 30 | L52: dk-datchik-davlenia-v-shinah-5q0907275b-16 | M52: <p> Каталожный номер датчика 5Q0907275F. Передача данных происходит по радиоканалу, задействована частота 433МГц. Компания производитель – <a href="https://alltpms.ru/proizvoditeli-sistem-tpms/beru"> BH Sens ( Huf ) </a>. Страна - Германия.</p><p> Датчики предназначены для авто производства VAG/Porsche.</p><p></p><p>В зависимости от интенсивности эксплуатации комплекта колес срок службы устройства достигает 7 лет. Срок эксплуатации зависит от продолжительности поездок, поскольку именно во время движения автомобиля датчик расходует заряд элемента питания.</p><p> Предназначенный для установки в автомобили концерна VAG/Porsche, датчик поступает в продажу с ниппелем. Благодаря этому покупатель получает полностью комплектное устройство. Для активации датчика и привязки его к автомобилю выполняется процедура <a href="https://alltpms.ru/katalog/privyazka/privyazka-4">«Автоматизированная привязка»</a> (Карточка привязки).</p> | N52: 96 | O52: /market/HUF1410B.jpg | P52: Датчик давления в шине BH Sens ( Huf ) 5Q0907275F для VAG/Porsche (Black Edition) | Q52: Датчик давления в шине BH Sens ( Huf ) 5Q0907275F для VAG/Porsche (Black Edition) | R52: Доставка от 1 шт. без предоплаты, Гарантия 2 года | S52: 0 | T52: 1 | U52: 5q0907275b-16 | V52: 5054208002306 | W52: 622 | X52: VAG/Porsche | Y52: 433 | Z52: no | AA52: Clamp-in | AB52: 5Q0907275, 5Q0907275B, 9J1907275, 9A790727502, PAB907275, 2N0907251A, 2N0907275A, 9A7907275, 9J1907275, 9A7907275, 9J1907275PFM, 4012, 550-1918, TX-S005L/R, TPS0005L/R, ECR0030, RDE047V21, RDE018V21, 9014-4012, 9015-4012, 1210-4012, 2210-4012, 2200-4012, 1400-4012, 1401-4012, 4040-4012, 4041-4012, 590914-4012, 590918-4012, 4012PFR, 4012PFM, 4012PVM, 4040-RDE047, 4041-RDE047, RDE047PVM, RDE047PFR, RDE047PVM, RDE047PFR | AC52: HUF1400_B-1.JPG||HUF1400_B-2.JPG||HUF1400_B-3.JPG||HUF1400_B-4.JPG||HUF1400_B-5.JPG||HUF1400_B-6.JPG||HUF1400_B-7.JPG||HUF1400_B-8.JPG||HUF1400_B-9.JPG||HUF1400_B-10.JPG | AD52: 229||92867||241||244||48032 | AE52: 588 | AG52: Покупайте датчик давления в шине BH Sens ( Huf ) 5Q0907275F для VAG/Porsche (Black Edition) по выгодным ценам | Большой выбор датчиков давления в шине | Осуществляем доставку на всей территории РФ
A53: 302766 | B53: 1 | C53: 8253 | D53: 20 | E53: 5Q0907275F | F53: =VLOOKUP(E53,Лист1!A1:A306,1,FALSE) -> 5Q0907275F | G53: Датчик давления в шине BH Sens ( Huf ) 5Q0907275F для VAG/Porsche | H53: Покупайте датчик давления в шине BH Sens ( Huf ) 5Q0907275F для VAG/Porsche по выгодным ценам | Большой выбор датчиков давления в шине | Осуществляем доставку на всей территории РФ | I53: 3250 | J53: Германия | K53: 30 | L53: dk-datchik-davlenia-v-shinah-5q0907275-16 | M53: <p>Датчик TPMS, производства компании <a href="https://alltpms.ru/proizvoditeli-sistem-tpms/beru"> BH Sens ( Huf ) </a>. Страна производства - Германия. Каталожный номер детали 5Q0907275F. Датчик применяется в автомобилях, производства VAG/Porsche.</p><p></p><p> При нормальных условиях эксплуатации устройство прослужит до 8 лет.</p><p>Данный датчик, производства компании <a href="https://alltpms.ru/proizvoditeli-sistem-tpms/beru"> BH Sens ( Huf ) </a> Германия номер 5Q0907275F рассчитан на установку в колеса легковых автомобилей VAG/Porsche. Датчик продается в комплекте со штуцером, т.е. покупатель получает полный набор деталей для установки. Материал штуцера - металл. После установки датчика необходимо осуществить его привязку к системе авто. Для этого используется метод <a href="https://alltpms.ru/katalog/privyazka/privyazka-4">«Автоматизированная привязка»</a> (Карточка привязки).</p> | N53: 98 | O53: /market/HUF1410.jpg | P53: Датчик давления в шине BH Sens ( Huf ) 5Q0907275F для VAG/Porsche | Q53: Датчик давления в шине BH Sens ( Huf ) 5Q0907275F для VAG/Porsche | R53: Доставка от 1 шт. без предоплаты, Гарантия 2 года | S53: 0 | T53: 1 | U53: 5q0907275-16 | V53: 5054208002307 | W53: 622 | X53: VAG/Porsche | Y53: 433 | Z53: no | AA53: Clamp-in | AB53: 5Q0907275, 5Q0907275B, 9J1907275, 9A790727502, PAB907275, 2N0907251A, 2N0907275A, 9A7907275, 9J1907275, 9A7907275, 9J1907275PFM, 4012, 550-1918, TX-S005L/R, TPS0005L/R, ECR0030, RDE047V21, RDE018V21, 9014-4012, 9015-4012, 1210-4012, 2210-4012, 2200-4012, 1400-4012, 1401-4012, 4040-4012, 4041-4012, 590914-4012, 590918-4012, 4012PFR, 4012PFM, 4012PVM, 4040-RDE047, 4041-RDE047, RDE047PVM, RDE047PFR, RDE047PVM, RDE047PFR | AC53: HUF1400-1.JPG||HUF1400-2.JPG||HUF1400-3.JPG||HUF1400-4.JPG||HUF1400-5.JPG||HUF1400-6.JPG||HUF1400-7.JPG||HUF1400-8.JPG||HUF1400-9.JPG||HUF1400-10.JPG | AD53: 229||92867||241||244||48032 | AE53: 588 | AG53: Покупайте датчик давления в шине BH Sens ( Huf ) 5Q0907275F для VAG/Porsche по выгодным ценам | Большой выбор датчиков давления в шине | Осуществляем доставку на всей территории РФ
A54: 302767 | B54: 1 | C54: 8253 | D54: 20 | E54: 5Q0998270D | F54: =VLOOKUP(E54,Лист1!A1:A306,1,FALSE) -> 5Q0998270D | G54: Комплект датчиков давления в шинах для VAG/Porsche 5Q0998270D Оригинал | H54: Купить по низкой цене комплект оригинальных датчиков давления в шинах для VAG/Porsche 5Q0998270D с доставкой по Москве или России. | I54: 28000 | J54: Германия | K54: 120 | L54: dk-datchik-davlenia-v-shinah-5q0998270b-15234234234 | M54: <p>Комплект датчиков, номер по каталогу запчастей 5Q0998270D. Предназначен для контроля давления в шинах. Передача данных осуществляется посредством радиосигнала на частоте 433МГц. Компания производитель автомобиля - VAG/Porsche. Место производства - Германия.</p><p>Правильно установленный датчик гарантировано проработает 5-7 лет. В каждом конкретном случае срок службы может изменяться. Он зависит от условий эксплуатации, длительности поездок, их частоты.</p><p>Предназначенный для установки в колеса автомобилей большинства моделей концерна VAG/Porsche, датчик поставляется в комплекте с ниппелем. Покупатель получает комплектное устройство. После установки датчик 5Q0998270D активируется, используется метод <a href="https://alltpms.ru/katalog/privyazka/privyazka-4">«Автоматизированная привязка»</a> (Карточка привязки).</p> | N54: 99 | O54: /market/5Q0DKIT.jpg | P54: Комплект датчиков давления в шинах для VAG/Porsche 5Q0998270D Оригинал | Q54: Комплект датчиков давления в шинах для VAG/Porsche 5Q0998270D Оригинал | R54: Доставка от 1 шт. без предоплаты, Гарантия 2 года | S54: 0 | T54: 0 | U54: 5q0998270b-15234234234 | V54: 5054208002308 | W54: 622 | X54: VAG/Porsche | Y54: 433 | Z54: yes | AA54: Clamp-in | AB54: 5Q0907275, 5Q0907275B, 5Q0998270, 4012-KIT, 9014-4012-KIT, 9015-4012-KIT, 1210-4012-KIT, 2210-4012-KIT, 2200-4012-KIT, 1400-4012-KIT, 1401-4012-KIT, 4040-4012-KIT, 4041-4012-KIT, 590914-4012-KIT, 590918-4012-KIT | AC54: 5Q0998270D-1.JPG||5Q0998270D-2.JPG||5Q0998270D-3.JPG||5Q0998270D-4.JPG||5Q0998270D-5.JPG||5Q0998270D-6.JPG||5Q0998270D-7.JPG||5Q0998270D-8.JPG||5Q0998270D-9.JPG||5Q0998270D-10.JPG | AD54: 229||92867||241||244||48032 | AE54: 588 | AF54: VAG/Porsche BH Sens ( Huf ) 5Q0998270D 5Q0907275, 5Q0907275B, 5Q0998270, 4012-KIT, 9014-4012-KIT, 9015-4012-KIT, 1210-4012-KIT, 2210-4012-KIT, 2200-4012-KIT, 1400-4012-KIT, 1401-4012-KIT, 4040-4012-KIT, 4041-4012-KIT, 590914-4012-KIT, 590918-4012-KIT 5Q0907275, 5Q0907275B, 5Q0998270, 4012KIT, 90144012KIT, 90154012KIT, 12104012KIT, 22104012KIT, 22004012KIT, 14004012KIT, 14014012KIT, 40404012KIT, 40414012KIT, 5909144012KIT, 5909184012KIT Оригинал | AG54: Купить комплект оригинальных датчиков давления в шине для VAG/Porsche 5Q0998270D в Москве с доставкой. Цена от производителя. Большой выбор датчиков. Гарантия.
A55: 302778 | B55: 1 | C55: 8253 | D55: 20 | E55: 68252495AA | F55: =VLOOKUP(E55,Лист1!A1:A306,1,FALSE) -> 68252495AA | G55: Датчик давления в шине Continental ( VDO ) 68252495AA для Fiat/Alfa/Chrysler/Dodge/Jeep | H55: Купить по низкой цене датчик давления в шинах Continental ( VDO ) 68252495AA для Fiat/Alfa/Chrysler/Dodge/Jeep с доставкой по Москве или России. | I55: 4500 | J55: Франция | K55: 30 | L55: dk-datchik-davlenia-v-shinah-68252495aa-2623 | M55: <p> Датчик давления в шинах. Предназначен для автомобилей Fiat/Alfa/Chrysler/Dodge/Jeep. Каталожный номер запчасти 68252495AA. Компания производитель - <a href="https://alltpms.ru/proizvoditeli-sistem-tpms/vdo"> Continental ( VDO ) </a>, Франция.</p><p></p><p>При условии соблюдения правил установки и эксплуатации, срок службы датчика варьируется в пределах от 7 до 8 лет. Срок нормальной работы зависит от условий эксплуатации.</p><p>Данный датчик полностью совместим с большинством моделей автомобилей концерна Fiat/Alfa/Chrysler/Dodge/Jeep. В продажу поступает комплект (датчик и ниппель). После установки требуется произвести привязку и активацию. Данные процедуры выполняются по методу <a href="https://alltpms.ru/katalog/privyazka/privyazka-4">«Автоматическая привязка»</a> (Карточка привязки).</p> | N55: 91 | O55: /market/SRTVDO.jpg | P55: Датчик давления в шине Continental ( VDO ) 68252495AA для Fiat/Alfa/Chrysler/Dodge/Jeep | Q55: Датчик давления в шине Continental ( VDO ) 68252495AA для Fiat/Alfa/Chrysler/Dodge/Jeep | R55: Доставка от 1 шт. без предоплаты, Гарантия 2 года | S55: 0 | T55: 0 | U55: 68252495aa-2623 | V55: 5054208002319 | W55: 180 | X55: Fiat/Alfa/Chrysler/Dodge/Jeep | Y55: 433 | Z55: no | AA55: Clamp-in | AB55: 50547691, 53305555, 53386476, 53394085, 68105280AF, 68193586AA, 68193586AB, 68193586AC, 68252495AB, 68443470AA, 68252493AA, 68252493AB, 68300920AA, 68336101AA, 68394608AA, 68399030AA, 68399030AB, 68313387AB, 4018, 4016, A2C9714580280, A2C97145802, A2C9915450180, A2C99154501, S180052048Z, S180052048, S180150008, S180211003Z, TX-S026, TPS0026, ECR0270, RDE068V21, 9014-4018, 9015-4018, 1210-4018, 2210-4018, 2200-4018, 1400-4018, 1401-4018, 4040-4018, 4041-4018, 590914-4018, 590918-4018, 4018PFR, 4018PFM, 4018PVM, 4040-RDE068, 4041-RDE068, RDE068PVM, RDE068PFR, RDE068PVM, RDE068PFR | AC55: 68252495AA-VDO-1.JPG||68252495AA-VDO-2.JPG||68252495AA-VDO-3.JPG||68252495AA-VDO-4.JPG||68252495AA-VDO-5.JPG||68252495AA-VDO-6.JPG||68252495AA-VDO-7.JPG||68252495AA-VDO-8.JPG||68252495AA-VDO-9.JPG||68252495AA-VDO-10.JPG | AD55: 226||48029||247||92866||220||48026||232 | AE55: 586 | AF55: Fiat/Alfa/Chrysler/Dodge/Jeep Continental ( VDO ) 68252495AA 50547691, 53305555, 53386476, 53394085, 68105280AF, 68193586AA, 68193586AB, 68193586AC, 68252495AB, 68443470AA, 68252493AA, 68252493AB, 68300920AA, 68336101AA, 68394608AA, 68399030AA, 68399030AB, 68313387AB, 4018, 4016, A2C9714580280, A2C97145802, A2C9915450180, A2C99154501, S180052048Z, S180052048, S180150008, S180211003Z, TX-S026, TPS0026, ECR0270, RDE068V21, 9014-4018, 9015-4018, 1210-4018, 2210-4018, 2200-4018, 1400-4018, 1401-4018, 4040-4018, 4041-4018, 590914-4018, 590918-4018, 4018PFR, 4018PFM, 4018PVM, 4040-RDE068, 4041-RDE068, RDE068PVM, RDE068PFR, RDE068PVM, RDE068PFR 50547691, 53305555, 53386476, 53394085, 68105280AF, 68193586AA, 68193586AB, 68193586AC, 68252495AB, 68443470AA, 68252493AA, 68252493AB, 68300920AA, 68336101AA, 68394608AA, 68399030AA, 68399030AB, 68313387AB, 4018, 4016, A2C9714580280, A2C97145802, A2C9915450180, A2C99154501, S180052048Z, S180052048, S180150008, S180211003Z, TXS026, TPS0026, ECR0270, RDE068V21, 90144018, 90154018, 12104018, 22104018, 22004018, 14004018, 14014018, 40404018, 40414018, 5909144018, 5909184018, 4018PFR, 4018PFM, 4018PVM, 4040RDE068, 4041RDE068, RDE068PVM, RDE068PFR, RDE068PVM, RDE068PFR | AG55: Купить датчик давления в шине Continental ( VDO ) 68252495AA для Fiat/Alfa/Chrysler/Dodge/Jeep в Москве с доставкой. Цена от производителя. Большой выбор датчиков. Гарантия.
A56: 302779 | B56: 1 | C56: 8253 | D56: 20 | E56: 68252495AA | F56: =VLOOKUP(E56,Лист1!A1:A306,1,FALSE) -> 68252495AA | G56: Датчик давления в шине BH Sens ( Huf ) 68252495AA для Fiat/Alfa/Chrysler/Dodge/Jeep | H56: Покупайте датчик давления в шине BH Sens ( Huf ) 68252495AA для Fiat/Alfa/Chrysler/Dodge/Jeep по выгодным ценам | Большой выбор датчиков давления в шине | Осуществляем доставку на всей территории РФ | I56: 3250 | J56: Германия | K56: 30 | L56: dk-datchik-davlenia-v-shinah-68252495aa-541 | M56: <p>Датчик 68252495AA контроля давления в шинах. Передача данных реализована по радиоканалу. Используемая частота - 433МГц. Производит устройства компания <a href="https://alltpms.ru/proizvoditeli-sistem-tpms/beru"> BH Sens ( Huf ) </a>. Страна производства - Германия.</p><p> Датчики устанавливаются в автомобили, выпускаемые концерном Fiat/Alfa/Chrysler/Dodge/Jeep.</p><p></p><p> При условии правильной установки и эксплуатации, срок работы составит 6 лет и более. Срок варьируется в зависимости от интенсивности эксплуатации, частоты и продолжительности поездок.</p><p>Данный датчик 68252495AA сконструирован в расчете на установку в автомобили концерна Fiat/Alfa/Chrysler/Dodge/Jeep. В продажу поступают готовые комплекты. В комплект входит сам датчик и ниппель. После установки датчик необходимо активировать. Процесс выполняется с использованием методики <a href="https://alltpms.ru/katalog/privyazka/privyazka-4">«Автоматическая привязка»</a> (Карточка привязки).</p> | N56: 90 | O56: /market/HUF1410.jpg | P56: Датчик давления в шине BH Sens ( Huf ) 68252495AA для Fiat/Alfa/Chrysler/Dodge/Jeep | Q56: Датчик давления в шине BH Sens ( Huf ) 68252495AA для Fiat/Alfa/Chrysler/Dodge/Jeep | R56: Доставка от 1 шт. без предоплаты, Гарантия 2 года | S56: 0 | T56: 1 | U56: 68252495aa-541 | V56: 5054208002320 | W56: 622 | X56: Fiat/Alfa/Chrysler/Dodge/Jeep | Y56: 433 | Z56: no | AA56: Clamp-in | AB56: 50547691, 53305555, 53386476, 53394085, 68105280AF, 68193586AA, 68193586AB, 68193586AC, 68252495AB, 68443470AA, 68252493AA, 68252493AB, 68300920AA, 68336101AA, 68394608AA, 68399030AA, 68399030AB, 68313387AB, 4018, 4016, A2C9714580280, A2C97145802, A2C9915450180, A2C99154501, S180052048Z, S180052048, S180150008, S180211003Z, TX-S026, TPS0026, ECR0270, RDE068V21, 9014-4018, 9015-4018, 1210-4018, 2210-4018, 2200-4018, 1400-4018, 1401-4018, 4040-4018, 4041-4018, 590914-4018, 590918-4018, 4018PFR, 4018PFM, 4018PVM, 4040-RDE068, 4041-RDE068, RDE068PVM, RDE068PFR, RDE068PVM, RDE068PFR | AC56: HUF1400-1.JPG||HUF1400-2.JPG||HUF1400-3.JPG||HUF1400-4.JPG||HUF1400-5.JPG||HUF1400-6.JPG||HUF1400-7.JPG||HUF1400-8.JPG||HUF1400-9.JPG||HUF1400-10.JPG | AD56: 226||48029||247||92866||220||48026||232 | AE56: 586 | AG56: Покупайте датчик давления в шине BH Sens ( Huf ) 68252495AA для Fiat/Alfa/Chrysler/Dodge/Jeep по выгодным ценам | Большой выбор датчиков давления в шине | Осуществляем доставку на всей территории РФ
A57: 302787 | B57: 1 | C57: 8253 | D57: 20 | E57: 7P6998270 | F57: =VLOOKUP(E57,Лист1!A1:A306,1,FALSE) -> 7P6998270 | G57: Комплект датчиков давления в шинах для VAG/Porsche 7P6998270 Оригинал | H57: Купить по низкой цене комплект оригинальных датчиков давления в шинах для VAG/Porsche 7P6998270 с доставкой по Москве или России. | I57: 27000 | J57: Германия | K57: 120 | L57: dk-datchik-davlenia-v-shinah-7p6998270-152342342 | M57: <p>Комплект датчиков 7P6998270 контроля давления в шинах. Передача данных реализована по радиоканалу. Используемая частота - 433МГц. Для автомобилей VAG/Porsche. Страна производства - Германия.</p><p> Датчики устанавливаются в автомобили, выпускаемые концерном VAG/Porsche.</p><p></p><p> При условии правильной установки и эксплуатации, срок работы составит 6 лет и более. Срок варьируется в зависимости от интенсивности эксплуатации, частоты и продолжительности поездок.</p><p>Данный датчик 7P6998270 сконструирован в расчете на установку в автомобили концерна VAG/Porsche. В продажу поступают готовые комплекты. В комплект входит сам датчик и ниппель. После установки датчик необходимо активировать. Процесс выполняется с использованием методики <a href="https://alltpms.ru/katalog/privyazka/privyazka-4">«Автоматизированная привязка»</a> (Карточка привязки).</p> | N57: 94 | O57: /market/7P6.jpg | P57: Комплект датчиков давления в шинах для VAG/Porsche 7P6998270 Оригинал | Q57: Комплект датчиков давления в шинах для VAG/Porsche 7P6998270 Оригинал | R57: Доставка от 1 шт. без предоплаты, Гарантия 2 года | S57: 0 | T57: 0 | U57: 7p6998270-152342342 | V57: 5054208002328 | W57: 622 | X57: VAG/Porsche | Y57: 433 | Z57: yes | AA57: Clamp-in | AB57: 228887, 239298, 248887, 282189, 2000680, 95560602100, 95836166100, 99760602120, 11B0015CP, 4F0907275, 4F0907275B, 4F0907275D, 7P0907275, 7P0907275A, 7PP907275, 7PP907275B, 7PP907275D, 7PP907275F, AD43-360671-AA, CD23-360671-CA, 4009-KIT, 9014-4009-KIT, 9015-4009-KIT, 1210-4009-KIT, 2210-4009-KIT, 2200-4009-KIT, 1400-4009-KIT, 1401-4009-KIT, 4040-4009-KIT, 4041-4009-KIT, 590914-4009-KIT, 590918-4009-KIT | AC57: 7P6998270-1.JPG||7P6998270-2.JPG||7P6998270-3.JPG||7P6998270-4.JPG||7P6998270-5.JPG||7P6998270-6.JPG||7P6998270-7.JPG||7P6998270-8.JPG||7P6998270-9.JPG||7P6998270-10.JPG | AD57: 229||92867||241||244||48032 | AE57: 588 | AF57: VAG/Porsche BH Sens ( Huf ) 7P6998270 228887, 239298, 248887, 282189, 2000680, 95560602100, 95836166100, 99760602120, 11B0015CP, 4F0907275, 4F0907275B, 4F0907275D, 7P0907275, 7P0907275A, 7PP907275, 7PP907275B, 7PP907275D, 7PP907275F, AD43-360671-AA, CD23-360671-CA, 4009-KIT, 9014-4009-KIT, 9015-4009-KIT, 1210-4009-KIT, 2210-4009-KIT, 2200-4009-KIT, 1400-4009-KIT, 1401-4009-KIT, 4040-4009-KIT, 4041-4009-KIT, 590914-4009-KIT, 590918-4009-KIT 228887, 239298, 248887, 282189, 2000680, 95560602100, 95836166100, 99760602120, 11B0015CP, 4F0907275, 4F0907275B, 4F0907275D, 7P0907275, 7P0907275A, 7PP907275, 7PP907275B, 7PP907275D, 7PP907275F, AD43360671AA, CD23360671CA, 4009KIT, 90144009KIT, 90154009KIT, 12104009KIT, 22104009KIT, 22004009KIT, 14004009KIT, 14014009KIT, 40404009KIT, 40414009KIT, 5909144009KIT, 5909184009KIT Оригинал | AG57: Купить оригинальный датчик давления в шине для VAG/Porsche 7P6998270 в Москве с доставкой. Цена от производителя. Большой выбор датчиков. Гарантия.
A58: 302788 | B58: 1 | C58: 8253 | D58: 20 | E58: 7PP907275F | F58: =VLOOKUP(E58,Лист1!A1:A306,1,FALSE) -> 7PP907275F | G58: Датчик давления в шине для VAG/Porsche 7PP907275F Оригинал (Black Edition) | H58: Покупайте датчик давления в шине для VAG/Porsche 7PP907275F Оригинал (Black Edition) по выгодным ценам | Большой выбор датчиков давления в шине для VAG/Porsche | Осуществляем доставку на всей территории РФ | I58: 7250 | J58: Германия | K58: 30 | L58: dk-datchik-davlenia-v-shinah-7pp907275fb-12 | M58: <p> Каталожный номер датчика 7PP907275F. Передача данных происходит по радиоканалу, задействована частота 433МГц. Компания производитель автомобиля – VAG/Porsche. Страна - Германия.</p><p> Датчики предназначены для авто производства VAG/Porsche.</p><p></p><p>В зависимости от интенсивности эксплуатации комплекта колес срок службы устройства достигает 7 лет. Срок эксплуатации зависит от продолжительности поездок, поскольку именно во время движения автомобиля датчик расходует заряд элемента питания.</p><p> Предназначенный для установки в автомобили концерна VAG/Porsche, датчик поступает в продажу с ниппелем. Благодаря этому покупатель получает полностью комплектное устройство. Для активации датчика и привязки его к автомобилю выполняется процедура <a href="https://alltpms.ru/katalog/privyazka/privyazka-4">«Автоматизированная привязка»</a> (Карточка привязки).</p> | N58: 90 | O58: /market/7PPB.jpg | P58: Датчик давления в шине для VAG/Porsche 7PP907275F Оригинал (Black Edition) | Q58: Датчик давления в шине для VAG/Porsche 7PP907275F Оригинал (Black Edition) | R58: Доставка от 1 шт. без предоплаты, Гарантия 2 года | S58: 0 | T58: 0 | U58: 7pp907275fb-12 | V58: 5054208002329 | W58: 622 | X58: VAG/Porsche | Y58: 433 | Z58: yes | AA58: Clamp-in | AB58: 228887, 239298, 248887, 282189, 282189, 2000680, 95560602100, 95836166100, 99760602120, 11B0015CP, 11B0015CP, 4F0907275, 4F0907275B, 4F0907275D, 7P0907275, 7P0907275A, 7PP907275, 7PP907275B, 7PP907275D, AD43-360671-AA, CD23-360671-CA, 4009, 550-1911, TX-S003, TPS0003, RDE048V21, RDE011V21, 9014-4009, 9015-4009, 1210-4009, 2210-4009, 2200-4009, 1400-4009, 1401-4009, 4040-4009, 4041-4009, 590914-4009, 590918-4009, 4009PFR, 4009PFM, 4009PVM, 4040-RDE048, 4041-RDE048, RDE048PVM, RDE048PFR, RDE048PVM, RDE048PFR | AC58: 7PP907275F_B-1.JPG||7PP907275F_B-2.JPG||7PP907275F_B-3.JPG||7PP907275F_B-4.JPG||7PP907275F_B-5.JPG||7PP907275F_B-6.JPG||7PP907275F_B-7.JPG||7PP907275F_B-8.JPG||7PP907275F_B-9.JPG||7PP907275F_B-10.JPG | AD58: 229||92867||241||244||48032 | AE58: 588 | AG58: Покупайте датчик давления в шине для VAG/Porsche 7PP907275F Оригинал (Black Edition) по выгодным ценам | Большой выбор датчиков давления в шине для VAG/Porsche | Осуществляем доставку на всей территории РФ
A59: 302789 | B59: 1 | C59: 8253 | D59: 20 | E59: 7PP907275F | F59: =VLOOKUP(E59,Лист1!A1:A306,1,FALSE) -> 7PP907275F | G59: Датчик давления в шине для VAG/Porsche 7PP907275F Оригинал | H59: Покупайте датчик давления в шине для VAG/Porsche 7PP907275F Оригинал по выгодным ценам | Большой выбор датчиков давления в шине для VAG/Porsche | Осуществляем доставку на всей территории РФ | I59: 6750 | J59: Германия | K59: 30 | L59: dk-datchik-davlenia-v-shinah-7pp907275f-12 | M59: <p>Датчик давления в шинах. Компания производитель автомобиля - VAG/Porsche. Страна производства - Германия. Каталожный номер запчасти 7PP907275F. Данные передаются на частоте 433МГц. Устройство предназначено для установки на автомобили выпускаемые концерном VAG/Porsche.</p><p></p><p>Производитель гарантирует качественную работу устройства, при условии правильной эксплуатации. Срок службы датчика составляет от 7 до 8 лет.</p><p>Для упрощения процесса установки датчика на автомобили концерна VAG/Porsche, датчик уже укомплектован ниппелем. Материал изготовления ниппеля - металл.</p><p>Датчик требует привязки к авто. Процедура выполняется по методу <a href="https://alltpms.ru/katalog/privyazka/privyazka-4">«Автоматизированная привязка»</a> (Карточка привязки). </p> | N59: 91 | O59: /market/7PP.jpg | P59: Датчик давления в шине для VAG/Porsche 7PP907275F Оригинал | Q59: Датчик давления в шине для VAG/Porsche 7PP907275F Оригинал | R59: Доставка от 1 шт. без предоплаты, Гарантия 2 года | S59: 0 | T59: 0 | U59: 7pp907275f-12 | V59: 5054208002330 | W59: 622 | X59: VAG/Porsche | Y59: 433 | Z59: yes | AA59: Clamp-in | AB59: 228887, 239298, 248887, 282189, 282189, 2000680, 95560602100, 95836166100, 99760602120, 11B0015CP, 11B0015CP, 4F0907275, 4F0907275B, 4F0907275D, 7P0907275, 7P0907275A, 7PP907275, 7PP907275B, 7PP907275D, AD43-360671-AA, CD23-360671-CA, 4009, 550-1911, TX-S003, TPS0003, RDE048V21, RDE011V21, 9014-4009, 9015-4009, 1210-4009, 2210-4009, 2200-4009, 1400-4009, 1401-4009, 4040-4009, 4041-4009, 590914-4009, 590918-4009, 4009PFR, 4009PFM, 4009PVM, 4040-RDE048, 4041-RDE048, RDE048PVM, RDE048PFR, RDE048PVM, RDE048PFR | AC59: 7PP907275F-1.JPG||7PP907275F-2.JPG||7PP907275F-3.JPG||7PP907275F-4.JPG||7PP907275F-5.JPG||7PP907275F-6.JPG||7PP907275F-7.JPG||7PP907275F-8.JPG||7PP907275F-9.JPG||7PP907275F-10.JPG | AD59: 229||92867||241||244||48032 | AE59: 588 | AG59: Покупайте датчик давления в шине для VAG/Porsche 7PP907275F Оригинал по выгодным ценам | Большой выбор датчиков давления в шине для VAG/Porsche | Осуществляем доставку на всей территории РФ
A60: 302790 | B60: 1 | C60: 8253 | D60: 20 | E60: 7PP907275F | F60: =VLOOKUP(E60,Лист1!A1:A306,1,FALSE) -> 7PP907275F | G60: Датчик давления в шине BH Sens ( Huf ) 7PP907275F для VAG/Porsche (Black Edition) | H60: Покупайте датчик давления в шине BH Sens ( Huf ) 7PP907275F для VAG/Porsche (Black Edition) по выгодным ценам | Большой выбор датчиков давления в шине | Осуществляем доставку на всей территории РФ | I60: 4250 | J60: Германия | K60: 30 | L60: dk-datchik-davlenia-v-shinah-7pp907275fb-13 | M60: <p> Датчик TPMS, номер по каталогу 7PP907275F. Совместим с системами большинства марок автомобилей, производства концерна VAG/Porsche. Производитель устройства - <a href="https://alltpms.ru/proizvoditeli-sistem-tpms/beru"> BH Sens ( Huf ) </a>, страна изготовитель - Германия.</p><p></p><p>Производитель гарантирует нормальную работу устройства на протяжении всего срока службы, составляющего 7-8 лет.</p><p>Датчик специально сконструирован для использования в автомобилях концерна VAG/Porsche. Комплект поставки устройства: датчик и штуцер. После установки требуется привязка устройства к системе автомобиля. Процедура выполняется по методу <a href="https://alltpms.ru/katalog/privyazka/privyazka-4">«Автоматизированная привязка»</a> (Карточка привязки).</p> | N60: 92 | O60: /market/RDE048B.jpg | P60: Датчик давления в шине BH Sens ( Huf ) 7PP907275F для VAG/Porsche (Black Edition) | Q60: Датчик давления в шине BH Sens ( Huf ) 7PP907275F для VAG/Porsche (Black Edition) | R60: Доставка от 1 шт. без предоплаты, Гарантия 2 года | S60: 0 | T60: 0 | U60: 7pp907275fb-13 | V60: 5054208002331 | W60: 622 | X60: VAG/Porsche | Y60: 433 | Z60: no | AA60: Clamp-in | AB60: 228887, 239298, 248887, 282189, 282189, 2000680, 95560602100, 95836166100, 99760602120, 11B0015CP, 11B0015CP, 4F0907275, 4F0907275B, 4F0907275D, 7P0907275, 7P0907275A, 7PP907275, 7PP907275B, 7PP907275D, AD43-360671-AA, CD23-360671-CA, 4009, 550-1911, TX-S003, TPS0003, RDE048V21, RDE011V21, 9014-4009, 9015-4009, 1210-4009, 2210-4009, 2200-4009, 1400-4009, 1401-4009, 4040-4009, 4041-4009, 590914-4009, 590918-4009, 4009PFR, 4009PFM, 4009PVM, 4040-RDE048, 4041-RDE048, RDE048PVM, RDE048PFR, RDE048PVM, RDE048PFR | AC60: HUF4040_B-1.JPG||HUF4040_B-2.JPG||HUF4040_B-3.JPG||HUF4040_B-4.JPG||HUF4040_B-5.JPG||HUF4040_B-6.JPG||HUF4040_B-7.JPG||HUF4040_B-8.JPG||HUF4040_B-9.JPG||HUF4040_B-10.JPG | AD60: 229||92867||241||244||48032 | AE60: 588 | AG60: Покупайте датчик давления в шине BH Sens ( Huf ) 7PP907275F для VAG/Porsche (Black Edition) по выгодным ценам | Большой выбор датчиков давления в шине | Осуществляем доставку на всей территории РФ
A61: 302791 | B61: 1 | C61: 8253 | D61: 20 | E61: 7PP907275F | F61: =VLOOKUP(E61,Лист1!A1:A306,1,FALSE) -> 7PP907275F | G61: Датчик давления в шине BH Sens ( Huf ) 7PP907275F для VAG/Porsche | H61: Покупайте датчик давления в шине BH Sens ( Huf ) 7PP907275F для VAG/Porsche по выгодным ценам | Большой выбор датчиков давления в шине | Осуществляем доставку на всей территории РФ | I61: 3750 | J61: Германия | K61: 30 | L61: dk-datchik-davlenia-v-shinah-7pp907275f-13 | M61: <p>Датчик давления в шинах, номер по каталогу 7PP907275F, передает сигналы с помощью радиоканала. Рабочая частота - 433МГц. Компания производитель <a href="https://alltpms.ru/proizvoditeli-sistem-tpms/beru"> BH Sens ( Huf ) </a>. Страна производства - Германия. Устройства предназначены для установки в колеса автомобилей, выпускаемых концерном VAG/Porsche.</p><p></p><p> При условии установки на специализированных СТО, срок службы устройства составляет до 7 лет.</p><p>Конструктивные особенности данного датчика гарантируют его полную совместимость с системами авто концерна VAG/Porsche. Датчик поставляется в комплекте с ниппелем, что заметно облегчает установку и не требует покупки дополнительных деталей. Материал ниппеля - металл. После установки датчик 7PP907275F требует привязки к авто. Привязка производится по методике <a href="https://alltpms.ru/katalog/privyazka/privyazka-4">«Автоматизированная привязка»</a> (Карточка привязки).</p> | N61: 93 | O61: /market/RDE048.jpg | P61: Датчик давления в шине BH Sens ( Huf ) 7PP907275F для VAG/Porsche | Q61: Датчик давления в шине BH Sens ( Huf ) 7PP907275F для VAG/Porsche | R61: Доставка от 1 шт. без предоплаты, Гарантия 2 года | S61: 0 | T61: 0 | U61: 7pp907275f-13 | V61: 5054208002332 | W61: 622 | X61: VAG/Porsche | Y61: 433 | Z61: no | AA61: Clamp-in | AB61: 228887, 239298, 248887, 282189, 282189, 2000680, 95560602100, 95836166100, 99760602120, 11B0015CP, 11B0015CP, 4F0907275, 4F0907275B, 4F0907275D, 7P0907275, 7P0907275A, 7PP907275, 7PP907275B, 7PP907275D, AD43-360671-AA, CD23-360671-CA, 4009, 550-1911, TX-S003, TPS0003, RDE048V21, RDE011V21, 9014-4009, 9015-4009, 1210-4009, 2210-4009, 2200-4009, 1400-4009, 1401-4009, 4040-4009, 4041-4009, 590914-4009, 590918-4009, 4009PFR, 4009PFM, 4009PVM, 4040-RDE048, 4041-RDE048, RDE048PVM, RDE048PFR, RDE048PVM, RDE048PFR | AC61: HUF4040-1.JPG||HUF4040-2.JPG||HUF4040-3.JPG||HUF4040-4.JPG||HUF4040-5.JPG||HUF4040-6.JPG||HUF4040-7.JPG||HUF4040-8.JPG||HUF4040-9.JPG||HUF4040-10.JPG | AD61: 229||92867||241||244||48032 | AE61: 588 | AG61: Покупайте датчик давления в шине BH Sens ( Huf ) 7PP907275F для VAG/Porsche по выгодным ценам | Большой выбор датчиков давления в шине | Осуществляем доставку на всей территории РФ
A62: 302902 | B62: 1 | C62: 8253 | D62: 20 | E62: 5Q0907275B | F62: =VLOOKUP(E62,Лист1!A1:A306,1,FALSE) -> 5Q0907275B | G62: Датчик давления в шине для VAG/Porsche 5Q0907275B Оригинал | H62: Купить по низкой цене оригинальный датчик давления в шинах для VAG/Porsche 5Q0907275B с доставкой по Москве или России. | I62: 7000 | J62: Германия | K62: 30 | L62: dk-datchik-davlenia-v-shinah-5q0907275b-151 | M62: <p> Датчик TPMS, номер по каталогу 5Q0907275B. Совместим с системами большинства марок автомобилей, производства концерна VAG/Porsche. Производитель автомобиля - VAG/Porsche, страна изготовитель - Германия.</p><p></p><p>Производитель гарантирует нормальную работу устройства на протяжении всего срока службы, составляющего 7-8 лет.</p><p>Датчик специально сконструирован для использования в автомобилях концерна VAG/Porsche. Комплект поставки устройства: датчик и штуцер. После установки требуется привязка устройства к системе автомобиля. Процедура выполняется по методу <a href="https://alltpms.ru/katalog/privyazka/privyazka-4">«Автоматизированная привязка»</a> (Карточка привязки).</p> | N62: 97 | O62: /market/5Q0.jpg | P62: Датчик давления в шине для VAG/Porsche 5Q0907275B Оригинал | Q62: Датчик давления в шине для VAG/Porsche 5Q0907275B Оригинал | R62: Доставка от 1 шт. без предоплаты, Гарантия 2 года | S62: 0 | T62: 0 | U62: 5q0907275b-151 | V62: 5054208002444 | W62: 622 | X62: VAG/Porsche | Y62: 433 | Z62: yes | AA62: Clamp-in | AB62: 5Q0907275, 5Q0907275F, 9J1907275, 9A790727502, PAB907275, 2N0907251A, 2N0907275A, 9A7907275, 9J1907275, 9A7907275, 9J1907275PFM, 4012, 550-1918, TX-S005L/R, TPS0005L/R, ECR0030, RDE047V21, RDE018V21, 9014-4012, 9015-4012, 1210-4012, 2210-4012, 2200-4012, 1400-4012, 1401-4012, 4040-4012, 4041-4012, 590914-4012, 590918-4012, 4012PFR, 4012PFM, 4012PVM, 4040-RDE047, 4041-RDE047, RDE047PVM, RDE047PFR, RDE047PVM, RDE047PFR | AC62: 5Q0907275-1.JPG||5Q0907275-2.JPG||5Q0907275-3.JPG||5Q0907275-4.JPG||5Q0907275-5.JPG||5Q0907275-6.JPG||5Q0907275-7.JPG||5Q0907275-8.JPG||5Q0907275-9.JPG||5Q0907275-10.JPG | AD62: 229||92867||241||244||48032 | AE62: 588 | AF62: VAG/Porsche BH Sens ( Huf ) 5Q0907275B 5Q0907275, 5Q0907275F, 9J1907275, 9A790727502, PAB907275, 2N0907251A, 2N0907275A, 9A7907275, 9J1907275, 9A7907275, 9J1907275PFM, 4012, 550-1918, TX-S005L/R, TPS0005L/R, ECR0030, RDE047V21, RDE018V21, 9014-4012, 9015-4012, 1210-4012, 2210-4012, 2200-4012, 1400-4012, 1401-4012, 4040-4012, 4041-4012, 590914-4012, 590918-4012, 4012PFR, 4012PFM, 4012PVM, 4040-RDE047, 4041-RDE047, RDE047PVM, RDE047PFR, RDE047PVM, RDE047PFR 5Q0907275, 5Q0907275B, 9J1907275, 9A790727502, PAB907275, 2N0907251A, 2N0907275A, 9A7907275, 9J1907275, 9A7907275, 9J1907275PFM, 4012, 5501918, TXS005L/R, TPS0005L/R, ECR0030, RDE047V21, RDE018V21, 90144012, 90154012, 12104012, 22104012, 22004012, 14004012, 14014012, 40404012, 40414012, 5909144012, 5909184012, 4012PFR, 4012PFM, 4012PVM, 4040RDE047, 4041RDE047, RDE047PVM, RDE047PFR, RDE047PVM, RDE047PFR Оригинал | AG62: Купить оригинальный датчик давления в шине для VAG/Porsche 5Q0907275B в Москве с доставкой. Цена от производителя. Большой выбор датчиков. Гарантия.
A63: 302980 | B63: 1 | C63: 8253 | D63: 20 | E63: 13533166 | F63: =VLOOKUP(E63,Лист1!A1:A306,1,FALSE) -> 13533166 | G63: Датчик давления в шине для General Motors 13533166 Оригинал | H63: Купить по низкой цене оригинальный датчик давления в шинах для General Motors 13533166 с доставкой по Москве или России. | I63: 7500 | J63: Англия | K63: 30 | L63: dk-datchik-davlenia-v-shinah-13533166-230 | M63: <p>Датчик, номер по каталогу запчастей 13533166. Предназначен для контроля давления в шинах. Передача данных осуществляется посредством радиосигнала на частоте 433МГц. Компания производитель автомобиля - General Motors. Место производства - Англия.</p><p>Правильно установленный датчик гарантировано проработает 7 лет. В каждом конкретном случае срок службы может изменяться. Он зависит от условий эксплуатации, длительности поездок, их частоты.</p><p>Предназначенный для установки в колеса автомобилей большинства моделей концерна General Motors, датчик поставляется в комплекте с ниппелем. Покупатель получает комплектное устройство. После установки датчик 13533166 активируется, используется метод <a href="https://alltpms.ru/katalog/privyazka/privyazka-4">«Автоматическая привязка»</a> (Карточка привязки).</p> | N63: 92 | O63: /market/13533166.jpg | P63: Датчик давления в шине для General Motors 13533166 Оригинал | Q63: Датчик давления в шине для General Motors 13533166 Оригинал | R63: Доставка от 1 шт. без предоплаты, Гарантия 2 года | S63: 0 | T63: 0 | U63: 13533166-230 | V63: 5054208002540 | W63: 625 | X63: General Motors | Y63: 433 | Z63: yes | AA63: Snap-in | AB63: 13542523, 3187 | AC63: 13533166-1.JPG||13533166-2.JPG||13533166-3.JPG||13533166-4.JPG||13533166-5.JPG||13533166-6.JPG||13533166-7.JPG||13533166-8.JPG||13533166-9.JPG||13533166-10.JPG | AD63: 220||48026||232 | AE63: 586 | AF63: General Motors Schrader 13533166 Оригинал | AG63: Купить оригинальный датчик давления в шине для General Motors 13533166 в Москве с доставкой. Цена от производителя. Большой выбор датчиков. Гарантия.
A64: 302981 | B64: 1 | C64: 8253 | D64: 20 | E64: 13533166 | F64: =VLOOKUP(E64,Лист1!A1:A306,1,FALSE) -> 13533166 | G64: Датчик давления в шине BH Sens ( Huf ) 13533166 для General Motors | H64: Покупайте датчик давления в шине BH Sens ( Huf ) 13533166 для General Motors по выгодным ценам | Большой выбор датчиков давления в шине | Осуществляем доставку на всей территории РФ | I64: 3750 | J64: Германия | K64: 30 | L64: dk-datchik-davlenia-v-shinah-13533166-45 | M64: <p>Датчик давления в шинах. Компания производитель - <a href="https://alltpms.ru/proizvoditeli-sistem-tpms/beru"> BH Sens ( Huf ) </a>. Страна производства - Германия. Каталожный номер запчасти 13533166. Данные передаются на частоте 433МГц. Устройство предназначено для установки на автомобили выпускаемые концерном General Motors.</p><p></p><p>Производитель гарантирует качественную работу устройства, при условии правильной эксплуатации. Срок службы датчика составляет от 7 до 8 лет.</p><p>Для упрощения процесса установки датчика на автомобили концерна General Motors, датчик уже укомплектован ниппелем. Материал изготовления ниппеля - металл.</p><p>Датчик требует привязки к авто. Процедура выполняется по методу <a href="https://alltpms.ru/katalog/privyazka/privyazka-4">«Автоматическая привязка»</a> (Карточка привязки). </p> | N64: 93 | O64: /market/HUF4040.jpg | P64: Датчик давления в шине BH Sens ( Huf ) 13533166 для General Motors | Q64: Датчик давления в шине BH Sens ( Huf ) 13533166 для General Motors | R64: Доставка от 1 шт. без предоплаты, Гарантия 2 года | S64: 0 | T64: 0 | U64: 13533166-45 | V64: 5054208002541 | W64: 622 | X64: General Motors | Y64: 433 | Z64: no | AA64: Clamp-in | AB64: 13542523, 3187 | AC64: HUF4040-1.JPG||HUF4040-2.JPG||HUF4040-3.JPG||HUF4040-4.JPG||HUF4040-5.JPG||HUF4040-6.JPG||HUF4040-7.JPG||HUF4040-8.JPG||HUF4040-9.JPG||HUF4040-10.JPG | AD64: 220||48026||232 | AE64: 586 | AG64: Покупайте датчик давления в шине BH Sens ( Huf ) 13533166 для General Motors по выгодным ценам | Большой выбор датчиков давления в шине | Осуществляем доставку на всей территории РФ
A65: 302982 | B65: 1 | C65: 8253 | D65: 20 | E65: 13533166 | F65: =VLOOKUP(E65,Лист1!A1:A306,1,FALSE) -> 13533166 | G65: Датчик давления в шине Schrader 13533166 для General Motors | H65: Покупайте датчик давления в шине Schrader 13533166 для General Motors по выгодным ценам | Большой выбор датчиков давления в шине | Осуществляем доставку на всей территории РФ | I65: 4500 | J65: Англия | K65: 30 | L65: dk-datchik-davlenia-v-shinah-13533166-452 | M65: <p>Датчик давления в шинах. Компания производитель - <a href="https://alltpms.ru/proizvoditeli-sistem-tpms/schrader"> Schrader </a>. Страна производства - Германия. Каталожный номер запчасти 13533166. Данные передаются на частоте 433МГц. Устройство предназначено для установки на автомобили выпускаемые концерном General Motors.</p><p></p><p>Производитель гарантирует качественную работу устройства, при условии правильной эксплуатации. Срок службы датчика составляет от 7 до 8 лет.</p><p>Для упрощения процесса установки датчика на автомобили концерна General Motors, датчик уже укомплектован ниппелем. Материал изготовления ниппеля - резина.</p><p>Датчик требует привязки к авто. Процедура выполняется по методу <a href="https://alltpms.ru/katalog/privyazka/privyazka-4">«Автоматическая привязка»</a> (Карточка привязки). </p> | N65: 93 | O65: /market/SCH1210.jpg | P65: Датчик давления в шине Schrader 13533166 для General Motors | Q65: Датчик давления в шине Schrader 13533166 для General Motors | R65: Доставка от 1 шт. без предоплаты, Гарантия 2 года | S65: 0 | T65: 0 | U65: 13533166-452 | V65: 5054208002542 | W65: 625 | X65: General Motors | Y65: 433 | Z65: no | AA65: Snap-in | AB65: 13542523, 3187 | AC65: 3187-1.JPG||3187-2.JPG||3187-3.JPG||3187-4.JPG||3187-5.JPG||3187-6.JPG||3187-7.JPG||3187-8.JPG||3187-9.JPG||3187-10.JPG | AD65: 220||48026||232 | AE65: 586 | AG65: Покупайте датчик давления в шине Schrader 13533166 для General Motors по выгодным ценам | Большой выбор датчиков давления в шине | Осуществляем доставку на всей территории РФ
A66: 302996 | B66: 1 | C66: 8253 | D66: 20 | E66: 68339096AB | F66: =VLOOKUP(E66,Лист1!A1:A306,1,FALSE) -> 68339096AB | G66: Датчик давления в шине для Fiat/Alfa/Chrysler/Dodge/Jeep 68339096AB Оригинал | H66: Купить по низкой цене оригинальный датчик давления в шинах для Fiat/Alfa/Chrysler/Dodge/Jeep 68339096AB с доставкой по Москве или России. | I66: 7250 | J66: США | K66: 30 | L66: dk-datchik-davlenia-v-shinah-68339096ab-543 | M66: <p>Датчик TPMS для автомобилей производства компании Fiat/Alfa/Chrysler/Dodge/Jeep. Страна производства - США. Каталожный номер детали 68339096AB. Датчик применяется в автомобилях, производства Fiat/Alfa/Chrysler/Dodge/Jeep.</p><p></p><p> При нормальных условиях эксплуатации устройство прослужит до 8 лет.</p><p>Данный датчик, производства компании Fiat/Alfa/Chrysler/Dodge/Jeep США номер 68339096AB рассчитан на установку в колеса легковых автомобилей Fiat/Alfa/Chrysler/Dodge/Jeep. Датчик продается в комплекте со штуцером, т.е. покупатель получает полный набор деталей для установки. Материал штуцера - резина. После установки датчика необходимо осуществить его привязку к системе авто. Для этого используется метод <a href="https://alltpms.ru/katalog/privyazka/privyazka-4">«Автоматическая привязка»</a> (Карточка привязки).</p> | N66: 97 | O66: /market/096AB.jpg | P66: Датчик давления в шине для Fiat/Alfa/Chrysler/Dodge/Jeep 68339096AB Оригинал | Q66: Датчик давления в шине для Fiat/Alfa/Chrysler/Dodge/Jeep 68339096AB Оригинал | R66: Доставка от 1 шт. без предоплаты, Гарантия 2 года | S66: 0 | T66: 0 | U66: 68339096ab-543 | V66: 5054208002556 | W66: 180 | X66: Fiat/Alfa/Chrysler/Dodge/Jeep | Y66: 433 | Z66: yes | AA66: Snap-in | AB66: 2802003011180 | AC66: 68339096AB-1.JPG||68339096AB-2.JPG||68339096AB-3.JPG||68339096AB-4.JPG||68339096AB-5.JPG||68339096AB-6.JPG||68339096AB-7.JPG||68339096AB-8.JPG||68339096AB-9.JPG||68339096AB-10.JPG | AD66: 220||48026||232 | AE66: 586 | AF66: Fiat/Alfa/Chrysler/Dodge/Jeep Continental ( VDO ) 68339096AB | AG66: Купить оригинальный датчик давления в шине для Fiat/Alfa/Chrysler/Dodge/Jeep 68339096AB в Москве с доставкой. Цена от производителя. Большой выбор датчиков. Гарантия.
A67: 302997 | B67: 1 | C67: 8253 | D67: 20 | E67: 68339096AB | F67: =VLOOKUP(E67,Лист1!A1:A306,1,FALSE) -> 68339096AB | G67: Датчик давления в шине Continental ( VDO ) 68339096AB для Fiat/Alfa/Chrysler/Dodge/Jeep | H67: Купить по низкой цене датчик давления в шинах Continental ( VDO ) 68339096AB для Fiat/Alfa/Chrysler/Dodge/Jeep с доставкой по Москве или России. | I67: 4500 | J67: Франция | K67: 30 | L67: dk-datchik-davlenia-v-shinah-68339096ab-2323 | M67: <p>Датчик TPMS производства компании <a href="https://alltpms.ru/proizvoditeli-sistem-tpms/vdo"> Continental ( VDO ) </a>. Страна изготовления - Франция. Номер по каталогу 68339096AB. Датчик специально разработан для автомобилей Fiat/Alfa/Chrysler/Dodge/Jeep.</p><p></p><p>В случае правильной эксплуатации срок службы устройства может достигать 8 лет. Данный показатель варьируется в достаточно широких пределах и зависит от условий эксплуатации автомобиля.</p><p>Выпускаемый компанией <a href="https://alltpms.ru/proizvoditeli-sistem-tpms/vdo"> Continental ( VDO ) </a> Франция, датчик номер 68339096AB устанавливается на автомобили, производства Fiat/Alfa/Chrysler/Dodge/Jeep. Покупатель получает полный комплект для установки. Привязка датчика к автомобилю выполняется по методу <a href="https://alltpms.ru/katalog/privyazka/privyazka-4">«Автоматическая привязка»</a> (Карточка привязки).</p> | N67: 99 | O67: /market/096ABVDO.jpg | P67: Датчик давления в шине Continental ( VDO ) 68339096AB для Fiat/Alfa/Chrysler/Dodge/Jeep | Q67: Датчик давления в шине Continental ( VDO ) 68339096AB для Fiat/Alfa/Chrysler/Dodge/Jeep | R67: Доставка от 1 шт. без предоплаты, Гарантия 2 года | S67: 0 | T67: 0 | U67: 68339096ab-2323 | V67: 5054208002557 | W67: 180 | X67: Fiat/Alfa/Chrysler/Dodge/Jeep | Y67: 433 | Z67: no | AA67: Snap-in | AB67: 2802003011180 | AC67: 68339096AB-VDO-1.JPG||68339096AB-VDO-2.JPG||68339096AB-VDO-3.JPG||68339096AB-VDO-4.JPG||68339096AB-VDO-5.JPG||68339096AB-VDO-6.JPG||68339096AB-VDO-7.JPG||68339096AB-VDO-8.JPG||68339096AB-VDO-9.JPG||68339096AB-VDO-10.JPG | AD67: 220||48026||232 | AE67: 586 | AF67: Fiat/Alfa/Chrysler/Dodge/Jeep Continental ( VDO ) 68339096AB | AG67: Купить датчик давления в шине Continental ( VDO ) 68339096AB для Fiat/Alfa/Chrysler/Dodge/Jeep в Москве с доставкой. Цена от производителя. Большой выбор датчиков. Гарантия.
A68: 302998 | B68: 1 | C68: 8253 | D68: 20 | E68: 68339096AB | F68: =VLOOKUP(E68,Лист1!A1:A306,1,FALSE) -> 68339096AB | G68: Датчик давления в шине BH Sens ( Huf ) 68339096AB для Fiat/Alfa/Chrysler/Dodge/Jeep | H68: Покупайте датчик давления в шине BH Sens ( Huf ) 68339096AB для Fiat/Alfa/Chrysler/Dodge/Jeep по выгодным ценам | Большой выбор датчиков давления в шине | Осуществляем доставку на всей территории РФ | I68: 3250 | J68: Германия | K68: 30 | L68: dk-datchik-davlenia-v-shinah-68339096ab-541 | M68: <p>Датчик, каталожный номер 68339096AB. Передача данных производится посредством радиосигнала. Частота работы - 433МГц. Производитель – компания <a href="https://alltpms.ru/proizvoditeli-sistem-tpms/beru"> BH Sens ( Huf ) </a>. Страна-производитель - Германия.</p><p> Срок службы устройства варьируется и может достигать 7 лет. Данный показатель во многом зависит от интенсивности использования авто и условий его эксплуатации.</p><p> Конструктивные особенности датчика позволяют использовать его на большинстве марок авто производства Fiat/Alfa/Chrysler/Dodge/Jeep. Комплект поставки – датчик и ниппель. Материал ниппеля - резина. Комплект полностью готов к установке. Данный датчик, номер 68339096AB требует привязки к системе автомобиля. Для этого используется процедура <a href="https://alltpms.ru/katalog/privyazka/privyazka-4">«Автоматическая привязка»</a> (Карточка привязки).</p> | N68: 98 | O68: /market/HUF1411.jpg | P68: Датчик давления в шине BH Sens ( Huf ) 68339096AB для Fiat/Alfa/Chrysler/Dodge/Jeep | Q68: Датчик давления в шине BH Sens ( Huf ) 68339096AB для Fiat/Alfa/Chrysler/Dodge/Jeep | R68: Доставка от 1 шт. без предоплаты, Гарантия 2 года | S68: 0 | T68: 1 | U68: 68339096ab-541 | V68: 5054208002558 | W68: 622 | X68: Fiat/Alfa/Chrysler/Dodge/Jeep | Y68: 433 | Z68: no | AA68: Snap-in | AB68: 2802003011180 | AC68: HUF1401-1.JPG||HUF1401-2.JPG||HUF1401-3.JPG||HUF1401-4.JPG||HUF1401-5.JPG||HUF1401-6.JPG||HUF1401-7.JPG||HUF1401-8.JPG||HUF1401-9.JPG||HUF1401-10.JPG | AD68: 220||48026||232 | AE68: 586 | AG68: Покупайте датчик давления в шине BH Sens ( Huf ) 68339096AB для Fiat/Alfa/Chrysler/Dodge/Jeep по выгодным ценам | Большой выбор датчиков давления в шине | Осуществляем доставку на всей территории РФ
A69: 303001 | B69: 1 | C69: 8253 | D69: 20 | E69: 5Q0907275F | F69: =VLOOKUP(E69,Лист1!A1:A306,1,FALSE) -> 5Q0907275F | G69: Датчик давления в шине BH Sens ( Huf, Германия ) 5Q0907275F для VAG/Porsche (Black Edition) | H69: Покупайте датчик давления в шине BH Sens ( Huf, Германия ) 5Q0907275F для VAG/Porsche (Black Edition) по выгодным ценам | Большой выбор датчиков давления в шине | Осуществляем доставку на всей территории РФ | I69: 4250 | J69: Германия | K69: 30 | L69: dk-datchik-davlenia-v-shinah-5q0907275b-162 | M69: <p> Каталожный номер датчика 5Q0907275F. Передача данных происходит по радиоканалу, задействована частота 433МГц. Компания производитель – <a href="https://alltpms.ru/proizvoditeli-sistem-tpms/beru"> BH Sens ( Huf ) </a>. Страна - Германия.</p><p> Датчики предназначены для авто производства VAG/Porsche.</p><p></p><p>В зависимости от интенсивности эксплуатации комплекта колес срок службы устройства достигает 7 лет. Срок эксплуатации зависит от продолжительности поездок, поскольку именно во время движения автомобиля датчик расходует заряд элемента питания.</p><p> Предназначенный для установки в автомобили концерна VAG/Porsche, датчик поступает в продажу с ниппелем. Благодаря этому покупатель получает полностью комплектное устройство. Для активации датчика и привязки его к автомобилю выполняется процедура <a href="https://alltpms.ru/katalog/privyazka/privyazka-4">«Автоматизированная привязка»</a> (Карточка привязки).</p> | N69: 96 | O69: /market/RDE047V21B.jpg | P69: Датчик давления в шине BH Sens ( Huf ) 5Q0907275F для VAG/Porsche (Black Edition) | Q69: Датчик давления в шине BH Sens ( Huf ) 5Q0907275F для VAG/Porsche (Black Edition) | R69: Доставка от 1 шт. без предоплаты, Гарантия 2 года | S69: 0 | T69: 1 | U69: 5q0907275b-162 | V69: 5054208002561 | W69: 622 | X69: VAG/Porsche | Y69: 433 | Z69: no | AA69: Clamp-in | AB69: 5Q0907275, 5Q0907275B, 9J1907275, 9A790727502, PAB907275, 2N0907251A, 2N0907275A, 9A7907275, 9J1907275, 9A7907275, 9J1907275PFM, 4012, 550-1918, TX-S005L/R, TPS0005L/R, ECR0030, RDE047V21, RDE018V21, 9014-4012, 9015-4012, 1210-4012, 2210-4012, 2200-4012, 1400-4012, 1401-4012, 4040-4012, 4041-4012, 590914-4012, 590918-4012, 4012PFR, 4012PFM, 4012PVM, 4040-RDE047, 4041-RDE047, RDE047PVM, RDE047PFR, RDE047PVM, RDE047PFR | AC69: HUF4040_B-1.JPG||HUF4040_B-2.JPG||HUF4040_B-3.JPG||HUF4040_B-4.JPG||HUF4040_B-5.JPG||HUF4040_B-6.JPG||HUF4040_B-7.JPG||HUF4040_B-8.JPG||HUF4040_B-9.JPG||HUF4040_B-10.JPG | AD69: 229||92867||241||244||48032 | AE69: 588 | AG69: Покупайте датчик давления в шине BH Sens ( Huf, Германия ) 5Q0907275F для VAG/Porsche (Black Edition) по выгодным ценам | Большой выбор датчиков давления в шине | Осуществляем доставку на всей территории РФ
A70: 303002 | B70: 1 | C70: 8253 | D70: 20 | E70: 5Q0907275F | F70: =VLOOKUP(E70,Лист1!A1:A306,1,FALSE) -> 5Q0907275F | G70: Датчик давления в шине BH Sens ( Huf, Германия ) 5Q0907275F для VAG/Porsche | H70: Покупайте датчик давления в шине BH Sens ( Huf, Германия ) 5Q0907275F для VAG/Porsche по выгодным ценам | Большой выбор датчиков давления в шине | Осуществляем доставку на всей территории РФ | I70: 3750 | J70: Германия | K70: 30 | L70: dk-datchik-davlenia-v-shinah-5q0907275-162 | M70: <p>Датчик TPMS, производства компании <a href="https://alltpms.ru/proizvoditeli-sistem-tpms/beru"> BH Sens ( Huf ) </a>. Страна производства - Германия. Каталожный номер детали 5Q0907275F. Датчик применяется в автомобилях, производства VAG/Porsche.</p><p></p><p> При нормальных условиях эксплуатации устройство прослужит до 8 лет.</p><p>Данный датчик, производства компании <a href="https://alltpms.ru/proizvoditeli-sistem-tpms/beru"> BH Sens ( Huf ) </a> Германия номер 5Q0907275F рассчитан на установку в колеса легковых автомобилей VAG/Porsche. Датчик продается в комплекте со штуцером, т.е. покупатель получает полный набор деталей для установки. Материал штуцера - металл. После установки датчика необходимо осуществить его привязку к системе авто. Для этого используется метод <a href="https://alltpms.ru/katalog/privyazka/privyazka-4">«Автоматизированная привязка»</a> (Карточка привязки).</p> | N70: 98 | O70: /market/RDE047.jpg | P70: Датчик давления в шине BH Sens ( Huf ) 5Q0907275F для VAG/Porsche | Q70: Датчик давления в шине BH Sens ( Huf ) 5Q0907275F для VAG/Porsche | R70: Доставка от 1 шт. без предоплаты, Гарантия 2 года | S70: 0 | T70: 1 | U70: 5q0907275-162 | V70: 5054208002562 | W70: 622 | X70: VAG/Porsche | Y70: 433 | Z70: no | AA70: Clamp-in | AB70: 5Q0907275, 5Q0907275B, 9J1907275, 9A790727502, PAB907275, 2N0907251A, 2N0907275A, 9A7907275, 9J1907275, 9A7907275, 9J1907275PFM, 4012, 550-1918, TX-S005L/R, TPS0005L/R, ECR0030, RDE047V21, RDE018V21, 9014-4012, 9015-4012, 1210-4012, 2210-4012, 2200-4012, 1400-4012, 1401-4012, 4040-4012, 4041-4012, 590914-4012, 590918-4012, 4012PFR, 4012PFM, 4012PVM, 4040-RDE047, 4041-RDE047, RDE047PVM, RDE047PFR, RDE047PVM, RDE047PFR | AC70: HUF4040-1.JPG||HUF4040-2.JPG||HUF4040-3.JPG||HUF4040-4.JPG||HUF4040-5.JPG||HUF4040-6.JPG||HUF4040-7.JPG||HUF4040-8.JPG||HUF4040-9.JPG||HUF4040-10.JPG | AD70: 229||92867||241||244||48032 | AE70: 588 | AG70: Покупайте датчик давления в шине BH Sens ( Huf, Германия ) 5Q0907275F для VAG/Porsche по выгодным ценам | Большой выбор датчиков давления в шине | Осуществляем доставку на всей территории РФ
A71: 303030 | B71: 1 | C71: 8253 | D71: 20 | E71: 13533166 | F71: =VLOOKUP(E71,Лист1!A1:A306,1,FALSE) -> 13533166 | G71: Датчик давления в шине BH Sens ( Huf, Германия ) 13533166 для General Motors | H71: Покупайте датчик давления в шине BH Sens ( Huf ) 13533166 для General Motors по выгодным ценам | Большой выбор датчиков давления в шине | Осуществляем доставку на всей территории РФ | I71: 3250 | J71: Германия | K71: 30 | L71: dk-datchik-davlenia-v-shinah-13533166-4521 | M71: <p>Датчик давления в шинах. Компания производитель - <a href="https://alltpms.ru/proizvoditeli-sistem-tpms/beru"> BH Sens ( Huf ) </a>. Страна производства - Германия. Каталожный номер запчасти 13533166. Данные передаются на частоте 433МГц. Устройство предназначено для установки на автомобили выпускаемые концерном General Motors.</p><p></p><p>Производитель гарантирует качественную работу устройства, при условии правильной эксплуатации. Срок службы датчика составляет от 7 до 8 лет.</p><p>Для упрощения процесса установки датчика на автомобили концерна General Motors, датчик уже укомплектован ниппелем. Материал изготовления ниппеля - резина.</p><p>Датчик требует привязки к авто. Процедура выполняется по методу <a href="https://alltpms.ru/katalog/privyazka/privyazka-4">«Автоматическая привязка»</a> (Карточка привязки). </p> | N71: 93 | O71: /market/HUF1411.jpg | P71: Датчик давления в шине BH Sens ( Huf ) 13533166 для General Motors | Q71: Датчик давления в шине BH Sens ( Huf ) 13533166 для General Motors | R71: Доставка от 1 шт. без предоплаты, Гарантия 2 года | S71: 0 | T71: 0 | U71: 13533166-4521 | V71: 5054208002592 | W71: 622 | X71: General Motors | Y71: 433 | Z71: no | AA71: Snap-in | AB71: 13542523, 3187 | AC71: HUF1401-1.JPG||HUF1401-2.JPG||HUF1401-3.JPG||HUF1401-4.JPG||HUF1401-5.JPG||HUF1401-6.JPG||HUF1401-7.JPG||HUF1401-8.JPG||HUF1401-9.JPG||HUF1401-10.JPG | AD71: 220||48026||232 | AE71: 586 | AG71: Покупайте датчик давления в шине BH Sens ( Huf, Германия ) 13533166 для General Motors по выгодным ценам | Большой выбор датчиков давления в шине | Осуществляем доставку на всей территории РФ
A72: 303051 | B72: 1 | C72: 8253 | D72: 20 | E72: 51839114 | F72: =VLOOKUP(E72,Лист1!A1:A306,1,FALSE) -> 51839114 | G72: Датчик давления в шине BH Sens ( Huf, Германия ) 51839114 для Fiat/Alfa/Chrysler/Dodge/Jeep | H72: Покупайте датчик давления в шине BH Sens ( Huf, Германия ) 51839114 для Fiat/Alfa/Chrysler/Dodge/Jeep по выгодным ценам | Большой выбор датчиков давления в шине | Осуществляем доставку на всей территории РФ | I72: 3750 | J72: Германия | K72: 30 | L72: dk-datchik-davlenia-v-shinah-51839114-2365 | M72: <p>Датчик давления в шинах, номер по каталогу 51839114, передает сигналы с помощью радиоканала. Рабочая частота - 433МГц. Компания производитель <a href="https://alltpms.ru/proizvoditeli-sistem-tpms/beru"> BH Sens ( Huf ) </a>. Страна производства - Германия. Устройства предназначены для установки в колеса автомобилей, выпускаемых концерном Fiat/Alfa/Chrysler/Dodge/Jeep.</p><p></p><p> При условии установки на специализированных СТО, срок службы устройства составляет до 7 лет.</p><p>Конструктивные особенности данного датчика гарантируют его полную совместимость с системами авто концерна Fiat/Alfa/Chrysler/Dodge/Jeep. Датчик поставляется в комплекте с ниппелем, что заметно облегчает установку и не требует покупки дополнительных деталей. Материал ниппеля - металл. После установки датчик 51839114 требует привязки к авто. Привязка производится по методике <a href="https://alltpms.ru/katalog/privyazka/privyazka-4">«Автоматическая привязка»</a> (Карточка привязки).</p> | N72: 78 | O72: /market/HUF4040.jpg | P72: Датчик давления в шине BH Sens ( Huf ) 51839114 для Fiat/Alfa/Chrysler/Dodge/Jeep | Q72: Датчик давления в шине BH Sens ( Huf ) 51839114 для Fiat/Alfa/Chrysler/Dodge/Jeep | R72: Доставка от 1 шт. без предоплаты, Гарантия 2 года | S72: 0 | T72: 1 | U72: 51839114-2365 | V72: 5054208002613 | W72: 622 | X72: Fiat/Alfa/Chrysler/Dodge/Jeep | Y72: 433 | Z72: no | AA72: Clamp-in | AB72: 4054, TX-S138, TPS0138, 9014-4054, 9015-4054, 1210-4054, 2210-4054, 2200-4054, 1400-4054, 1401-4054, 4040-4054, 4041-4054, 590914-4054, 590918-4054, 4054PFR, 4054PFM, 4054PVM | AC72: HUF4040-1.JPG||HUF4040-2.JPG||HUF4040-3.JPG||HUF4040-4.JPG||HUF4040-5.JPG||HUF4040-6.JPG||HUF4040-7.JPG||HUF4040-8.JPG||HUF4040-9.JPG||HUF4040-10.JPG | AD72: 229||92867||241||244||48032 | AE72: 586 | AG72: Покупайте датчик давления в шине BH Sens ( Huf, Германия ) 51839114 для Fiat/Alfa/Chrysler/Dodge/Jeep по выгодным ценам | Большой выбор датчиков давления в шине | Осуществляем доставку на всей территории РФ
A73: 303057 | B73: 1 | C73: 8253 | D73: 20 | E73: 36106877937 | F73: =VLOOKUP(E73,Лист1!A1:A306,1,FALSE) -> 36106877937 | G73: Датчик давления в шине BH Sens ( Huf, Германия) 36106877937 для BMW | H73: Покупайте датчик давления в шине BH Sens ( Huf, Германия) 36106877937 для BMW по выгодным ценам | Большой выбор датчиков давления в шине | Осуществляем доставку на всей территории РФ | I73: 3750 | J73: Германия | K73: 30 | L73: dk-datchik-davlenia-v-shinah-36106877937-2371 | M73: <p>Датчик TPMS производства компании <a href="https://alltpms.ru/proizvoditeli-sistem-tpms/beru"> BH Sens ( Huf ) </a>. Страна изготовления - Германия. Номер по каталогу 36106877937. Датчик специально разработан для автомобилей BMW.</p><p></p><p>В случае правильной эксплуатации срок службы устройства может достигать 8 лет. Данный показатель варьируется в достаточно широких пределах и зависит от условий эксплуатации автомобиля.</p><p>Выпускаемый компанией <a href="https://alltpms.ru/proizvoditeli-sistem-tpms/beru"> BH Sens ( Huf ) </a> Германия, датчик номер 36106877937 устанавливается на автомобили, производства BMW. Покупатель получает полный комплект для установки. Привязка датчика к автомобилю выполняется по методу <a href="https://alltpms.ru/katalog/privyazka/privyazka-4">«Автоматизированная привязка»</a> (Карточка привязки).</p> | N73: 94 | O73: /market/HUF4040.jpg | P73: Датчик давления в шине BH Sens ( Huf ) 36106877937 для BMW | Q73: Датчик давления в шине BH Sens ( Huf ) 36106877937 для BMW | R73: Доставка от 1 шт. без предоплаты, Гарантия 2 года | S73: 0 | T73: 1 | U73: 36106877937-2371 | V73: 5054208002619 | W73: 622 | X73: BMW | Y73: 433 | Z73: no | AA73: Clamp-in | AB73: A0009054104, 36106872774, 36106872803, 36106876955, 36106876957, 36106876957, 36106887147, A0009052102, A0009057205, 3057, A0009058706, 28238, S180211005Z, ECR0280, RDE077V21, RDE035V21, 9014-3057, 9015-3057, 1210-3057, 2210-3057, 2200-3057, 1400-3057, 1401-3057, 4040-3057, 4041-3057, 590914-3057, 590918-3057, 1900-28238, 2901-28238, 4040-28238, 4041-28238, 1400-28238, 1401-28238, 590914-28238, 590918-28238, 3057PFR, 3057PFM, 3057PVM, 28238PVM, 28238PFR, 4040-RDE077, 4041-RDE077, RDE077PVM, RDE077PFR, RDE077PVM, RDE077PFR | AC73: HUF4040-1.JPG||HUF4040-2.JPG||HUF4040-3.JPG||HUF4040-4.JPG||HUF4040-5.JPG||HUF4040-6.JPG||HUF4040-7.JPG||HUF4040-8.JPG||HUF4040-9.JPG||HUF4040-10.JPG | AD73: 229||92867||241||244||48032 | AE73: 588 | AG73: Покупайте датчик давления в шине BH Sens ( Huf, Германия) 36106877937 для BMW по выгодным ценам | Большой выбор датчиков давления в шине | Осуществляем доставку на всей территории РФ
A74: 303058 | B74: 1 | C74: 8253 | D74: 20 | E74: 36106881890 | F74: =VLOOKUP(E74,Лист1!A1:A306,1,FALSE) -> 36106881890 | G74: Датчик давления в шине BH Sens ( Huf, Германия ) 36106881890 для BMW | H74: Покупайте датчик давления в шине BH Sens ( Huf, Германия ) 36106881890 для BMW по выгодным ценам | Большой выбор датчиков давления в шине | Осуществляем доставку на всей территории РФ | I74: 3750 | J74: Германия | K74: 30 | L74: dk-datchik-davlenia-v-shinah-36106881890-2372 | M74: <p>Датчик, номер по каталогу запчастей 36106881890. Предназначен для контроля давления в шинах. Передача данных осуществляется посредством радиосигнала на частоте 433МГц. Компания производитель датчика - <a href="https://alltpms.ru/proizvoditeli-sistem-tpms/beru"> BH Sens ( Huf ) </a>. Место производства - Германия.</p><p>Правильно установленный датчик гарантировано проработает 7 лет. В каждом конкретном случае срок службы может изменяться. Он зависит от условий эксплуатации, длительности поездок, их частоты.</p><p>Предназначенный для установки в колеса автомобилей большинства моделей концерна BMW, датчик поставляется в комплекте с ниппелем. Покупатель получает комплектное устройство. После установки датчик 36106881890 активируется, используется метод <a href="https://alltpms.ru/katalog/privyazka/privyazka-4">«Автоматизированная привязка»</a> (Карточка привязки).</p> | N74: 89 | O74: /market/HUF4040.jpg | P74: Датчик давления в шине BH Sens ( Huf ) 36106881890 для BMW | Q74: Датчик давления в шине BH Sens ( Huf ) 36106881890 для BMW | R74: Доставка от 1 шт. без предоплаты, Гарантия 2 года | S74: 0 | T74: 1 | U74: 36106881890-2372 | V74: 5054208002620 | W74: 622 | X74: BMW | Y74: 433 | Z74: no | AA74: Clamp-in | AB74: 36106855539, 36106856209, 36106858887, 36106858888, 4043, A2C9743250080, A2C97432500, A2C97432501, A2C97432502, S180052056, S180052056Z, S180211011Z, S180211001Z, ECR0050, RDE027V21, 9014-4043, 9015-4043, 1210-4043, 2210-4043, 2200-4043, 1400-4043, 1401-4043, 4040-4043, 4041-4043, 590914-4043, 590918-4043, 4043PFR, 4043PFM, 4043PVM, 4040-RDE027, 4041-RDE027, RDE027PVM, RDE027PFR, RDE027PVM, RDE027PFR | AC74: HUF4040-1.JPG||HUF4040-2.JPG||HUF4040-3.JPG||HUF4040-4.JPG||HUF4040-5.JPG||HUF4040-6.JPG||HUF4040-7.JPG||HUF4040-8.JPG||HUF4040-9.JPG||HUF4040-10.JPG | AD74: 226||48029 | AE74: 588 | AG74: Покупайте датчик давления в шине BH Sens ( Huf, Германия ) 36106881890 для BMW по выгодным ценам | Большой выбор датчиков давления в шине | Осуществляем доставку на всей территории РФ
